Workbook
Name Accessories_Extras: 'Outdoor Blinds'!$D$1348
Name Accessories_Extras: #REF!
Name Fixed_Channel_Screens_Category_Five: 'Outdoor Blinds'!$C$1160
Name Fixed_Channel_Screens_Category_Five: #REF!
Name Fixed_Channel_Screens_Category_Four: 'Outdoor Blinds'!$C$1138
Name Fixed_Channel_Screens_Category_Four: #REF!
Name Fixed_Channel_Screens_Category_One: 'Outdoor Blinds'!$C$1063
Name Fixed_Channel_Screens_Category_One: #REF!
Name Fixed_Channel_Screens_Category_Three: 'Outdoor Blinds'!$C$1113
Name Fixed_Channel_Screens_Category_Three: #REF!
Name Fixed_Channel_Screens_Category_Two: 'Outdoor Blinds'!$C$1091
Name Fixed_Channel_Screens_Category_Two: #REF!
Name Motorisation: 'Outdoor Blinds'!$H$1380
Name Motorisation: #REF!
Name Ombra_ToC: 'Outdoor Blinds'!$B$6
Name Ombra_ToC: #REF!
Name Reskin_for_Awnings_Category_Five: 'Outdoor Blinds'!$C$1303
Name Reskin_for_Awnings_Category_Five: #REF!
Name Reskin_for_Awnings_Category_Four: 'Outdoor Blinds'!$C$1276
Name Reskin_for_Awnings_Category_Four: #REF!
Name Reskin_for_Awnings_Category_One: 'Outdoor Blinds'!$C$1186
Name Reskin_for_Awnings_Category_One: #REF!
Name Reskin_for_Awnings_Category_Three: 'Outdoor Blinds'!$C$1246
Name Reskin_for_Awnings_Category_Three: #REF!
Name Reskin_for_Awnings_Category_Two: 'Outdoor Blinds'!$C$1219
Name Reskin_for_Awnings_Category_Two: #REF!
Name Sail_Track_Screens_Category_Five: 'Outdoor Blinds'!$C$1048
Name Sail_Track_Screens_Category_Five: #REF!
Name Sail_Track_Screens_Category_Four: 'Outdoor Blinds'!$C$1016
Name Sail_Track_Screens_Category_Four: #REF!
Name Sail_Track_Screens_Category_One: 'Outdoor Blinds'!$C$944
Name Sail_Track_Screens_Category_One: #REF!
Name Sail_Track_Screens_Category_Three: 'Outdoor Blinds'!$C$991
Name Sail_Track_Screens_Category_Three: #REF!
Name Sail_Track_Screens_Category_Two: 'Outdoor Blinds'!$C$969
Name Sail_Track_Screens_Category_Two: #REF!
Name Straight_Drop_Awnings_Category_Five: 'Outdoor Blinds'!$C$547
Name Straight_Drop_Awnings_Category_Five: #REF!
Name Straight_Drop_Awnings_Category_Four: 'Outdoor Blinds'!$C$516
Name Straight_Drop_Awnings_Category_Four: #REF!
Name Straight_Drop_Awnings_Category_One: 'Outdoor Blinds'!$C$414
Name Straight_Drop_Awnings_Category_One: #REF!
Name Straight_Drop_Awnings_Category_Three: 'Outdoor Blinds'!$C$482
Name Straight_Drop_Awnings_Category_Three: #REF!
Name Straight_Drop_Awnings_Category_Two: 'Outdoor Blinds'!$C$451
Name Straight_Drop_Awnings_Category_Two: #REF!
Name Wire_Guide_Awnings_Category_Five: 'Outdoor Blinds'!$C$381
Name Wire_Guide_Awnings_Category_Five: #REF!
Name Wire_Guide_Awnings_Category_Four: 'Outdoor Blinds'!$C$350
Name Wire_Guide_Awnings_Category_Four: #REF!
Name Wire_Guide_Awnings_Category_One: 'Outdoor Blinds'!$C$248
Name Wire_Guide_Awnings_Category_One: #REF!
Name Wire_Guide_Awnings_Category_Three: 'Outdoor Blinds'!$C$316
Name Wire_Guide_Awnings_Category_Three: #REF!
Name Wire_Guide_Awnings_Category_Two: 'Outdoor Blinds'!$C$285
Name Wire_Guide_Awnings_Category_Two: #REF!
Name Wire_Guide_Extreme_Awnings_Category_Five: 'Outdoor Blinds'!$C$908
Name Wire_Guide_Extreme_Awnings_Category_Five: #REF!
Name Wire_Guide_Extreme_Awnings_Category_Four: 'Outdoor Blinds'!$C$874
Name Wire_Guide_Extreme_Awnings_Category_Four: #REF!

Sheet Cover
B21: Product Category Price List
B29: **All downloaded Pricelists can be found on separate sheets in the footer of this document**
B55: Luxe Blinds Shutters Awnings
L58: As of
I59: =TODAY() -> 46113

Sheet Bayview
B2: Plantation Shutters | F2: As of | G2: =Cover!I59 -> 46113
A3: Bayview Collection | E3: Luxe Blinds Shutters Awnings
A5: Basswood
A6: Knoxcote solid paint | F6: 240
A7: Knoxcote stained | F7: 276
A8: Ardenwood
A9: Select paint | F9: 220
A10: ThermoPoly | L10: 10
A11: Knoxcote paint | F11: 240
A12: Veilcote paint | F12: =F13+L10 -> 212
A13: Select paint | F13: 202
A14: Thermotec
A15: Knoxcote paint | F15: 240
A16: Price includes: framing*, hinges and magnets if required
A17: NOTE: Minimum charge 1m² per item
A19: Additional Charges
A20: Custom Colour | F20: $300 /colour
A21: Raked Shutters (uneven sides) | F21: $315 /item
A22: Shaped Shutter | F22: $420 /item
A23: French Door Cut Out | F23: $275 /cut out
A24: Bay & Corner Window | F24: $18 /m²
A25: Internal Tilt | F25: $15 /m²
A26: Flat Stile – 90mm Flat Stile | F26: $18 /m²
A27: Stainless Steel Hinges | F27: $18 /m²
A28: Fly Screen Build Out | F28: $18 /m²
A29: Frame Build Outs - Small (<20mm) | F29: $18 /m²
A30: Frame Build Outs - Large (>20mm) | F30: $28 /m²
A31: Frame Cut Out | F31: $18 /cutout
... A38: Extra Blades | F38: $18 /blade
A39: Sliding & Bifold Tracking System
A40: Above prices include: hardware, head bAbove prices include: hardware, head board, side boards, top and bottom track (even if some items are not needed).oard, side boards, top and bottom track (even if some items are not needed).
A41: Single Track Sliding or Bifold | F41: $165 /LM - Min 2/LM
A42: Double Track Sliding | F42: $240 /LM - Min 2/LM
A43: Triple Track Sliding | F43: $240 /LM - Min 2/LM
A44: Sliding & Bifold Tracking System
A45: Joinery Size | D45: Painted | F45: Stained
A46: Joinery - Size <20x20 | D46: $10 /LM | F46: $15 /LM
A47: Joinery - Size <30x30 | D47: $12 /LM | F47: $17 /LM
A48: Joinery - Size <40x40 | D48: $15 /LM | F48: $19 /LM
A49: Joinery - Size <50x50 | D49: $19 /LM | F49: $24 /LM
A50: Joinery - Size <60x60 | D50: $21 /LM | F50: $26 /LM
A52: Prices do not include any applicable shipping/handling fees.
A53: All prices are subject to 10% GST. Prices subject to change without notice. All prices subject to CW Systems’ General Terms & Conditions.

Sheet Bayview S2
B2: Plantation Shutters | F2: As of | G2: =Cover!I59 -> 46113
A3: Bayview II Collection | E3: Luxe Blinds Shutters Awnings
A5: Basswood
A6: Knoxcote - Solid Paint | F6: 247
A7: Knoxcote - Stained | F7: 283
A8: Ardenwood
A9: Knoxcote - Solid Paint | F9: 236
A10: Knoxcote - Brushed Finish | F10: 273
A11: Select paint | F11: 220
A12: ThermoPoly
A13: Knoxcote - Solid Paint | F13: 247
A14: Select paint | F14: 200
A15: Price includes: framing*, hinges and magnets if required
A16: NOTE: Minimum charge 1m² per item
A17: Additional Charges
A18: Custom Colour | F18: 300
A19: Shaped Shutter (all shapes) - Min 1 sqm | F19: 130
A20: French Door Cut Out | F20: 275
A21: Bay & Corner Window | F21: 21
A22: Internal Tilt | F22: 24
A23: Flat Stile – 90mm Flat Stile | F23: 21
A24: 15mm Thick Blades (Basswood) | F24: 28
A25: Stainless Steel Hinges/Hidden Hinge | F25: 18
A26: Fly Screen Build Out | F26: 18
A27: Frame Build Outs - Small (<20mm) | F27: 18
A28: Frame Build Outs - Large (>20mm) | F28: 26
A29: Frame Cut Out | F29: 18
... A36: Solid Panels | F36: 15
A37: Sliding & Bifold Tracking System
A38: Above prices include: hardware, head bAbove prices include: hardware, head board, side boards, top and bottom track (even if some items are not needed).oard, side boards, top and bottom track (even if some items are not needed).
A39: Single Track Sliding or Bifold | F39: $165 /LM - Min 2/LM
A40: Double Track Sliding | F40: $240 /LM - Min 2/LM
A41: Triple Track Sliding | F41: $300 /LM - Min 2/LM
A42: Sliding & Bifold Tracking System
A43: Joinery Size | D43: Painted | F43: Stained
A44: Joinery - Size <20x20 | D44: $10 /LM | F44: $15 /LM
A45: Joinery - Size <30x30 | D45: $13 /LM | F45: $17 /LM
A46: Joinery - Size <40x40 | D46: $15 /LM | F46: $19 /LM
A47: Joinery - Size <50x50 | D47: $19 /LM | F47: $24 /LM
A48: Joinery - Size <60x60 | D48: $21 /LM | F48: $26 /LM
A50: Prices do not include any applicable shipping/handling fees.
A52: All prices are subject to 10% GST. Prices subject to change without notice. All prices subject to CW Systems’ General Terms & Conditions.

Sheet Forte
B2: Plantation Shutters | F2: As of | G2: =Cover!I59 -> 46113
A3: Forte Collection | E3: Luxe Blinds Shutters Awnings
A5: ThermoPoly
A6: Veilcote paint | F6: =J6+K6 -> 194 | J6: 184 | K6: 10
A7: Select paint | F7: 184
A8: Price includes: framing*, hinges and magnets if required
A9: NOTE: Minimum charge 1m² per item
A10: Additional Charges
A11: Raked Shutters (uneven sides) | F11: $315 /item
A12: Shaped Shutter | F12: $420 /item
A13: French Door Cut Out | F13: $275 /cut out
A14: Bay & Corner Window | F14: $18 /m²
A15: Internal Tilt | F15: $15 /m²
A16: Stainless Steel Hinges | F16: $18 /m²
A17: Fly Screen Build Out | F17: $18 /m²
A18: Frame Build Outs - Small (<20mm) | F18: $18 /m²
A19: Frame Build Outs - Large (>20mm) | F19: $28 /m²
A20: Frame Cut Out | F20: $18 /cutout
A21: Tier on Tier | F21: $28 /m²
A22: Star Key Lock | F22: $45 each
A23: Extra Blades | F23: $18 /blade
A24: Sliding & Bifold Tracking System
A25: Above prices include: hardware, head bAbove prices include: hardware, head board, side boards, top and bottom track (even if some items are not needed).oard, side boards, top and bottom track (even if some items are not needed).
A26: Single Track Sliding or Bifold | F26: $165 /LM - Min 2/LM
A27: Double Track Sliding | F27: $240 /LM - Min 2/LM
A28: Triple Track Sliding | F28: $240 /LM - Min 2/LM
A29: Joinery
A30: Joinery Size | F30: Painted
A31: Joinery - Size <20x20 | F31: $10 /LM
A32: Joinery - Size <30x30 | F32: $12 /LM
A33: Joinery - Size <40x40 | F33: $15 /LM
A34: Joinery - Size <50x50 | F34: $19 /LM
A35: Joinery - Size <60x60 | F35: $21 /LM
A36: Prices do not include any applicable shipping/handling fees.
A38: All prices are subject to 10% GST. Prices subject to change without notice. All prices subject to CW Systems’ General Terms & Conditions.

Sheet Oasis
B2: Plantation Shutters | F2: As of | G2: =Cover!I59 -> 46113
A3: Oasis Collection | E3: Luxe Blinds Shutters Awnings
A5: ThermoPoly (Price includes: framing*, hinges and magnets if required)
A6: Knoxcote paint | F6: $202/m²
A7: NOTE: Minimum charge 1m² per item
A8: Additional Charges
A9: Bay & Corner Window | F9: $12 /m²
A10: Shaped Shutters | F10: $200 /m²
A11: French Door Cut Out | F11: $375 /item
A12: Custom Colour | F12: $75 /Sqm - min 5sqm
A13: Stainless Steel Hinges | F13: $24 /m²
A14: Frame Build out | F14: $18 /m²
A15: Frame Cut Out | F15: $18 /cut out
A16: Tier on Tier | F16: $24 /m²
A17: Large Z-Frame Surcharge - Large Bullnose Z-Frame - Deluxe Z-Frame - Elegant Z-Frame - Deco Z-Frame - Flat Z-Frame | F17: $25 /m²
A18: Face Fit L-Frame Surcharge - 72mm Face Fit L-Frame - Deco Face Fit L-Frame | F18: $15 /m²
A19: Flush Bolt | F19: $12 /each
A20: Extra Blades | F20: $19 /blade
A21: Standard Joinery
A22: Joinery - 17.1 x 17.1mm | F22: $10 /LM
A23: Joinery - 40 x 38mm | F23: $13 /LM
A24: Joinery - 53.8 x 38.1mm | F24: $18 /LM
A25: Custom Joinery
A26: Joinery < 20x20 | F26: $11.5 /LM
A27: Joinery < 30x30 | F27: $13.5 /LM
A28: Joinery < 40x40 | F28: $17 /LM
A29: Joinery < 50x50 | F29: $23 /LM
A30: Joinery < 60x60 | F30: $30 /LM
A31: Tracking
A32: Single Track Bi-Fold/Sliding | F32: $165 /LM - min 2 LM
A33: Double Track Sliding | F33: $240 /LM - min 2 LM
A34: Triple Track Sliding | F34: $300 /LM - min 2 LM
A35: Prices do not include any applicable shipping/handling fees.
A36: All prices are subject to 10% GST. Prices subject to change without notice. All prices subject to CW Systems’ General Terms & Conditions.

Sheet Imported Alum.
B2: Plantation Shutters | F2: As of | G2: =Cover!I59 -> 46113
A3: Vueline Collection | E3: Luxe Blinds Shutters Awnings
A5: ForgeCote Standard panels with 90mm & 115mm Blades
A6: Panels Only | E6: 287 | G6: /m² *
A7: Fixed in U-Channel (inc. U-channels, H-Section, side channels, angles) | E7: 308 | G7: /m² *
A8: Hinged in Frame | E8: 330 | G8: /m² *
B9: Surcharge: 63mm Blade | E9: 57 | G9: /m²
B10: Surcharge: 150mm Blade | E10: 67 | G10: /m²
A11: *Minimum 1 m² / Item
A12: Fixed Blade Shutters
A13: ForgeCote Fixed Blades with 50x3mm Flatbar stiles
A14: Standard panels (90mm Blades) | E14: 270 | G14: /m² *
B15: Surcharge: 63mm Blade | E15: 67 | G15: /m²
A16: Fixed Blades with 100x3mm Flatbar stiles
A17: Standard panels (115mm Blades) | E17: =E14+AC17 -> 270 | G17: /m² * | AA17: 67
B18: Surcharge: 150mm Blade | E18: 88 | G18: /m² *
A19: Fixed Blade w/ Box Section Stiles
A20: Standard Panels (90mm Blades) | E20: 316 | G20: /m² *
A21: Standard Panels (115mm Blades) | E21: 386 | G21: /m² *
A22: *Minimum 1 m² / Item
A23: Fixed Blade Sunhoods
A24: Sunhoods with 50mm Support Beams
A25: Sunhood panels (90mm Blades) | E25: 270 | G25: /m² *
A26: 50mm Support Beams (Include Wall Mount) | E26: 42 | G26: /Lm
A27: *Minimum 1 m² / Item
A28: Vertical Louvres
A29: Vertical Louvres w/ Top & Bottom 100x50mm Stiles
A30: Operable Vertical Louvres - 150mm | E30: 588 | G30: /m² *
A31: Fixed Vertical Louvres - 150mm | E31: 537 | G31: /m² *
A32: *Minimum 1 m² / Item
A33: Colour Surcharges
A34: Custom & Woodgrain Colours | E34: $75/sqm - Minimum 5/sqm
A35: Prices do not include any applicable shipping/handling fees.
A36: All prices are subject to 10% GST. Prices subject to change without notice. All prices subject to CW Systems’ General Terms & Conditions.
A38: Locks & Bolts
A39: Flush Bolts | E39: $42 each
A40: Door Handle Lock | E40: $95 each
A41: Dead Lock | E41: $95 each
A42: Blade Lock | E42: $27 each
A43: Mounting Brackets
A44: T-Mounting Brackets (for 50mm Posts) | E44: $32 each
A45: Corner Stakes Fitted (for 50mm Posts) | E45: $13 each
A46: Concealed Mounting U-Bracket (for 50mm Posts) | E46: $13 each
A47: Specialty Options
A48: Raked Panels | E48: $105 /m² (minium 2m² per item)
A49: Fly Screen Build Out | E49: $37 /m² (minium 1m² per item)
A50: L-Frame w/ 25mm Build Out | E50: $32 /m² (minium 1m² per item)
A51: Tracking
A52: Prices includes Tracking & Componentry ONLY - does NOT include any framing or pelmets
A53: Bi-Fold Tracking - includes all hinges & hardware | E53: $110 /LM
A54: Single Track Sliding | E54: $95 /LM
A55: Double Track Sliding | E55: $126 /LM
A56: Triple Track Sliding | E56: $158 /LM
A57: L-Angles
A58: L-angle 25x15x2mm | E58: $5 /LM
A59: L-angle 20x20x2mm | E59: $5 /LM
A60: L-angle 40x20x2mm | E60: $6 /LM
A61: L-angle 50x25x1.5mm | E61: $7 /LM
A62: L-angle 70x25x1.5mm | E62: $8 /LM
A63: L-angle 60x40x3mm | E63: $13 /LM
A64: L-angle 100x50x3mm | E64: $20 /LM
A65: Box Sections
A66: Box Section - 38x25x2mm | E66: $12 /LM
A67: Box Section - 50x50x3mm | E67: $24 /LM
A68: Box Section - 100 x 50mm | E68: $41 /LM
A69: U-Channels
A70: Top U-Channel | E70: $11 /LM
A71: Bottom U-Channel | E71: $9 /LM
A72: Side U-Channel | E72: $9 /LM
A73: U-Channel 45.6 x 38 x 2.9 | E73: $18 /LM
A74: H-Section | E74: $11 /LM
A75: Prices do not include any applicable shipping/handling fees.
A76: All prices are subject to 10% GST. Prices subject to change without notice. All prices subject to CW Systems’ General Terms & Conditions.

Sheet Local Poly
B2: Plantation Shutters | F2: As of | G2: =Cover!I59 -> 46113
A3: Local Made Poly Shutters | E3: Luxe Blinds Shutters Awnings
A5: Local Made Poly Shutter | E5: 245 | G5: /m²*
D6: *Min 1m² /item
A7: Additional Charges
A8: Bay & Corner Window | F8: $22 /m²
A9: Tier on Tier Surchage | F9: $30 /m²
A10: Frame Buildout | F10: $20 /m²
A11: • All Panels wraped in bubble wrap and have plastic coating on blades and stiles. This is suitable for pick-up or delivery with our in house logistics. If you are outside this area please ask for Extra Packaging.
A12: • Price includes Framing, Hinges & Magnets
A13: Lead Times
A14: • 2-3 Week Lead times
A15: Specifications
A16: Max Panel Width | E16: 800mm
A17: Max Panel Height | E17: 2400mm
A18: Mid rail required for panels over height | E18: 1500mm
A19: Clearview max length | E19: 1200mm
A20: Warranty | E20: 20 Years Material / 5 Years Paint
A21: Options
A22: Stiles | D22: 51mm Beaded - Square & D-Mould
A23: Blades | D23: 89mm Blade ( Aluminium Insert )
A24: Shutter Types | D24: Hinged, Fixed or Panel only
A25: Colours
A26: Frames
A29: Prices do not include any applicable shipping/handling fees.
A30: All prices are subject to 10% GST. Prices subject to change without notice. All prices subject to CW Systems’ General Terms & Conditions.

Sheet Outdoor Blinds
D2: Outdoor Blinds | X2: As of | Y2: =Cover!I59 -> 46113
C3: Ombra Collection | W3: Luxe Blinds Shutters Awnings
AE5: Awning Discount | AF5: -35
B6: Table of Contents
C7: Zipscreen System 78 (Standard ) | O7: Page 2
C8: Wire Guide System 78 (Standard) | O8: Page 5
C9: Straight Drop Blind System 78 (Standard) | O9: Page 8
C10: Zipscreen System 110 (Extreme) | O10: Page 11
C11: Wireguide System 110 (Extreme) | O11: Page 14
C12: Sail Track Fixed Screens | O12: Page 17
C13: Channel Fixed Screens | O13: Page 20
C14: Reskin / Skin Only | O14: Page 23
C15: Assessories & Motorisation | O15: Page 26
B18: Fabric Categories
C20: Fabric Category 1
C21: Fabric Range Name | I21: Brand | O21: Fabric Type | U21: Fabric Width
C22: Ombra 6% Fabric | I22: Cotewood | O22: 2 x 2 PVC Mesh | U22: 3200 mm
C23: Skyline 94 | I23: Ricky Richards | O23: 2 x 2 PVC Mesh | U23: 3200 mm
C24: Fabric Category 2
C25: Fabric Range Name | I25: Brand | O25: Fabric Type | U25: Fabric Width
C26: Ombra 1% Fabric | I26: Cotewood | O26: 2 x 2 PVC Mesh | U26: 3200 mm
C27: Skyline 99 | I27: Ricky Richards | O27: 2 x 2 PVC Mesh | U27: 3200 mm
C28: Mode 95 | I28: Outlook - Ricky Richards | O28: 2 x 2 PVC Mesh | U28: 3200 mm
C29: Mode Designs 95 | I29: Outlook - Ricky Richards | O29: 2 x 2 PVC Mesh | U29: 3000 mm
C30: Vistaweave 95 | I30: Vistaweave - Nolans | O30: 2 x 2 PVC Mesh | U30: 3200 mm
C31: Vistaweave Stripe 95 | I31: Vistaweave - Nolans | O31: 2 x 2 PVC Mesh | U31: 3000 mm
C32: Dayscreen 5% | I32: Shaw Fabrics | O32: 2 x 2 PVC Mesh | U32: 3200 mm
C33: Visiontex View | I33: Visiontex - HVG | U33: 3200 mm
C34: Visiontex Plus | I34: Visiontex - HVG | U34: 3200 mm
C35: Fabric Category 3
C36: Fabric Range Name | I36: Brand | O36: Fabric Type | U36: Fabric Width
C37: Mode Textures | I37: Outlook - Ricky Richards | O37: 2 x 2 PVC Mesh | U37: 3200 mm
C38: Dayscreen 1% | I38: Shaw Fabrics
C39: Visiontex Ultra | I39: Visiontex - HVG
C40: Visiontex Extreme | I40: Visiontex - HVG
C41: Fabric Category 4
C42: Fabric Range Name | I42: Brand | O42: Fabric Type | U42: Fabric Width
C43: Mode Privacy 99% | I43: Outlook - Ricky Richards | U43: 3200 mm
C44: Mode Zero | I44: Outlook - Ricky Richards
C45: Vistaweave 99% | I45: Vistaweave - Nolans
C46: Vistaweave Max | I46: Vistaweave - Nolans
C47: Visiontex Perform | I47: Visiontex - HVG
C48: Visiontex Glisse | I48: Visiontex - HVG
C49: Fabric Category 5
C50: Fabric Range Name | I50: Brand | O50: Fabric Type | U50: Fabric Width
C51: Clear PVC | I51: Achilles | O51: 1mm Clear PVC | U51: 1250mm
C52: Acrylic Orchestra | I52: Dickson Fabric | O52: Acrylic
C53: Acrylic Infinity | I53: Dickson Fabric | O53: Acrylic
C54: Acrylic Max | I54: Dickson Fabric | O54: Acrylic
X55: Back to Table of Contents
C61: Zip Guide Awnings Category One
C62: Width
B63: Height | D63: 1400 | E63: 1600 | F63: 1800 | G63: 2000 | H63: 2200 | I63: 2400 | J63: 2600 | K63: 2800 | L63: 3000 | M63: 3200 | N63: 3400 | O63: 3600 | P63: 3800 | Q63: 4000 | R63: 4200 | S63: 4400 | T63: 4600 | U63: 4800 | V63: 5000 | W63: 5200 | X63: 5400 | Y63: 5600 | Z63: 5800 | AH63: 1400 | AI63: 1600 | AJ63: 1800 | AK63: 2000 | AL63: 2200 | AM63: 2400 | AN63: 2600 | AO63: 2800 | AP63: 3000 | AQ63: 3200 | AR63: 3400 | AS63: 3600 | AT63: 3800 | AU63: 4000 | AV63: 4200 | AW63: 4400 | AX63: 4600 | AY63: 4800 | AZ63: 5000 | BA63: 5200 | BB63: 5400 | BC63: 5600 | BD63: 5800
C64: 1400 | D64: =AH64*(1+$AF$5/100) -> 433.55 | E64: =AI64*(1+$AF$5/100) -> 438.1 | F64: =AJ64*(1+$AF$5/100) -> 492.05 | G64: =AK64*(1+$AF$5/100) -> 497.25 | H64: =AL64*(1+$AF$5/100) -> 517.4 | I64: =AM64*(1+$AF$5/100) -> 544.7 | J64: =AN64*(1+$AF$5/100) -> 549.9 | K64: =AO64*(1+$AF$5/100) -> 554.45 | ... Z64: =BD64*(1+$AF$5/100) -> 1028.95 | AG64: 1400 | AH64: 667 | AI64: 674 | AJ64: 757 | AK64: 765 | AL64: 796 | AM64: 838 | AN64: 846 | AO64: 853 | AP64: 907 | AQ64: 1070 | AR64: 1090 | AS64: 1110 | AT64: 1129 | AU64: 1149 | AV64: 1193 | AW64: 1345 | AX64: 1366 | AY64: 1386 | AZ64: 1406 | BA64: 1519 | BB64: 1540 | BC64: 1561 | BD64: 1583
C65: 1600 | D65: =AH65*(1+$AF$5/100) -> 436.15 | E65: =AI65*(1+$AF$5/100) -> 448.5 | F65: =AJ65*(1+$AF$5/100) -> 502.45 | G65: =AK65*(1+$AF$5/100) -> 507.65 | H65: =AL65*(1+$AF$5/100) -> 527.8 | I65: =AM65*(1+$AF$5/100) -> 555.1 | J65: =AN65*(1+$AF$5/100) -> 560.3 | K65: =AO65*(1+$AF$5/100) -> 565.5 | ... Z65: =BD65*(1+$AF$5/100) -> 1031.55 | AG65: 1600 | AH65: 671 | AI65: 690 | AJ65: 773 | AK65: 781 | AL65: 812 | AM65: 854 | AN65: 862 | AO65: 870 | AP65: 923 | AQ65: 1074 | AR65: 1094 | AS65: 1114 | AT65: 1134 | AU65: 1154 | AV65: 1197 | AW65: 1350 | AX65: 1370 | AY65: 1390 | AZ65: 1411 | BA65: 1523 | BB65: 1545 | BC65: 1566 | BD65: 1587
C66: 1800 | D66: =AH66*(1+$AF$5/100) -> 439.4 | E66: =AI66*(1+$AF$5/100) -> 451.75 | F66: =AJ66*(1+$AF$5/100) -> 512.85 | G66: =AK66*(1+$AF$5/100) -> 539.5 | H66: =AL66*(1+$AF$5/100) -> 560.95 | I66: =AM66*(1+$AF$5/100) -> 588.25 | J66: =AN66*(1+$AF$5/100) -> 594.1 | K66: =AO66*(1+$AF$5/100) -> 599.3 | ... Z66: =BD66*(1+$AF$5/100) -> 1136.2 | AG66: 1800 | AH66: 676 | AI66: 695 | AJ66: 789 | AK66: 830 | AL66: 863 | AM66: 905 | AN66: 914 | AO66: 922 | AP66: 977 | AQ66: 1122 | AR66: 1142 | AS66: 1186 | AT66: 1207 | AU66: 1228 | AV66: 1343 | AW66: 1487 | AX66: 1510 | AY66: 1532 | AZ66: 1554 | BA66: 1678 | BB66: 1701 | BC66: 1724 | BD66: 1748
C67: 2000 | D67: =AH67*(1+$AF$5/100) -> 451.1 | E67: =AI67*(1+$AF$5/100) -> 464.1 | F67: =AJ67*(1+$AF$5/100) -> 536.9 | G67: =AK67*(1+$AF$5/100) -> 560.95 | H67: =AL67*(1+$AF$5/100) -> 583.05 | I67: =AM67*(1+$AF$5/100) -> 599.95 | J67: =AN67*(1+$AF$5/100) -> 605.15 | K67: =AO67*(1+$AF$5/100) -> 610.35 | ... Z67: =BD67*(1+$AF$5/100) -> 1139.45 | AG67: 2000 | AH67: 694 | AI67: 714 | AJ67: 826 | AK67: 863 | AL67: 897 | AM67: 923 | AN67: 931 | AO67: 939 | AP67: 995 | AQ67: 1126 | AR67: 1147 | AS67: 1213 | AT67: 1234 | AU67: 1256 | AV67: 1348 | AW67: 1492 | AX67: 1515 | AY67: 1537 | AZ67: 1559 | BA67: 1683 | BB67: 1706 | BC67: 1729 | BD67: 1753
C68: 2200 | D68: =AH68*(1+$AF$5/100) -> 463.45 | E68: =AI68*(1+$AF$5/100) -> 476.45 | F68: =AJ68*(1+$AF$5/100) -> 561.6 | G68: =AK68*(1+$AF$5/100) -> 575.25 | H68: =AL68*(1+$AF$5/100) -> 605.15 | I68: =AM68*(1+$AF$5/100) -> 622.7 | J68: =AN68*(1+$AF$5/100) -> 627.9 | K68: =AO68*(1+$AF$5/100) -> 633.75 | ... Z68: =BD68*(1+$AF$5/100) -> 1142.7 | AG68: 2200 | AH68: 713 | AI68: 733 | AJ68: 864 | AK68: 885 | AL68: 931 | AM68: 958 | AN68: 966 | AO68: 975 | AP68: 1031 | AQ68: 1153 | AR68: 1174 | AS68: 1218 | AT68: 1239 | AU68: 1261 | AV68: 1354 | AW68: 1497 | AX68: 1520 | AY68: 1542 | AZ68: 1564 | BA68: 1688 | BB68: 1711 | BC68: 1734 | BD68: 1758
C69: 2400 | D69: =AH69*(1+$AF$5/100) -> 503.75 | E69: =AI69*(1+$AF$5/100) -> 517.4 | F69: =AJ69*(1+$AF$5/100) -> 586.3 | G69: =AK69*(1+$AF$5/100) -> 577.85 | H69: =AL69*(1+$AF$5/100) -> 608.4 | I69: =AM69*(1+$AF$5/100) -> 633.75 | J69: =AN69*(1+$AF$5/100) -> 639.6 | K69: =AO69*(1+$AF$5/100) -> 644.8 | ... Z69: =BD69*(1+$AF$5/100) -> 1145.95 | AG69: 2400 | AH69: 775 | AI69: 796 | AJ69: 902 | AK69: 889 | AL69: 936 | AM69: 975 | AN69: 984 | AO69: 992 | AP69: 1049 | AQ69: 1158 | AR69: 1179 | AS69: 1223 | AT69: 1244 | AU69: 1266 | AV69: 1359 | AW69: 1502 | AX69: 1525 | AY69: 1547 | AZ69: 1570 | BA69: 1693 | BB69: 1716 | BC69: 1740 | BD69: 1763
C70: 2600 | D70: =AH70*(1+$AF$5/100) -> 519.35 | E70: =AI70*(1+$AF$5/100) -> 533.65 | F70: =AJ70*(1+$AF$5/100) -> 592.8 | G70: =AK70*(1+$AF$5/100) -> 584.35 | H70: =AL70*(1+$AF$5/100) -> 614.9 | I70: =AM70*(1+$AF$5/100) -> 640.25 | J70: =AN70*(1+$AF$5/100) -> 653.9 | K70: =AO70*(1+$AF$5/100) -> 659.75 | ... Z70: =BD70*(1+$AF$5/100) -> 1167.4 | AG70: 2600 | AH70: 799 | AI70: 821 | AJ70: 912 | AK70: 899 | AL70: 946 | AM70: 985 | AN70: 1006 | AO70: 1015 | AP70: 1071 | AQ70: 1170 | AR70: 1192 | AS70: 1236 | AT70: 1257 | AU70: 1279 | AV70: 1372 | AW70: 1536 | AX70: 1558 | AY70: 1679 | AZ70: 1702 | BA70: 1726 | BB70: 1749 | BC70: 1773 | BD70: 1796
C71: 2800 | D71: =AH71*(1+$AF$5/100) -> 532.35 | E71: =AI71*(1+$AF$5/100) -> 546.65 | F71: =AJ71*(1+$AF$5/100) -> 607.1 | G71: =AK71*(1+$AF$5/100) -> 587.6 | H71: =AL71*(1+$AF$5/100) -> 618.15 | I71: =AM71*(1+$AF$5/100) -> 655.85 | J71: =AN71*(1+$AF$5/100) -> 669.5 | K71: =AO71*(1+$AF$5/100) -> 683.8 | ... Z71: =BD71*(1+$AF$5/100) -> 1170.65 | AG71: 2800 | AH71: 819 | AI71: 841 | AJ71: 934 | AK71: 904 | AL71: 951 | AM71: 1009 | AN71: 1030 | AO71: 1052 | AP71: 1109 | AQ71: 1197 | AR71: 1219 | AS71: 1286 | AT71: 1309 | AU71: 1331 | AV71: 1402 | AW71: 1637 | AX71: 1661 | AY71: 1684 | AZ71: 1707 | BA71: 1731 | BB71: 1754 | BC71: 1778 | BD71: 1801
C72: 3000 | D72: =AH72*(1+$AF$5/100) -> 628.55 | E72: =AI72*(1+$AF$5/100) -> 633.75 | F72: =AJ72*(1+$AF$5/100) -> 687.05 | G72: =AK72*(1+$AF$5/100) -> 706.55 | H72: =AL72*(1+$AF$5/100) -> 728 | I72: =AM72*(1+$AF$5/100) -> 732.55 | J72: =AN72*(1+$AF$5/100) -> 737.75 | K72: =AO72*(1+$AF$5/100) -> 742.95 | ... Z72: =BD72*(1+$AF$5/100) -> 1295.45 | AG72: 3000 | AH72: 967 | AI72: 975 | AJ72: 1057 | AK72: 1087 | AL72: 1120 | AM72: 1127 | AN72: 1135 | AO72: 1143 | AP72: 1195 | AQ72: 1254 | AR72: 1274 | AS72: 1373 | AT72: 1393 | AU72: 1414 | AV72: 1691 | AW72: 1829 | AX72: 1853 | AY72: 1876 | AZ72: 1899 | BA72: 1923 | BB72: 1946 | BC72: 1970 | BD72: 1993
C73: 3200 | D73: =AH73*(1+$AF$5/100) -> 638.95 | E73: =AI73*(1+$AF$5/100) -> 644.15 | F73: =AJ73*(1+$AF$5/100) -> 697.45 | G73: =AK73*(1+$AF$5/100) -> 716.95 | H73: =AL73*(1+$AF$5/100) -> 738.4 | I73: =AM73*(1+$AF$5/100) -> 743.6 | J73: =AN73*(1+$AF$5/100) -> 748.15 | K73: =AO73*(1+$AF$5/100) -> 753.35 | ... Z73: =BD73*(1+$AF$5/100) -> 1342.25 | AG73: 3200 | AH73: 983 | AI73: 991 | AJ73: 1073 | AK73: 1103 | AL73: 1136 | AM73: 1144 | AN73: 1151 | AO73: 1159 | AP73: 1211 | AQ73: 1470 | AR73: 1478 | AS73: 1516 | AT73: 1652 | AU73: 1661 | AV73: 1737 | AW73: 1853 | AX73: 1862 | AY73: 1871 | AZ73: 1881 | BA73: 2035 | BB73: 2045 | BC73: 2055 | BD73: 2065
C74: 3400 | D74: =AH74*(1+$AF$5/100) -> 703.3 | E74: =AI74*(1+$AF$5/100) -> 708.5 | F74: =AJ74*(1+$AF$5/100) -> 707.85 | G74: =AK74*(1+$AF$5/100) -> 787.15 | H74: =AL74*(1+$AF$5/100) -> 809.9 | I74: =AM74*(1+$AF$5/100) -> 815.1 | J74: =AN74*(1+$AF$5/100) -> 820.95 | K74: =AO74*(1+$AF$5/100) -> 826.15 | ... Z74: =BD74*(1+$AF$5/100) -> 1411.8 | AG74: 3400 | AH74: 1082 | AI74: 1090 | AJ74: 1089 | AK74: 1211 | AL74: 1246 | AM74: 1254 | AN74: 1263 | AO74: 1271 | AP74: 1328 | AQ74: 1621 | AR74: 1629 | AS74: 1806 | AT74: 1815 | AU74: 1825 | AV74: 1902 | AW74: 2027 | AX74: 2037 | AY74: 2120 | AZ74: 2131 | BA74: 2141 | BB74: 2151 | BC74: 2162 | BD74: 2172
C75: Heights over 3400mm only achievable with Open Brackets or Headbox 160 - Sizes over 14m2 are not recommended and NOT covered by warranty | AG75: Heights over 3400mm only achievable with Open Brackets - Sizes over 14m2 are not recommended and NOT covered by warranty
C76: =C74+200 -> 3600 | D76: =AH76*(1+$AF$5/100) -> 714.35 | E76: =AI76*(1+$AF$5/100) -> 720.2 | F76: =AJ76*(1+$AF$5/100) -> 718.25 | G76: =AK76*(1+$AF$5/100) -> 798.85 | H76: =AL76*(1+$AF$5/100) -> 820.95 | I76: =AM76*(1+$AF$5/100) -> 826.8 | J76: =AN76*(1+$AF$5/100) -> 832 | K76: =AO76*(1+$AF$5/100) -> 837.85 | ... Z76: =BD76*(1+$AF$5/100) -> 1433.25 | AG76: 3600 | AH76: 1099 | AI76: 1108 | AJ76: 1105 | AK76: 1229 | AL76: 1263 | AM76: 1272 | AN76: 1280 | AO76: 1289 | AP76: 1345 | AQ76: 1651 | AR76: 1793 | AS76: 1836 | AT76: 1846 | AU76: 1856 | AV76: 1934 | AW76: 2059 | AX76: 2069 | AY76: 2153 | AZ76: 2164 | BA76: 2174 | BB76: 2184 | BC76: 2195 | BD76: 2205
C77: 3800 | D77: =AH77*(1+$AF$5/100) -> 725.4 | E77: =AI77*(1+$AF$5/100) -> 731.25 | F77: =AJ77*(1+$AF$5/100) -> 728.65 | G77: =AK77*(1+$AF$5/100) -> 809.9 | H77: =AL77*(1+$AF$5/100) -> 832.65 | I77: =AM77*(1+$AF$5/100) -> 837.85 | J77: =AN77*(1+$AF$5/100) -> 843.7 | K77: =AO77*(1+$AF$5/100) -> 848.9 | ... Z77: =BD77*(1+$AF$5/100) -> 1454.7 | AG77: 3800 | AH77: 1116 | AI77: 1125 | AJ77: 1121 | AK77: 1246 | AL77: 1281 | AM77: 1289 | AN77: 1298 | AO77: 1306 | AP77: 1363 | AQ77: 1814 | AR77: 1823 | AS77: 1867 | AT77: 1877 | AU77: 1886 | AV77: 1966 | AW77: 2091 | AX77: 2101 | AY77: 2187 | AZ77: 2197 | BA77: 2207 | BB77: 2217 | BC77: 2228 | BD77: 2238
C78: 4000 | D78: =AH78*(1+$AF$5/100) -> 737.1 | E78: =AI78*(1+$AF$5/100) -> 742.3 | F78: =AJ78*(1+$AF$5/100) -> 739.05 | G78: =AK78*(1+$AF$5/100) -> 821.6 | H78: =AL78*(1+$AF$5/100) -> 843.7 | I78: =AM78*(1+$AF$5/100) -> 849.55 | J78: =AN78*(1+$AF$5/100) -> 854.75 | K78: =AO78*(1+$AF$5/100) -> 860.6 | ... Z78: =BD78*(1+$AF$5/100) -> 1476.15 | AG78: 4000 | AH78: 1134 | AI78: 1142 | AJ78: 1137 | AK78: 1264 | AL78: 1298 | AM78: 1307 | AN78: 1315 | AO78: 1324 | AP78: 1380 | AQ78: 1844 | AR78: 1853 | AS78: 1898 | AT78: 1908 | AU78: 1917 | AV78: 1998 | AW78: 2123 | AX78: 2133 | AY78: 2220 | AZ78: 2230 | BA78: 2240 | BB78: 2251 | BC78: 2261 | BD78: 2271
C79: Pricing does NOT include Spring, Gear Crank or Motorised control systems. Add for Spring and Gear Crank Below, Motor pricing is on last page | AG79: Pricing does NOT include Spring, Gear Crank or Motorised control systems. Add for Spring and Gear Crank Below, Motor pricing is on last page
B80: Add | C80: Spring | D80: $54 | E80: $54 | F80: $54 | G80: $54 | H80: $58 | I80: $58 | J80: $58 | K80: $58 | L80: $58 | M80: $58 | N80: $58 | O80: $58 | P80: $70 | Q80: $70 | R80: $70 | S80: $70 | T80: $70 | U80: $70 | V80: $87 | W80: $87 | X80: $87 | Y80: $87 | Z80: $87 | AG80: Spring | AH80: 54 | AI80: 54 | AJ80: 54 | AK80: 54 | AL80: 58 | AM80: 58 | AN80: 58 | AO80: 58 | AP80: 58 | AQ80: 58 | AR80: 58 | AS80: 58 | AT80: 70 | AU80: 70 | AV80: 70 | AW80: 70 | AX80: 70 | AY80: 70 | AZ80: 87 | BA80: 87 | BB80: 87 | BC80: 87 | BD80: 87
C81: Gear Crank | D81: $62 | E81: $62 | F81: $62 | G81: $62 | H81: $62 | I81: $62 | J81: $62 | K81: $62 | L81: $62 | M81: $121 | N81: $121 | O81: $121 | P81: $121 | Q81: $121 | R81: $121 | S81: $121 | T81: $121 | U81: $121 | V81: $121 | W81: $121 | X81: $121 | Y81: $121 | Z81: $121 | AG81: Gear Crank | AH81: 62 | AI81: 62 | AJ81: 62 | AK81: 62 | AL81: 62 | AM81: 62 | AN81: 62 | AO81: 62 | AP81: 62 | AQ81: 121 | AR81: 121 | AS81: 121 | AT81: 121 | AU81: 121 | AV81: 121 | AW81: 121 | AX81: 121 | AY81: 121 | AZ81: 121 | BA81: 121 | BB81: 121 | BC81: 121 | BD81: 121
C82: Headbox 120 | D82: $159 | E82: $161 | F82: $163 | G82: $165 | H82: $168 | I82: $170 | J82: $172 | K82: $174 | L82: $176 | M82: $256 | N82: $259 | O82: $261 | P82: $263 | Q82: $265 | R82: $267 | S82: $270 | T82: $326 | U82: $328 | V82: $330 | W82: $333 | X82: $335 | Y82: $337 | Z82: $339 | AB82: 340.9758 | AG82: Headbox | AH82: 159 | AI82: 161 | AJ82: 163 | AK82: 165 | AL82: 168 | AM82: 170 | AN82: 172 | AO82: 174 | AP82: 176 | AQ82: 256 | AR82: 259 | AS82: 261 | AT82: 263 | AU82: 265 | AV82: 267 | AW82: 270 | AX82: 326 | AY82: 328 | AZ82: 330 | BA82: 333 | BB82: 335 | BC82: 337 | BD82: 339
C83: Headbox 160 | D83: $540 | E83: $543 | F83: $547 | G83: $550 | H83: $553 | I83: $557 | J83: $560 | K83: $563 | L83: $567 | M83: $570 | N83: $573 | O83: $576 | P83: $580 | Q83: $583 | R83: $586 | S83: $590 | T83: $593 | U83: $596 | V83: $600 | W83: $603 | X83: $606 | Y83: $610 | Z83: $613
C85: Category Fabrics: Ombra 6% (Gen II) | AH85: ="${OBS-SPG-"&AH63&"}" -> ${OBS-SPG-1400} | AI85: ="${OBS-SPG-"&AI63&"}" -> ${OBS-SPG-1600} | AJ85: ="${OBS-SPG-"&AJ63&"}" -> ${OBS-SPG-1800} | AK85: ="${OBS-SPG-"&AK63&"}" -> ${OBS-SPG-2000} | AL85: ="${OBS-SPG-"&AL63&"}" -> ${OBS-SPG-2200} | AM85: ="${OBS-SPG-"&AM63&"}" -> ${OBS-SPG-2400} | AN85: ="${OBS-SPG-"&AN63&"}" -> ${OBS-SPG-2600} | AO85: ="${OBS-SPG-"&AO63&"}" -> ${OBS-SPG-2800} | ... BD85: ="${OBS-SPG-"&BD63&"}" -> ${OBS-SPG-5800}
C86: Standard Headbox 120 Colours: Monument, Black, White, Surfmist, Woodland Gray, Shale Grey, Paperbark, Classic Cream & Custom on request | AH86: ="${OBS-CRK-"&AH63&"}" -> ${OBS-CRK-1400} | AI86: ="${OBS-CRK-"&AI63&"}" -> ${OBS-CRK-1600} | AJ86: ="${OBS-CRK-"&AJ63&"}" -> ${OBS-CRK-1800} | AK86: ="${OBS-CRK-"&AK63&"}" -> ${OBS-CRK-2000} | AL86: ="${OBS-CRK-"&AL63&"}" -> ${OBS-CRK-2200} | AM86: ="${OBS-CRK-"&AM63&"}" -> ${OBS-CRK-2400} | AN86: ="${OBS-CRK-"&AN63&"}" -> ${OBS-CRK-2600} | AO86: ="${OBS-CRK-"&AO63&"}" -> ${OBS-CRK-2800} | ... BD86: ="${OBS-CRK-"&BD63&"}" -> ${OBS-CRK-5800}
C87: Standard Headbox 160 Colours: Monument, Black, White & Custom on request | AH87: ="${OBS-HB-"&AH63&"}" -> ${OBS-HB-1400} | AI87: ="${OBS-HB-"&AI63&"}" -> ${OBS-HB-1600} | AJ87: ="${OBS-HB-"&AJ63&"}" -> ${OBS-HB-1800} | AK87: ="${OBS-HB-"&AK63&"}" -> ${OBS-HB-2000} | AL87: ="${OBS-HB-"&AL63&"}" -> ${OBS-HB-2200} | AM87: ="${OBS-HB-"&AM63&"}" -> ${OBS-HB-2400} | AN87: ="${OBS-HB-"&AN63&"}" -> ${OBS-HB-2600} | AO87: ="${OBS-HB-"&AO63&"}" -> ${OBS-HB-2800} | ... BD87: ="${OBS-HB-"&BD63&"}" -> ${OBS-HB-5800}
C88: All tubes are now Aluminium, HD tube is used when over 12m2 and included in price or smaller if purchased as upgrade | AH88: ="${OBS-HB160-"&AH63&"}" -> ${OBS-HB160-1400} | AI88: ="${OBS-HB160-"&AI63&"}" -> ${OBS-HB160-1600} | AJ88: ="${OBS-HB160-"&AJ63&"}" -> ${OBS-HB160-1800} | AK88: ="${OBS-HB160-"&AK63&"}" -> ${OBS-HB160-2000} | AL88: ="${OBS-HB160-"&AL63&"}" -> ${OBS-HB160-2200} | AM88: ="${OBS-HB160-"&AM63&"}" -> ${OBS-HB160-2400} | AN88: ="${OBS-HB160-"&AN63&"}" -> ${OBS-HB160-2600} | AO88: ="${OBS-HB160-"&AO63&"}" -> ${OBS-HB160-2800} | ... BD88: ="${OBS-HB160-"&BD63&"}" -> ${OBS-HB160-5800}
C89: Standard warranty is 5 Years. Sizes shaded in red are outside of product spec and therefore are not covered by warranty. If you need a solution to this please call the Sales Team on 02 9624 0700
C90: All prices are subject to 10% GST. Prices subject to change without notice. All prices subject to CW Systems’ General Terms & Conditions - Prices do not include any applicable shipping/handling fees
B95: Page 2 of 28 | X95: Back to Table of Contents
C98: Zip Guide Awnings Category Two
C99: Width
B100: Height | D100: 1400 | E100: 1600 | F100: 1800 | G100: 2000 | H100: 2200 | I100: 2400 | J100: 2600 | K100: 2800 | L100: 3000 | M100: 3200 | N100: 3400 | O100: 3600 | P100: 3800 | Q100: 4000 | R100: 4200 | S100: 4400 | T100: 4600 | U100: 4800 | V100: 5000 | W100: 5200 | X100: 5400 | Y100: 5600 | Z100: 5800 | AH100: 1400 | AI100: 1600 | AJ100: 1800 | AK100: 2000 | AL100: 2200 | AM100: 2400 | AN100: 2600 | AO100: 2800 | AP100: 3000 | AQ100: 3200 | AR100: 3400 | AS100: 3600 | AT100: 3800 | AU100: 4000 | AV100: 4200 | AW100: 4400 | AX100: 4600 | AY100: 4800 | AZ100: 5000 | BA100: 5200 | BB100: 5400 | BC100: 5600 | BD100: 5800
C101: 1400 | D101: =AH101*(1+$AF$5/100) -> 450.45 | E101: =AI101*(1+$AF$5/100) -> 455 | F101: =AJ101*(1+$AF$5/100) -> 508.95 | G101: =AK101*(1+$AF$5/100) -> 514.15 | H101: =AL101*(1+$AF$5/100) -> 534.3 | I101: =AM101*(1+$AF$5/100) -> 561.6 | J101: =AN101*(1+$AF$5/100) -> 566.8 | K101: =AO101*(1+$AF$5/100) -> 572 | ... Z101: =BD101*(1+$AF$5/100) -> 1098.5 | AG101: 1400 | AH101: 693 | AI101: 700 | AJ101: 783 | AK101: 791 | AL101: 822 | AM101: 864 | AN101: 872 | AO101: 880 | AP101: 934 | AQ101: 1129 | AR101: 1152 | AS101: 1176 | AT101: 1199 | AU101: 1223 | AV101: 1271 | AW101: 1428 | AX101: 1452 | AY101: 1476 | AZ101: 1500 | BA101: 1615 | BB101: 1640 | BC101: 1665 | BD101: 1690
C102: 1600 | D102: =AH102*(1+$AF$5/100) -> 453.05 | E102: =AI102*(1+$AF$5/100) -> 468 | F102: =AJ102*(1+$AF$5/100) -> 521.3 | G102: =AK102*(1+$AF$5/100) -> 526.5 | H102: =AL102*(1+$AF$5/100) -> 546.65 | I102: =AM102*(1+$AF$5/100) -> 574.6 | J102: =AN102*(1+$AF$5/100) -> 579.8 | K102: =AO102*(1+$AF$5/100) -> 585 | ... Z102: =BD102*(1+$AF$5/100) -> 1101.75 | AG102: 1600 | AH102: 697 | AI102: 720 | AJ102: 802 | AK102: 810 | AL102: 841 | AM102: 884 | AN102: 892 | AO102: 900 | AP102: 954 | AQ102: 1133 | AR102: 1157 | AS102: 1180 | AT102: 1204 | AU102: 1227 | AV102: 1276 | AW102: 1432 | AX102: 1456 | AY102: 1480 | AZ102: 1504 | BA102: 1620 | BB102: 1645 | BC102: 1670 | BD102: 1695
C103: 1800 | D103: =AH103*(1+$AF$5/100) -> 455.65 | E103: =AI103*(1+$AF$5/100) -> 470.6 | F103: =AJ103*(1+$AF$5/100) -> 533.65 | G103: =AK103*(1+$AF$5/100) -> 561.6 | H103: =AL103*(1+$AF$5/100) -> 583.05 | I103: =AM103*(1+$AF$5/100) -> 611.65 | J103: =AN103*(1+$AF$5/100) -> 616.85 | K103: =AO103*(1+$AF$5/100) -> 622.05 | ... Z103: =BD103*(1+$AF$5/100) -> 1212.9 | AG103: 1800 | AH103: 701 | AI103: 724 | AJ103: 821 | AK103: 864 | AL103: 897 | AM103: 941 | AN103: 949 | AO103: 957 | AP103: 1013 | AQ103: 1183 | AR103: 1208 | AS103: 1256 | AT103: 1281 | AU103: 1306 | AV103: 1431 | AW103: 1578 | AX103: 1604 | AY103: 1630 | AZ103: 1657 | BA103: 1784 | BB103: 1811 | BC103: 1839 | BD103: 1866
C104: 2000 | D104: =AH104*(1+$AF$5/100) -> 468 | E104: =AI104*(1+$AF$5/100) -> 482.95 | F104: =AJ104*(1+$AF$5/100) -> 559 | G104: =AK104*(1+$AF$5/100) -> 585.65 | H104: =AL104*(1+$AF$5/100) -> 607.75 | I104: =AM104*(1+$AF$5/100) -> 625.3 | J104: =AN104*(1+$AF$5/100) -> 630.5 | K104: =AO104*(1+$AF$5/100) -> 635.7 | ... Z104: =BD104*(1+$AF$5/100) -> 1216.15 | AG104: 2000 | AH104: 720 | AI104: 743 | AJ104: 860 | AK104: 901 | AL104: 935 | AM104: 962 | AN104: 970 | AO104: 978 | AP104: 1034 | AQ104: 1188 | AR104: 1212 | AS104: 1284 | AT104: 1310 | AU104: 1335 | AV104: 1436 | AW104: 1583 | AX104: 1609 | AY104: 1635 | AZ104: 1662 | BA104: 1789 | BB104: 1816 | BC104: 1844 | BD104: 1871
C105: 2200 | D105: =AH105*(1+$AF$5/100) -> 481 | E105: =AI105*(1+$AF$5/100) -> 495.95 | F105: =AJ105*(1+$AF$5/100) -> 584.35 | G105: =AK105*(1+$AF$5/100) -> 600.6 | H105: =AL105*(1+$AF$5/100) -> 633.1 | I105: =AM105*(1+$AF$5/100) -> 650.65 | J105: =AN105*(1+$AF$5/100) -> 656.5 | K105: =AO105*(1+$AF$5/100) -> 661.7 | ... Z105: =BD105*(1+$AF$5/100) -> 1219.4 | AG105: 2200 | AH105: 740 | AI105: 763 | AJ105: 899 | AK105: 924 | AL105: 974 | AM105: 1001 | AN105: 1010 | AO105: 1018 | AP105: 1075 | AQ105: 1215 | AR105: 1240 | AS105: 1289 | AT105: 1315 | AU105: 1340 | AV105: 1441 | AW105: 1588 | AX105: 1614 | AY105: 1640 | AZ105: 1667 | BA105: 1794 | BB105: 1821 | BC105: 1849 | BD105: 1876
C106: 2400 | D106: =AH106*(1+$AF$5/100) -> 522.6 | E106: =AI106*(1+$AF$5/100) -> 538.85 | F106: =AJ106*(1+$AF$5/100) -> 610.35 | G106: =AK106*(1+$AF$5/100) -> 603.2 | H106: =AL106*(1+$AF$5/100) -> 636.35 | I106: =AM106*(1+$AF$5/100) -> 664.95 | J106: =AN106*(1+$AF$5/100) -> 670.15 | K106: =AO106*(1+$AF$5/100) -> 676 | ... Z106: =BD106*(1+$AF$5/100) -> 1222.65 | AG106: 2400 | AH106: 804 | AI106: 829 | AJ106: 939 | AK106: 928 | AL106: 979 | AM106: 1023 | AN106: 1031 | AO106: 1040 | AP106: 1096 | AQ106: 1220 | AR106: 1245 | AS106: 1294 | AT106: 1320 | AU106: 1345 | AV106: 1446 | AW106: 1593 | AX106: 1619 | AY106: 1645 | AZ106: 1672 | BA106: 1799 | BB106: 1826 | BC106: 1854 | BD106: 1881
C107: 2600 | D107: =AH107*(1+$AF$5/100) -> 538.85 | E107: =AI107*(1+$AF$5/100) -> 555.75 | F107: =AJ107*(1+$AF$5/100) -> 616.85 | G107: =AK107*(1+$AF$5/100) -> 609.7 | H107: =AL107*(1+$AF$5/100) -> 642.85 | I107: =AM107*(1+$AF$5/100) -> 671.45 | J107: =AN107*(1+$AF$5/100) -> 687.7 | K107: =AO107*(1+$AF$5/100) -> 692.9 | ... Z107: =BD107*(1+$AF$5/100) -> 1244.1 | AG107: 2600 | AH107: 829 | AI107: 855 | AJ107: 949 | AK107: 938 | AL107: 989 | AM107: 1033 | AN107: 1058 | AO107: 1066 | AP107: 1123 | AQ107: 1233 | AR107: 1258 | AS107: 1307 | AT107: 1332 | AU107: 1358 | AV107: 1460 | AW107: 1626 | AX107: 1652 | AY107: 1777 | AZ107: 1805 | BA107: 1832 | BB107: 1859 | BC107: 1887 | BD107: 1914
C108: 2800 | D108: =AH108*(1+$AF$5/100) -> 551.85 | E108: =AI108*(1+$AF$5/100) -> 568.75 | F108: =AJ108*(1+$AF$5/100) -> 631.8 | G108: =AK108*(1+$AF$5/100) -> 612.95 | H108: =AL108*(1+$AF$5/100) -> 646.1 | I108: =AM108*(1+$AF$5/100) -> 687.05 | J108: =AN108*(1+$AF$5/100) -> 703.95 | K108: =AO108*(1+$AF$5/100) -> 720.2 | ... Z108: =BD108*(1+$AF$5/100) -> 1247.35 | AG108: 2800 | AH108: 849 | AI108: 875 | AJ108: 972 | AK108: 943 | AL108: 994 | AM108: 1057 | AN108: 1083 | AO108: 1108 | AP108: 1166 | AQ108: 1261 | AR108: 1287 | AS108: 1361 | AT108: 1387 | AU108: 1413 | AV108: 1491 | AW108: 1728 | AX108: 1755 | AY108: 1782 | AZ108: 1810 | BA108: 1837 | BB108: 1865 | BC108: 1892 | BD108: 1919
C109: 3000 | D109: =AH109*(1+$AF$5/100) -> 664.95 | E109: =AI109*(1+$AF$5/100) -> 670.15 | F109: =AJ109*(1+$AF$5/100) -> 723.45 | G109: =AK109*(1+$AF$5/100) -> 743.6 | H109: =AL109*(1+$AF$5/100) -> 765.05 | I109: =AM109*(1+$AF$5/100) -> 769.6 | J109: =AN109*(1+$AF$5/100) -> 774.8 | K109: =AO109*(1+$AF$5/100) -> 780 | ... Z109: =BD109*(1+$AF$5/100) -> 1372.15 | AG109: 3000 | AH109: 1023 | AI109: 1031 | AJ109: 1113 | AK109: 1144 | AL109: 1177 | AM109: 1184 | AN109: 1192 | AO109: 1200 | AP109: 1252 | AQ109: 1312 | AR109: 1335 | AS109: 1442 | AT109: 1466 | AU109: 1491 | AV109: 1777 | AW109: 1919 | AX109: 1947 | AY109: 1974 | AZ109: 2002 | BA109: 2029 | BB109: 2056 | BC109: 2084 | BD109: 2111
C110: 3200 | D110: =AH110*(1+$AF$5/100) -> 677.3 | E110: =AI110*(1+$AF$5/100) -> 682.5 | F110: =AJ110*(1+$AF$5/100) -> 736.45 | G110: =AK110*(1+$AF$5/100) -> 756.6 | H110: =AL110*(1+$AF$5/100) -> 777.4 | I110: =AM110*(1+$AF$5/100) -> 782.6 | J110: =AN110*(1+$AF$5/100) -> 787.8 | K110: =AO110*(1+$AF$5/100) -> 793 | ... Z110: =BD110*(1+$AF$5/100) -> 1431.95 | AG110: 3200 | AH110: 1042 | AI110: 1050 | AJ110: 1133 | AK110: 1164 | AL110: 1196 | AM110: 1204 | AN110: 1212 | AO110: 1220 | AP110: 1272 | AQ110: 1591 | AR110: 1599 | AS110: 1640 | AT110: 1776 | AU110: 1785 | AV110: 1865 | AW110: 1981 | AX110: 1991 | AY110: 2000 | AZ110: 2009 | BA110: 2174 | BB110: 2184 | BC110: 2194 | BD110: 2203
C111: 3400 | D111: =AH111*(1+$AF$5/100) -> 747.5 | E111: =AI111*(1+$AF$5/100) -> 752.7 | F111: =AJ111*(1+$AF$5/100) -> 748.8 | G111: =AK111*(1+$AF$5/100) -> 832 | H111: =AL111*(1+$AF$5/100) -> 854.75 | I111: =AM111*(1+$AF$5/100) -> 860.6 | J111: =AN111*(1+$AF$5/100) -> 865.8 | K111: =AO111*(1+$AF$5/100) -> 871.65 | ... Z111: =BD111*(1+$AF$5/100) -> 1510.6 | AG111: 3400 | AH111: 1150 | AI111: 1158 | AJ111: 1152 | AK111: 1280 | AL111: 1315 | AM111: 1324 | AN111: 1332 | AO111: 1341 | AP111: 1397 | AQ111: 1759 | AR111: 1768 | AS111: 1947 | AT111: 1956 | AU111: 1966 | AV111: 2049 | AW111: 2174 | AX111: 2184 | AY111: 2272 | AZ111: 2282 | BA111: 2293 | BB111: 2303 | BC111: 2313 | BD111: 2324
C112: Heights over 3400mm only achievable with Open Brackets or Headbox 160 - Sizes over 14m2 are not recommended and NOT covered by warranty | AG112: Heights over 3400mm only achievable with Open Brackets - Sizes over 14m2 are not recommended and NOT covered by warranty
C113: =C111+200 -> 3600 | D113: =AH113*(1+$AF$5/100) -> 761.15 | E113: =AI113*(1+$AF$5/100) -> 766.35 | F113: =AJ113*(1+$AF$5/100) -> 761.15 | G113: =AK113*(1+$AF$5/100) -> 846.3 | H113: =AL113*(1+$AF$5/100) -> 869.05 | I113: =AM113*(1+$AF$5/100) -> 874.25 | J113: =AN113*(1+$AF$5/100) -> 879.45 | K113: =AO113*(1+$AF$5/100) -> 885.3 | ... Z113: =BD113*(1+$AF$5/100) -> 1537.25 | AG113: 3600 | AH113: 1171 | AI113: 1179 | AJ113: 1171 | AK113: 1302 | AL113: 1337 | AM113: 1345 | AN113: 1353 | AO113: 1362 | AP113: 1418 | AQ113: 1797 | AR113: 1939 | AS113: 1985 | AT113: 1995 | AU113: 2004 | AV113: 2089 | AW113: 2214 | AX113: 2224 | AY113: 2313 | AZ113: 2324 | BA113: 2334 | BB113: 2344 | BC113: 2355 | BD113: 2365
C114: 3800 | D114: =AH114*(1+$AF$5/100) -> 774.8 | E114: =AI114*(1+$AF$5/100) -> 780 | F114: =AJ114*(1+$AF$5/100) -> 773.5 | G114: =AK114*(1+$AF$5/100) -> 859.95 | H114: =AL114*(1+$AF$5/100) -> 882.7 | I114: =AM114*(1+$AF$5/100) -> 887.9 | J114: =AN114*(1+$AF$5/100) -> 893.75 | K114: =AO114*(1+$AF$5/100) -> 898.95 | ... Z114: =BD114*(1+$AF$5/100) -> 1563.9 | AG114: 3800 | AH114: 1192 | AI114: 1200 | AJ114: 1190 | AK114: 1323 | AL114: 1358 | AM114: 1366 | AN114: 1375 | AO114: 1383 | AP114: 1440 | AQ114: 1968 | AR114: 1977 | AS114: 2024 | AT114: 2033 | AU114: 2043 | AV114: 2129 | AW114: 2254 | AX114: 2264 | AY114: 2355 | AZ114: 2365 | BA114: 2375 | BB114: 2386 | BC114: 2396 | BD114: 2406
C115: 4000 | D115: =AH115*(1+$AF$5/100) -> 788.45 | E115: =AI115*(1+$AF$5/100) -> 793.65 | F115: =AJ115*(1+$AF$5/100) -> 786.5 | G115: =AK115*(1+$AF$5/100) -> 873.6 | H115: =AL115*(1+$AF$5/100) -> 896.35 | I115: =AM115*(1+$AF$5/100) -> 902.2 | J115: =AN115*(1+$AF$5/100) -> 907.4 | K115: =AO115*(1+$AF$5/100) -> 912.6 | ... Z115: =BD115*(1+$AF$5/100) -> 1591.2 | AG115: 4000 | AH115: 1213 | AI115: 1221 | AJ115: 1210 | AK115: 1344 | AL115: 1379 | AM115: 1388 | AN115: 1396 | AO115: 1404 | AP115: 1461 | AQ115: 2005 | AR115: 2015 | AS115: 2062 | AT115: 2072 | AU115: 2082 | AV115: 2169 | AW115: 2294 | AX115: 2304 | AY115: 2396 | AZ115: 2406 | BA115: 2417 | BB115: 2427 | BC115: 2437 | BD115: 2448
C116: Pricing does NOT include Spring, Gear Crank or Motorised control systems. Add for Spring and Gear Crank Below, Motor pricing is on last page | AG116: Pricing does NOT include Spring, Gear Crank or Motorised control systems. Add for Spring and Gear Crank Below, Motor pricing is on last page
B117: Add | C117: Spring | D117: $54 | E117: $54 | F117: $54 | G117: $54 | H117: $58 | I117: $58 | J117: $58 | K117: $58 | L117: $58 | M117: $58 | N117: $58 | O117: $58 | P117: $70 | Q117: $70 | R117: $70 | S117: $70 | T117: $70 | U117: $70 | V117: $87 | W117: $87 | X117: $87 | Y117: $87 | Z117: $87 | AG117: Spring | AH117: 54 | AI117: 54 | AJ117: 54 | AK117: 54 | AL117: 58 | AM117: 58 | AN117: 58 | AO117: 58 | AP117: 58 | AQ117: 58 | AR117: 58 | AS117: 58 | AT117: 70 | AU117: 70 | AV117: 70 | AW117: 70 | AX117: 70 | AY117: 70 | AZ117: 87 | BA117: 87 | BB117: 87 | BC117: 87 | BD117: 87
...

Sheet Pleated
B2: Insect Screens | G2: As of | H2: =Cover!I59 -> 46113
A3: Element Collection | F3: Luxe Blinds Shutters Awnings
D4: =IFERROR(IF(-X4/100>0,-X4/100,""),"") -> 0.25 | E4: =IF(D4="","","Discount already applied to the prices below") -> Discount already applied to the prices below | X4: -25
A5: Pleated Screen Price List
A6: Standard Single
A7: WIDTH
A8: HEIGHT | C8: 1100 | D8: 1500 | E8: 2000 | F8: 2700 | G8: 3600 | H8: 4500
B9: 800 | C9: 270 | D9: 334.5 | E9: 399.75 | F9: n/a | G9: n/a | H9: n/a
B10: 1000 | C10: 316.5 | D10: 384.75 | E10: 454.5 | F10: n/a | G10: n/a | H10: n/a
B11: 1200 | C11: 327 | D11: 396.75 | E11: 466.5 | F11: 526.5 | G11: n/a | H11: n/a
B12: 1400 | C12: 429.75 | D12: 540 | E12: 651.75 | F12: 753.75 | G12: n/a | H12: n/a
B13: 1600 | C13: 466.5 | D13: 576 | E13: 687 | F13: 789.75 | G13: 990.75 | H13: n/a
B14: 1800 | C14: 483.75 | D14: 594.75 | E14: 706.5 | F14: 809.25 | G14: 1008.75 | H14: n/a
B15: 2000 | C15: 486 | D15: 598.5 | E15: 709.5 | F15: 812.25 | G15: 1011.75 | H15: 1157.25
B16: 2200 | C16: 493.5 | D16: 604.5 | E16: 714.75 | F16: 820.5 | G16: 1019.25 | H16: 1165.5
B17: 2400 | C17: 500.25 | D17: 610.5 | E17: 720 | F17: 828.75 | G17: 1026.75 | H17: 1173
B18: 2600 | C18: 546.75 | D18: 664.5 | E18: 782.25 | F18: 900 | G18: 1120.5 | H18: 1283.25
B19: 2800 | C19: 574.5 | D19: 698.25 | E19: 821.25 | F19: 945 | G19: 1176 | H19: 1347.75
B20: 3000 | C20: 591 | D20: 718.5 | E20: 846 | F20: 974.25 | G20: 1211.25 | H20: 1387.5
A22: Standard Double
A23: WIDTH
A24: HEIGHT | C24: 2200 | D24: 3000 | E24: 4000 | F24: 5400 | G24: 7200 | H24: 9000
B25: 800 | C25: 538.5 | D25: 669 | E25: 799.5 | F25: n/a | G25: n/a | H25: n/a
B26: 1000 | C26: 632.25 | D26: 769.5 | E26: 908.25 | F26: n/a | G26: n/a | H26: n/a
B27: 1200 | C27: 653.25 | D27: 792 | E27: 931.5 | F27: 1051.5 | G27: n/a | H27: n/a
B28: 1400 | C28: 859.5 | D28: 1080 | E28: 1302 | F28: 1506.75 | G28: n/a | H28: n/a
B29: 1600 | C29: 931.5 | D29: 1151.25 | E29: 1374 | F29: 1578.75 | G29: 1980 | H29: n/a
B30: 1800 | C30: 966.75 | D30: 1188.75 | E30: 1412.25 | F30: 1617.75 | G30: 2016.75 | H30: n/a
B31: 2000 | C31: 971.25 | D31: 1196.25 | E31: 1418.25 | F31: 1624.5 | G31: 2022 | H31: 2313.75
B32: 2200 | C32: 985.5 | D32: 1207.5 | E32: 1429.5 | F32: 1641 | G32: 2037.75 | H32: 2329.5
B33: 2400 | C33: 999.75 | D33: 1220.25 | E33: 1439.25 | F33: 1656.75 | G33: 2053.5 | H33: 2346
B34: 2600 | C34: 1092.75 | D34: 1329 | E34: 1563.75 | F34: 1800 | G34: 2239.5 | H34: 2565.75
B35: 2800 | C35: 1147.5 | D35: 1395 | E35: 1642.5 | F35: 1890 | G35: 2351.25 | H35: 2694.75
B36: 3000 | C36: 1181.25 | D36: 1436.25 | E36: 1691.25 | F36: 1947.75 | G36: 2421.75 | H36: 2775
A38: Vertical
A39: WIDTH
A40: HEIGHT | C40: 500 | D40: 1000 | E40: 1500 | F40: 2000 | G40: 2500 | H40: 3000
B41: 500 | C41: 285 | D41: 318 | E41: 359.25 | F41: 383.25 | G41: 410.25 | H41: 475.5
B42: 1000 | C42: 330.75 | D42: 366.75 | E42: 413.25 | F42: 436.5 | G42: 463.5 | H42: 540
B43: 1500 | C43: 377.25 | D43: 415.5 | E43: 465.75 | F43: 489 | G43: 517.5 | H43: 605.25
B44: 2000 | C44: 423.75 | D44: 463.5 | E44: 519 | F44: 543 | G44: 570 | H44: 671.25
B45: 2400 | C45: 462.75 | D45: 504.75 | E45: 562.5 | F45: 586.5 | G45: 614.25 | H45: 725.25
B46: 2800 | C46: 501 | D46: 544.5 | E46: 606 | F46: 630 | G46: 657 | H46: 777
A48: Pleated Screen Price List
A49: Zero Single
A50: HEIGHT | B50: WIDTH
B51: 950 | C51: 1150 | D51: 1350 | E51: 1550 | F51: 1750 | G51: 1950 | H51: 2150
A52: 1400 | B52: 575.25 | C52: 603 | D52: n/a | E52: n/a | F52: n/a | G52: n/a | H52: n/a
A53: 1600 | B53: 600.75 | C53: 629.25 | D53: 659.25 | E53: n/a | F53: n/a | G53: n/a | H53: n/a
A54: 1800 | B54: 614.25 | C54: 642.75 | D54: 673.5 | E54: 702.75 | F54: n/a | G54: n/a | H54: n/a
A55: 2000 | B55: 632.25 | C55: 660.75 | D55: 691.5 | E55: 720 | F55: 749.25 | G55: n/a | H55: n/a
A56: 2200 | B56: 646.5 | C56: 675 | D56: 705 | E56: 734.25 | F56: 762.75 | G56: 791.25 | H56: n/a
A57: 2400 | B57: 673.5 | C57: 702.75 | D57: 733.5 | E57: 762.75 | F57: 792.75 | G57: 822 | H57: 852
A58: 2600 | B58: 706.5 | C58: 739.5 | D58: 775.5 | E58: 808.5 | F58: 842.25 | G58: 875.25 | H58: 909
A59: 2800 | B59: 728.25 | C59: 762 | D59: 797.25 | E59: 831 | F59: 864 | G59: 897.75 | H59: 931.5
A60: 3000 | B60: 744.75 | C60: 779.25 | D60: 814.5 | E60: 847.5 | F60: 881.25 | G60: 915 | H60: 948
A64: HEIGHT | B64: WIDTH
B65: 1900 | C65: 2300 | D65: 2700 | E65: 3100 | F65: 3500 | G65: 3900 | H65: 4300
A66: 1400 | B66: 1149.75 | C66: 1205.25 | D66: n/a | E66: n/a | F66: n/a | G66: n/a | H66: n/a
A67: 1600 | B67: 1200.75 | C67: 1257.75 | D67: 1318.5 | E67: n/a | F67: n/a | G67: n/a | H67: n/a
A68: 1800 | B68: 1228.5 | C68: 1285.5 | D68: 1346.25 | E68: 1404.75 | F68: n/a | G68: n/a | H68: n/a
A69: 2000 | B69: 1264.5 | C69: 1321.5 | D69: 1383 | E69: 1440 | F69: 1497.75 | G69: n/a | H69: n/a
A70: 2200 | B70: 1292.25 | C70: 1349.25 | D70: 1409.25 | E70: 1467.75 | F70: 1525.5 | G70: 1582.5 | H70: n/a
A71: 2400 | B71: 1346.25 | C71: 1404.75 | D71: 1466.25 | E71: 1525.5 | F71: 1585.5 | G71: 1644 | H71: 1703.25
A72: 2600 | B72: 1412.25 | C72: 1479 | D72: 1550.25 | E72: 1616.25 | F72: 1684.5 | G72: 1750.5 | H72: 1817.25
A73: 2800 | B73: 1455.75 | C73: 1524 | D73: 1594.5 | E73: 1661.25 | F73: 1728 | G73: 1795.5 | H73: 1862.25
A74: 3000 | B74: 1489.5 | C74: 1557.75 | D74: 1629 | E74: 1695 | F74: 1761.75 | G74: 1830 | H74: 1896
A76: Additional Charges
A77: Bullnose Bottom Track | E77: $10 /LM
A78: Custom Powder Coating Finish | E78: $200 (includes 2 Units) then $50 /unit after
A79: Deco Wood-grain Finish | E79: $550 (includes 2 Units) then $100 /unit after
A80: Re-cord | E80: $150 / Unit
A81: Remesh | E81: 0.3
A82: Express Order Surcharge - Standard Colour (48hrs) | E82: $150 /order
A83: Express Order Surcharge - Custom Colour (5 Days) | E83: $300 /order
A84: Angles
A85: 32 x 20mm Angle | E85: $10 /LM
A86: 40 x 20mm Angle | E86: $12 /LM
A87: 50 x 25 Angle | E87: $14 /LM
A89: Prices do not include any applicable shipping/handling fees.
A90: All prices are subject to 10% GST. Prices subject to change without notice. All prices subject to CW Systems’ General Terms & Conditions.

Sheet Lumex Custom
B2: Roofing | E2: CUSTOM ROOF Price List | M2: As of | N2: =Cover!I59 -> 46113
A3: Lumex Collection - SkyStrong 220 | M3: Luxe Blinds Shutters Awnings
J4: =IFERROR(IF(-Q4/100>0,-Q4/100,""),"") -> 0.1 | L4: =IF(J4="","","Discount already applied to the prices below") -> Discount already applied to the prices below | Q4: -10
A5: Prices include: Blades, Gutters, Pivot Rails; Monument & White colours only (see below for surcharge on other colours)
C7: Width (mm)
A8: No. of Blades | B8: Projection | C8: 1500 | D8: 1750 | E8: 2000 | F8: 2250 | G8: 2500 | H8: 2750 | I8: 3000 | J8: 3250 | K8: 3500 | L8: 3750 | M8: 4000 | N8: 4250 | O8: 4500
A9: 7 | B9: 1400 | C9: 1955.7 | D9: 2099.7 | E9: 2263.5 | F9: 2425.5 | G9: 2589.3 | H9: 2733.3 | I9: 2897.1 | J9: 3059.1 | K9: 3222.9 | L9: 3366.9 | M9: 3529.8 | N9: 3692.7 | O9: 3855.6
A10: 8 | B10: 1600 | C10: 2153.7 | D10: 2335.5 | E10: 2516.4 | F10: 2697.3 | G10: 2878.2 | H10: 3059.1 | I10: 3240 | J10: 3420.9 | K10: 3584.7 | L10: 3765.6 | M10: 3945.6 | N10: 4126.5 | O10: 4307.4
A11: 9 | B11: 1800 | C11: 2390.4 | D11: 2570.4 | E11: 2770.2 | F11: 2969.1 | G11: 3167.1 | H11: 3366.9 | I11: 3565.8 | J11: 3765.6 | K11: 3964.5 | L11: 4163.4 | M11: 4363.2 | N11: 4561.2 | O11: 4760.1
A12: 10 | B12: 2000 | C12: 2589.3 | D12: 2806.2 | E12: 3023.1 | F12: 3258 | G12: 3457.8 | H12: 3692.7 | I12: 3910.5 | J12: 4126.5 | K12: 4344.3 | L12: 4561.2 | M12: 4779 | N12: 4995.9 | O12: 5212.8
A13: 11 | B13: 2200 | C13: 2806.2 | D13: 3041.1 | E13: 3294 | F13: 3529.8 | G13: 3765.6 | H13: 4000.5 | I13: 4236.3 | J13: 4471.2 | K13: 4706.1 | L13: 4959.9 | M13: 5194.8 | N13: 5430.6 | O13: 5230.8
A14: 12 | B14: 2400 | C14: 3023.1 | D14: 3276.9 | E14: 3547.8 | F14: 3800.7 | G14: 4054.5 | H14: 4307.4 | I14: 4579.2 | J14: 4833 | K14: 5085.9 | L14: 5339.7 | M14: 5176.8 | N14: 5411.7 | O14: 5647.5
A15: 13 | B15: 2600 | C15: 3240 | D15: 3529.8 | E15: 3800.7 | F15: 4072.5 | G15: 4344.3 | H15: 4633.2 | I15: 4905 | J15: 5194.8 | K15: 5466.6 | L15: 5303.7 | M15: 5557.5 | N15: 5810.4 | O15: 6081.3
A16: 14 | B16: 2800 | C16: 3457.8 | D16: 3765.6 | E16: 4054.5 | F16: 4344.3 | G16: 4652.1 | H16: 4941 | I16: 5249.7 | J16: 5538.6 | K16: 5393.7 | L16: 5665.5 | M16: 5937.3 | N16: 6208.2 | O16: 6498
A17: 15 | B17: 3000 | C17: 3674.7 | D17: 4000.5 | E17: 4307.4 | F17: 4633.2 | G17: 4941 | H17: 5266.8 | I17: 5574.6 | J17: 5447.7 | K17: 5737.5 | L17: 6027.3 | M17: 6317.1 | N17: 6334.2 | O17: 6624.9
A18: 16 | B18: 3200 | C18: 3891.6 | D18: 4217.4 | E18: 4561.2 | F18: 4905 | G18: 5249.7 | H18: 5574.6 | I18: 5918.4 | J18: 5773.5 | K18: 6081.3 | L18: 6407.1 | M18: 6425.1 | N18: 6732.9 | O18: 7022.7
A19: 17 | B19: 3400 | C19: 4109.4 | D19: 4452.3 | E19: 4814.1 | F19: 5176.8 | G19: 5538.6 | H19: 5900.4 | I19: 5773.5 | J19: 6099.3 | K19: 6425.1 | L19: 6769.8 | M19: 6786.9 | N19: 7112.7 | O19: 7420.5
A20: 18 | B20: 3600 | C20: 4326.3 | D20: 4706.1 | E20: 5067.9 | F20: 5447.7 | G20: 5827.5 | H20: 5737.5 | I20: 6081.3 | J20: 6425.1 | K20: 6786.9 | L20: 6823.8 | M20: 7167.6 | N20: 7493.4 | O20: 7837.2
... A42: 40 | B42: 8000 | C42: 8996.4 | D42: 9564.3 | E42: 10131.3 | F42: 10699.2 | G42: 11265.3 | H42: 11832.3 | I42: 12400.2 | J42: 12967.2 | K42: 13534.2 | L42: 14102.1 | M42: 14669.1 | N42: 15235.2 | O42: 15962.4
C43: Note: shaded section indicates 2 motor control boxes required
A45: Structural Extras | H45: Motorisation & Electronics (each Roof requires a Control System + Remote)
A46: 250x50 Beam | F46: 90 | G46: /m | H46: Control System (Includes Motor, 5m Cable, Control Box, Transformer) | N46: 760 | O46: each
A47: 250x50 Beam Corner Joint | F47: 50 | G47: each | H47: Motor Cable - 10m | N47: 100 | O47: each
A48: 250x50 Internal U-Bracket | F48: 30 | G48: each | H48: Rain Sensor | N48: 275 | O48: each
A49: 120mm Posts (Max Length 3800mm) | F49: 360 | G49: each | H49: Remotes & Transmitters
A50: 150mm Posts (Max Length 5400mm) | F50: 360 | G50: each | H50: 3 Button Transmitter - 6 Channel | N50: 95 | O50: each
A51: Post External Base Plate | F51: 60 | G51: each | H51: Lumex Wifi Hub (Multiple Smartphones) | N51: 650 | O51: each
A52: Post Internal U-Bracket | F52: 30 | G52: each | H52: Lumex Bluetooth Hub (1 Smartphone Only) | N52: 355 | O52: each
A53: Roof Mount Bracket | F53: 90 | G53: each | H53: Wifi Interface for Home Automation | N53: 650 | O53: each
A54: Custom Colour Surcharge | F54: 10% - Min $500 | G54: /colour | H54: RS232 Interface for Home Automation | N54: 536 | O54: each
A55: Marine Grade Powdercoat Surcharge | F55: 25% - Min $1300 | G55: /colour | H55: 433MHz Interface for Somfy Control | N55: 250 | O55: each
A56: Woodgrain Powdercoat Surcharge | F56: 25% - Min $1300 | G56: /colour
A57: Drawing Fee (credited once order is in production) | F57: 300 | G57: /order
A58: Raked/Angled Roof | F58: 0.05 | G58: surcharge
A59: When direct wall mounting 250x50 surrounds are not required although recommended for ease of installation.
A60: Lighting
A61: White Light Drivers | E61: Multicoloured Light Drivers | H61: White Lighting | L61: Multicoloured Lighting
A62: Max Power Draw | B62: No. Of Outputs | D62: Price | E62: Max Power Draw | F62: No. Of Outputs | G62: Price | H62: Type | I62: Length | J62: Power Draw | K62: Price | L62: Type | M62: Length | N62: Power Draw | O62: Price
A63: 60w | B63: 1 | D63: $275 each | E63: 150w | F63: 4 | G63: $540 each | H63: Down Light | I63: 1.5m cable | J63: 4.5w/ea | K63: $85 each | L63: Adhesive Strip Light | M63: 5m | N63: 7.5w/m | O63: $330 each
A64: 100w | B64: 1 | D64: $275 each | E64: 185w | F64: 4 | G64: $560 each | H64: Adhesive Strip Light | I64: 5m | J64: 8w/m | K64: $205 each | M64: 7m | N64: 7.5w/m | O64: $470 each
A65: 150w | B65: 4 | D65: $530 each | E65: 240w | F65: 4 | G65: $580 each | I65: 7m | J65: 8w/m | K65: $265 each
A66: 185w | B66: 4 | D66: $550 each | E66: 320w | F66: 4 | G66: $655 each | H66: Diffuser Strip Light Kit to suit | I66: 5m | J66: 16w/m | K66: $640 each
A67: 240w | B67: 4 | D67: $570 each | I67: 7m | J67: 16w/m | K67: $900 each
A68: 320w | B68: 4 | D68: $645 each | H68: LED Cabling | L68: Multicoloured Light Cabling
H69: 1.5m Extension | K69: $10 each | L69: 1m Extension | O69: $16 each
H70: 3m Extension | K70: $22 each | L70: 5m Extension | O70: $36 each
H71: 5m Extension | K71: $26 each | L71: 2 Head Splitter | O71: $36 each
H72: 2 Head Splitter | K72: $26 each
A73: When Quoting Lights, calculate your total power load using the wattages given, and choose a Dimmer accordingly.
A75: Prices do not include any applicable shipping/handling fees.
A76: All prices are subject to 10% GST. Prices subject to change without notice. All prices subject to CW Systems’ General Terms & Conditions.

Sheet Manual Roof
B2: Roofing | F2: As of | G2: =Cover!I59 -> 46113
A3: Lumex Collection - AltrisShield 140 | E3: Luxe Blinds Shutters Awnings
E4: =IFERROR(IF(-J4/100>0,-J4/100,""),"") -> 0.2 | F4: =IF(E4="","","Discount already applied to the prices below") -> Discount already applied to the prices below | J4: -20
A5: 140mm Louvre Roof Pricing
A6: Pricing includes: Louvres, Beams, Gutters, Gearbox, Crank Handle Note: Roofs over 4000x4000 will be supplied with 2 Gearboxes & Handles
A7: Item Code | C7: Description | E7: Projection (No. of Blades) | F7: Width (Span) | G7: Price Ex. GST | J7: Base Prices
A8: LR140M-6040-W | C8: Louvre Roof 140 Manual Crank: 6000 x 4000 - White | E8: 5845 | F8: 3895 | G8: =J8*(1+$J$4/100) -> 6928 | J8: 8660
A9: LR140M-6040-M | C9: Louvre Roof 140 Manual Crank: 6000 x 4000 - Monument | E9: 5845 | F9: 3895 | G9: =J9*(1+$J$4/100) -> 6928 | J9: 8660
A10: LR140M-5040-W | C10: Louvre Roof 140 Manual Crank: 5000 x 4000 - White | E10: 4935 | F10: 3895 | G10: =J10*(1+$J$4/100) -> 6014.4 | J10: 7518
A11: LR140M-5040-M | C11: Louvre Roof 140 Manual Crank: 5000 x 4000 - Monument | E11: 4935 | F11: 3895 | G11: =J11*(1+$J$4/100) -> 6014.4 | J11: 7518
A12: LR140M-5030-W | C12: Louvre Roof 140 Manual Crank: 5000 x 3000 - White | E12: 4935 | F12: 2985 | G12: =J12*(1+$J$4/100) -> 5087.2 | J12: 6359
A13: LR140M-5030-M | C13: Louvre Roof 140 Manual Crank: 5000 x 3000 - Monument | E13: 4935 | F13: 2985 | G13: =J13*(1+$J$4/100) -> 5087.2 | J13: 6359
A14: LR140M-4040-W | C14: Louvre Roof 140 Manual Crank: 4000 x 4000 - White | E14: 3895 | F14: 3895 | G14: =J14*(1+$J$4/100) -> 4762.4 | J14: 5953
A15: LR140M-4040-M | C15: Louvre Roof 140 Manual Crank: 4000 x 4000 - Monument | E15: 3895 | F15: 3895 | G15: =J15*(1+$J$4/100) -> 4762.4 | J15: 5953
A16: LR140M-3030-W | C16: Louvre Roof 140 Manual Crank: 3000 x 3000 - White | E16: 2985 | F16: 2985 | G16: =J16*(1+$J$4/100) -> 3320 | J16: 4150
A17: LR140M-3030-M | C17: Louvre Roof 140 Manual Crank: 3000 x 3000 - Monument | E17: 2985 | F17: 2985 | G17: =J17*(1+$J$4/100) -> 3320 | J17: 4150
A18: Posts & Accessories
A19: Post Pricing includes Baseplates Note: All 6m x 4m, 5m x 4m, & 5m x 3m systems require a centre Support Post when wall mounted or freestanding.
A20: Item Code | B20: Description | G20: Price Ex. GST
A21: LR140-CP-W | B21: Louvre Roof 140: Corner Post- White (includes Baseplate) 120x120 @ 2750mm | G21: 135
A22: LR140-CP-M | B22: Louvre Roof 140: Corner Post- Monument (includes Baseplate) 120x120 @ 2750mm | G22: 135
A23: LR140-SP-W | B23: Louvre Roof 140: Support Post- White (includes Baseplate) 120x120 @ 2750mm | G23: 135
A24: LR140-SP-M | B24: Louvre Roof 140: Support Post- Monument (includes Baseplate) 120x120 @ 2750mm | G24: 135
A26: All prices are subject to 10% GST
A27: Prices subject to change without notice. All prices subject to CW Systems’ General Terms & Conditions.

Sheet Roller Blinds | Atlas
B2: Blinds | W2: As of | X2: =Cover!AA61 -> 0
A3: Roller Blinds - Atlas Collection | W3: Luxe Blinds Shutters Awnings
W4: =IF(AF4="","","Discount already applied to the prices below") -> Discount already applied to the prices below | AE4: Cat 1 Discount | AF4: -25
AE5: Cat 2 Discount | AF5: -25
AE6: Cat 3 Discount | AF6: -25
B7: Fabric Categories - Atlas Collection | P7: Motorisation
B8: Fabric Name | E8: Fabric Type | H8: Category | K8: Max Width
B9: Essence | E9: Blockout | H9: Category 1 | K9: 3210mm | P9: Somfy
B10: Aristocrat | E10: Blockout | H10: Category 2 | K10: 3210mm | P10: Motors
B11: Boulevard | E11: Light Filtering | H11: Category 2 | K11: 3210mm | P11: Power Source | R11: Control | T11: Description | X11: Price | Z11: Price Per
B12: Verve | E12: Blockout | H12: Category 2 | K12: 3210mm | P12: Battery | R12: RTS | T12: Sonesse 30 2/20 | X12: 280 | Z12: Each
B13: Empyrean | E13: Light Filtering | H13: Category 2 | K13: 3210mm | P13: 240V (Hardwired) | R13: RTS | T13: Altus 40 3/30 | X13: 230 | Z13: Each
B14: Kyoto | E14: Light Filtering | H14: Category 2 | K14: 3210mm | P14: 240V (Hardwired) | R14: RTS | T14: Sonesse 40 3/30 | X14: 370 | Z14: Each
B15: Panorama | E15: Screen 5% & 10% | H15: Category 2 | K15: 3210mm | P15: 240V (Hardwired) | R15: WC | T15: LS 40 3/30 | X15: 200 | Z15: Each
B16: Symphony | E16: Screen 5% | H16: Category 2 | K16: 3210mm | P16: Remotes
B17: Sedona | E17: Light Filtering | H17: Category 2 | K17: 3210mm | P17: Type | R17: Description | X17: Price | Z17: Price Per
B18: Tropicana | E18: Light Filtering | H18: Category 2 | K18: 3210mm | P18: Handheld | R18: 1 Channel Situo White | V18: $85 | X18: 85 | Y18: Each | Z18: Each
B19: Urbania | E19: Light Filtering | H19: Category 2 | K19: 3210mm | P19: Handheld | R19: 5 Channel Situo White | V19: $100 | X19: 100 | Y19: Each | Z19: Each
B20: Velvet | E20: Light Filtering | H20: Category 2 | K20: 3210mm | P20: Handheld | R20: 16 Channel Telis White | V20: $260 | X20: 260 | Y20: Each | Z20: Each
B21: Vogue | E21: Light Filtering | H21: Category 2 | K21: 3210mm | P21: Surface Wall Mount | R21: 1 Channel White | V21: $90 | X21: 90 | Y21: Each | Z21: Each
B22: Boulevard | E22: Blockout | H22: Category 3 | K22: 3210mm | P22: Accessories
B23: Chiffon | E23: Blockout | H23: Category 3 | K23: 3210mm | P23: Description | X23: Price | Z23: Price Per
B24: Empyrean | E24: Blockout | H24: Category 3 | K24: 3210mm | P24: Connexoon | X24: 180 | Y24: $180 | Z24: Each
B25: Lisbon | E25: Blockout | H25: Category 3 | K25: 3210mm | P25: Tahoma Switch | V25: $250 | X25: 250 | Y25: Each | Z25: Each
B26: Kyoto | E26: Blockout | H26: Category 3 | K26: 3210mm | P26: Somfy Charger | V26: $25 | X26: 25 | Y26: Each | Z26: Each
B27: Velvet | E27: Blockout | H27: Category 3 | K27: 3210mm
B28: Montecarlo | E28: Blockout | H28: Category 3 | K28: 3210mm | P28: Automate
B29: Santorini | E29: Blockout | H29: Category 3 | K29: 3210mm | P29: Motors
B30: Sedona | E30: Blockout | H30: Category 3 | K30: 3210mm | P30: Power Source | R30: Control | T30: Description | X30: Price | Z30: Price Per
B31: Tropicana | E31: Blockout | H31: Category 3 | K31: 3210mm | P31: Battery | R31: RTS | T31: Zero Li-ion Q 1.1/28 | X31: 200 | Z31: Each
B32: Urbania | E32: Blockout | H32: Category 3 | K32: 3210mm | P32: Battery | R32: RTS | T32: Zero Li-ion Q 2/28 | X32: 240 | Z32: Each
B33: Vogue | E33: Blockout | H33: Category 3 | K33: 3210mm | P33: Battery | R33: Wand | T33: Magnetic Wand Motor | X33: 70 | Z33: Each
P34: 240V (Hardwired) | R34: RTS | T34: E6 6/33 | X34: 170 | Z34: Each
B35: Hardware & Components | P35: 240V (Hardwired) | R35: WC | T35: M6 6/33 | X35: 140 | Z35: Each
B37: Description | J37: Price | L37: Price Per | P37: Remotes
B38: Silent Bottom Rail | J38: =4*1.5 -> 6 | L38: Blind | P38: Type | R38: Description | X38: Price | Z38: Price Per
B39: Stainless steel chain | J39: 8 | L39: Blind | P39: Handheld | R39: 1 Channel White or Black | X39: 65 | Z39: Each
P40: Handheld | R40: 5 Channel White or Black | X40: 70 | Z40: Each
B41: Double Roller Blind - How to Price Correctly | P41: Handheld | R41: 15 Channel White or Black | X41: 80 | Z41: Each
P42: Handheld | R42: 30 Channel White "Push Pro" | X42: 145 | Z42: Each
B43: Double Blind | P43: Wall mount | R43: 5 Channel White or Black | X43: 90 | Z43: Each
B44: Price two single rollers and add bracket cost below | P44: Wand | R44: Control Wand White | X44: 12 | Z44: Each
B45: Description | J45: Price | L45: Price Per | P45: Accessories
B46: Double Brackets (Slimline) | J46: 15 | L46: Each | P46: Description | X46: Price | Z46: Price Per
B47: Double - Linked (4 Blinds) | P47: Motor Cap White or Black to Suit | R47: Pulse Hub for App & Automation Control | X47: 6 | Z47: Each
B48: Price two single - linked (2 Blinds) and add bracket cost below | P48: Interior Sun Sensor | R48: Acmeda DC USB Charger | X48: 65 | Z48: Each
B49: Description | J49: Price | L49: Price Per | P49: Rechargable Motor Charger | X49: 26 | Z49: Each
B50: Double Brackets (Slimline) - Dependent | J50: 30 | L50: Each | P50: Solar Panel | X50: 180 | Z50: Each
B51: Double Brackets (Slimline) - Independent | J51: 45 | L51: Each
B52: Double - Linked (6 Blinds)
B53: Price two single - linked (3 Blinds) and add bracket cost below
B54: Description | J54: Price | L54: Price Per
B55: Double Brackets (Slimline) - Dependant & Independent | J55: 60 | L55: Each
A59: Single Roller Blind
A61: Category One
B62: 610 | C62: 710 | D62: 810 | E62: 910 | F62: 1010 | G62: 1110 | H62: 1210 | I62: 1310 | J62: 1410 | K62: 1510 | L62: 1610 | M62: 1710 | N62: 1810 | O62: 1910 | P62: 2010 | Q62: 2110 | R62: 2210 | S62: 2310 | T62: 2410 | U62: 2510 | V62: 2610 | W62: 2710 | X62: 2810 | Y62: 2910 | Z62: 3010 | AA62: 3110 | AB62: 3210 | AF62: 610 | AG62: 710 | AH62: 810 | AI62: 910 | AJ62: 1010 | AK62: 1110 | AL62: 1210 | AM62: 1310 | AN62: 1410 | AO62: 1510 | AP62: 1610 | AQ62: 1710 | AR62: 1810 | AS62: 1910 | AT62: 2010 | AU62: 2110 | AV62: 2210 | AW62: 2310 | AX62: 2410 | AY62: 2510 | AZ62: 2610 | BA62: 2710 | BB62: 2810 | BC62: 2910 | BD62: 3010 | BE62: 3110 | BF62: 3210 | BG62: 3310
A63: 600 | B63: =ROUNDUP(IFERROR(AF63*(1+$AF$4/100),AF63),0) -> 36 | C63: =ROUNDUP(IFERROR(AG63*(1+$AF$4/100),AG63),0) -> 38 | D63: =ROUNDUP(IFERROR(AH63*(1+$AF$4/100),AH63),0) -> 40 | E63: =ROUNDUP(IFERROR(AI63*(1+$AF$4/100),AI63),0) -> 42 | F63: =ROUNDUP(IFERROR(AJ63*(1+$AF$4/100),AJ63),0) -> 45 | G63: =ROUNDUP(IFERROR(AK63*(1+$AF$4/100),AK63),0) -> 48 | H63: =ROUNDUP(IFERROR(AL63*(1+$AF$4/100),AL63),0) -> 50 | I63: =ROUNDUP(IFERROR(AM63*(1+$AF$4/100),AM63),0) -> 52 | ... AB63: =ROUNDUP(IFERROR(BF63*(1+$AF$4/100),BF63),0) -> 98 | AC63: 600 | AE63: 600 | AF63: 47 | AG63: 50 | AH63: 53 | AI63: 56 | AJ63: 60 | AK63: 63 | AL63: 66 | AM63: 69 | AN63: 73 | AO63: 76 | AP63: 79 | AQ63: 79 | AR63: 82 | AS63: 85 | AT63: 88 | AU63: 91 | AV63: 94 | AW63: 97 | AX63: 100 | AY63: 104 | AZ63: 107 | BA63: 111 | BB63: 114 | BC63: 118 | BD63: 122 | BE63: 126 | BF63: 130 | BG63: 134
A64: 800 | B64: =ROUNDUP(IFERROR(AF64*(1+$AF$4/100),AF64),0) -> 39 | C64: =ROUNDUP(IFERROR(AG64*(1+$AF$4/100),AG64),0) -> 42 | D64: =ROUNDUP(IFERROR(AH64*(1+$AF$4/100),AH64),0) -> 45 | E64: =ROUNDUP(IFERROR(AI64*(1+$AF$4/100),AI64),0) -> 48 | F64: =ROUNDUP(IFERROR(AJ64*(1+$AF$4/100),AJ64),0) -> 51 | G64: =ROUNDUP(IFERROR(AK64*(1+$AF$4/100),AK64),0) -> 54 | H64: =ROUNDUP(IFERROR(AL64*(1+$AF$4/100),AL64),0) -> 57 | I64: =ROUNDUP(IFERROR(AM64*(1+$AF$4/100),AM64),0) -> 57 | ... AB64: =ROUNDUP(IFERROR(BF64*(1+$AF$4/100),BF64),0) -> 114 | AC64: 800 | AE64: 800 | AF64: 51 | AG64: 56 | AH64: 60 | AI64: 64 | AJ64: 68 | AK64: 72 | AL64: 76 | AM64: 76 | AN64: 80 | AO64: 84 | AP64: 88 | AQ64: 91 | AR64: 95 | AS64: 99 | AT64: 103 | AU64: 107 | AV64: 110 | AW64: 114 | AX64: 118 | AY64: 122 | AZ64: 126 | BA64: 130 | BB64: 135 | BC64: 139 | BD64: 143 | BE64: 147 | BF64: 151 | BG64: 155
A65: 1000 | B65: =ROUNDUP(IFERROR(AF65*(1+$AF$4/100),AF65),0) -> 42 | C65: =ROUNDUP(IFERROR(AG65*(1+$AF$4/100),AG65),0) -> 46 | D65: =ROUNDUP(IFERROR(AH65*(1+$AF$4/100),AH65),0) -> 50 | E65: =ROUNDUP(IFERROR(AI65*(1+$AF$4/100),AI65),0) -> 54 | F65: =ROUNDUP(IFERROR(AJ65*(1+$AF$4/100),AJ65),0) -> 54 | G65: =ROUNDUP(IFERROR(AK65*(1+$AF$4/100),AK65),0) -> 58 | H65: =ROUNDUP(IFERROR(AL65*(1+$AF$4/100),AL65),0) -> 61 | I65: =ROUNDUP(IFERROR(AM65*(1+$AF$4/100),AM65),0) -> 65 | ... AB65: =ROUNDUP(IFERROR(BF65*(1+$AF$4/100),BF65),0) -> 132 | AC65: 1000 | AE65: 1000 | AF65: 56 | AG65: 61 | AH65: 66 | AI65: 71 | AJ65: 72 | AK65: 77 | AL65: 81 | AM65: 86 | AN65: 90 | AO65: 95 | AP65: 99 | AQ65: 104 | AR65: 108 | AS65: 113 | AT65: 118 | AU65: 122 | AV65: 127 | AW65: 131 | AX65: 136 | AY65: 140 | AZ65: 145 | BA65: 150 | BB65: 155 | BC65: 160 | BD65: 165 | BE65: 170 | BF65: 175 | BG65: 180
A66: 1200 | B66: =ROUNDUP(IFERROR(AF66*(1+$AF$4/100),AF66),0) -> 46 | C66: =ROUNDUP(IFERROR(AG66*(1+$AF$4/100),AG66),0) -> 51 | D66: =ROUNDUP(IFERROR(AH66*(1+$AF$4/100),AH66),0) -> 54 | E66: =ROUNDUP(IFERROR(AI66*(1+$AF$4/100),AI66),0) -> 57 | F66: =ROUNDUP(IFERROR(AJ66*(1+$AF$4/100),AJ66),0) -> 60 | G66: =ROUNDUP(IFERROR(AK66*(1+$AF$4/100),AK66),0) -> 64 | H66: =ROUNDUP(IFERROR(AL66*(1+$AF$4/100),AL66),0) -> 68 | I66: =ROUNDUP(IFERROR(AM66*(1+$AF$4/100),AM66),0) -> 72 | ... AB66: =ROUNDUP(IFERROR(BF66*(1+$AF$4/100),BF66),0) -> 150 | AC66: 1200 | AE66: 1200 | AF66: 61 | AG66: 67 | AH66: 72 | AI66: 75 | AJ66: 80 | AK66: 85 | AL66: 90 | AM66: 96 | AN66: 101 | AO66: 106 | AP66: 111 | AQ66: 117 | AR66: 122 | AS66: 127 | AT66: 132 | AU66: 137 | AV66: 143 | AW66: 148 | AX66: 153 | AY66: 159 | AZ66: 164 | BA66: 170 | BB66: 175 | BC66: 181 | BD66: 187 | BE66: 193 | BF66: 199 | BG66: 205
A67: 1400 | B67: =ROUNDUP(IFERROR(AF67*(1+$AF$4/100),AF67),0) -> 50 | C67: =ROUNDUP(IFERROR(AG67*(1+$AF$4/100),AG67),0) -> 55 | D67: =ROUNDUP(IFERROR(AH67*(1+$AF$4/100),AH67),0) -> 57 | E67: =ROUNDUP(IFERROR(AI67*(1+$AF$4/100),AI67),0) -> 61 | F67: =ROUNDUP(IFERROR(AJ67*(1+$AF$4/100),AJ67),0) -> 66 | G67: =ROUNDUP(IFERROR(AK67*(1+$AF$4/100),AK67),0) -> 70 | H67: =ROUNDUP(IFERROR(AL67*(1+$AF$4/100),AL67),0) -> 75 | I67: =ROUNDUP(IFERROR(AM67*(1+$AF$4/100),AM67),0) -> 79 | ... AB67: =ROUNDUP(IFERROR(BF67*(1+$AF$4/100),BF67),0) -> 165 | AC67: 1400 | AE67: 1400 | AF67: 66 | AG67: 73 | AH67: 75 | AI67: 81 | AJ67: 87 | AK67: 93 | AL67: 99 | AM67: 105 | AN67: 111 | AO67: 117 | AP67: 123 | AQ67: 129 | AR67: 135 | AS67: 141 | AT67: 147 | AU67: 153 | AV67: 159 | AW67: 165 | AX67: 171 | AY67: 177 | AZ67: 183 | BA67: 190 | BB67: 196 | BC67: 202 | BD67: 208 | BE67: 214 | BF67: 220 | BG67: 226
A68: 1600 | B68: =ROUNDUP(IFERROR(AF68*(1+$AF$4/100),AF68),0) -> 54 | C68: =ROUNDUP(IFERROR(AG68*(1+$AF$4/100),AG68),0) -> 57 | D68: =ROUNDUP(IFERROR(AH68*(1+$AF$4/100),AH68),0) -> 62 | E68: =ROUNDUP(IFERROR(AI68*(1+$AF$4/100),AI68),0) -> 66 | F68: =ROUNDUP(IFERROR(AJ68*(1+$AF$4/100),AJ68),0) -> 72 | G68: =ROUNDUP(IFERROR(AK68*(1+$AF$4/100),AK68),0) -> 77 | H68: =ROUNDUP(IFERROR(AL68*(1+$AF$4/100),AL68),0) -> 81 | I68: =ROUNDUP(IFERROR(AM68*(1+$AF$4/100),AM68),0) -> 87 | ... AB68: =ROUNDUP(IFERROR(BF68*(1+$AF$4/100),BF68),0) -> 183 | AC68: 1600 | AE68: 1600 | AF68: 71 | AG68: 75 | AH68: 82 | AI68: 88 | AJ68: 95 | AK68: 102 | AL68: 108 | AM68: 115 | AN68: 122 | AO68: 128 | AP68: 135 | AQ68: 142 | AR68: 148 | AS68: 155 | AT68: 162 | AU68: 168 | AV68: 175 | AW68: 182 | AX68: 188 | AY68: 195 | AZ68: 202 | BA68: 209 | BB68: 216 | BC68: 223 | BD68: 230 | BE68: 237 | BF68: 244 | BG68: 251
A69: 1800 | B69: =ROUNDUP(IFERROR(AF69*(1+$AF$4/100),AF69),0) -> 55 | C69: =ROUNDUP(IFERROR(AG69*(1+$AF$4/100),AG69),0) -> 60 | D69: =ROUNDUP(IFERROR(AH69*(1+$AF$4/100),AH69),0) -> 66 | E69: =ROUNDUP(IFERROR(AI69*(1+$AF$4/100),AI69),0) -> 72 | F69: =ROUNDUP(IFERROR(AJ69*(1+$AF$4/100),AJ69),0) -> 77 | G69: =ROUNDUP(IFERROR(AK69*(1+$AF$4/100),AK69),0) -> 83 | H69: =ROUNDUP(IFERROR(AL69*(1+$AF$4/100),AL69),0) -> 88 | I69: =ROUNDUP(IFERROR(AM69*(1+$AF$4/100),AM69),0) -> 94 | ... AB69: =ROUNDUP(IFERROR(BF69*(1+$AF$4/100),BF69),0) -> 202 | AC69: 1800 | AE69: 1800 | AF69: 73 | AG69: 80 | AH69: 88 | AI69: 95 | AJ69: 102 | AK69: 110 | AL69: 117 | AM69: 125 | AN69: 132 | AO69: 139 | AP69: 147 | AQ69: 154 | AR69: 162 | AS69: 169 | AT69: 176 | AU69: 184 | AV69: 191 | AW69: 199 | AX69: 206 | AY69: 214 | AZ69: 221 | BA69: 229 | BB69: 237 | BC69: 245 | BD69: 253 | BE69: 261 | BF69: 269 | BG69: 277
A70: 2000 | B70: =ROUNDUP(IFERROR(AF70*(1+$AF$4/100),AF70),0) -> 58 | C70: =ROUNDUP(IFERROR(AG70*(1+$AF$4/100),AG70),0) -> 65 | D70: =ROUNDUP(IFERROR(AH70*(1+$AF$4/100),AH70),0) -> 71 | E70: =ROUNDUP(IFERROR(AI70*(1+$AF$4/100),AI70),0) -> 77 | F70: =ROUNDUP(IFERROR(AJ70*(1+$AF$4/100),AJ70),0) -> 83 | G70: =ROUNDUP(IFERROR(AK70*(1+$AF$4/100),AK70),0) -> 89 | H70: =ROUNDUP(IFERROR(AL70*(1+$AF$4/100),AL70),0) -> 95 | I70: =ROUNDUP(IFERROR(AM70*(1+$AF$4/100),AM70),0) -> 101 | ... AB70: =ROUNDUP(IFERROR(BF70*(1+$AF$4/100),BF70),0) -> 220 | AC70: 2000 | AE70: 2000 | AF70: 77 | AG70: 86 | AH70: 94 | AI70: 102 | AJ70: 110 | AK70: 118 | AL70: 126 | AM70: 134 | AN70: 142 | AO70: 150 | AP70: 159 | AQ70: 167 | AR70: 175 | AS70: 183 | AT70: 191 | AU70: 199 | AV70: 207 | AW70: 215 | AX70: 223 | AY70: 232 | AZ70: 240 | BA70: 249 | BB70: 257 | BC70: 266 | BD70: 275 | BE70: 284 | BF70: 293 | BG70: 302
A71: 2200 | B71: =ROUNDUP(IFERROR(AF71*(1+$AF$4/100),AF71),0) -> 62 | C71: =ROUNDUP(IFERROR(AG71*(1+$AF$4/100),AG71),0) -> 69 | D71: =ROUNDUP(IFERROR(AH71*(1+$AF$4/100),AH71),0) -> 75 | E71: =ROUNDUP(IFERROR(AI71*(1+$AF$4/100),AI71),0) -> 82 | F71: =ROUNDUP(IFERROR(AJ71*(1+$AF$4/100),AJ71),0) -> 88 | G71: =ROUNDUP(IFERROR(AK71*(1+$AF$4/100),AK71),0) -> 95 | H71: =ROUNDUP(IFERROR(AL71*(1+$AF$4/100),AL71),0) -> 102 | I71: =ROUNDUP(IFERROR(AM71*(1+$AF$4/100),AM71),0) -> 108 | ... AB71: =ROUNDUP(IFERROR(BF71*(1+$AF$4/100),BF71),0) -> 234 | AC71: 2200 | AE71: 2200 | AF71: 82 | AG71: 91 | AH71: 100 | AI71: 109 | AJ71: 117 | AK71: 126 | AL71: 135 | AM71: 144 | AN71: 153 | AO71: 162 | AP71: 170 | AQ71: 179 | AR71: 188 | AS71: 197 | AT71: 206 | AU71: 215 | AV71: 223 | AW71: 232 | AX71: 241 | AY71: 250 | AZ71: 259 | BA71: 270 | BB71: 279 | BC71: 287 | BD71: 295 | BE71: 303 | BF71: 311 | BG71: 319
A72: 2400 | B72: =ROUNDUP(IFERROR(AF72*(1+$AF$4/100),AF72),0) -> 66 | C72: =ROUNDUP(IFERROR(AG72*(1+$AF$4/100),AG72),0) -> 72 | D72: =ROUNDUP(IFERROR(AH72*(1+$AF$4/100),AH72),0) -> 80 | E72: =ROUNDUP(IFERROR(AI72*(1+$AF$4/100),AI72),0) -> 87 | F72: =ROUNDUP(IFERROR(AJ72*(1+$AF$4/100),AJ72),0) -> 94 | G72: =ROUNDUP(IFERROR(AK72*(1+$AF$4/100),AK72),0) -> 101 | H72: =ROUNDUP(IFERROR(AL72*(1+$AF$4/100),AL72),0) -> 108 | I72: =ROUNDUP(IFERROR(AM72*(1+$AF$4/100),AM72),0) -> 116 | ... AB72: =ROUNDUP(IFERROR(BF72*(1+$AF$4/100),BF72),0) -> 249 | AC72: 2400 | AE72: 2400 | AF72: 87 | AG72: 96 | AH72: 106 | AI72: 115 | AJ72: 125 | AK72: 134 | AL72: 144 | AM72: 154 | AN72: 163 | AO72: 173 | AP72: 182 | AQ72: 192 | AR72: 201 | AS72: 211 | AT72: 220 | AU72: 230 | AV72: 240 | AW72: 249 | AX72: 259 | AY72: 268 | AZ72: 277 | BA72: 286 | BB72: 295 | BC72: 304 | BD72: 313 | BE72: 322 | BF72: 331 | BG72: 340
A73: 2600 | B73: =ROUNDUP(IFERROR(AF73*(1+$AF$4/100),AF73),0) -> 69 | C73: =ROUNDUP(IFERROR(AG73*(1+$AF$4/100),AG73),0) -> 77 | D73: =ROUNDUP(IFERROR(AH73*(1+$AF$4/100),AH73),0) -> 84 | E73: =ROUNDUP(IFERROR(AI73*(1+$AF$4/100),AI73),0) -> 92 | F73: =ROUNDUP(IFERROR(AJ73*(1+$AF$4/100),AJ73),0) -> 99 | G73: =ROUNDUP(IFERROR(AK73*(1+$AF$4/100),AK73),0) -> 108 | H73: =ROUNDUP(IFERROR(AL73*(1+$AF$4/100),AL73),0) -> 115 | I73: =ROUNDUP(IFERROR(AM73*(1+$AF$4/100),AM73),0) -> 123 | ... AB73: =ROUNDUP(IFERROR(BF73*(1+$AF$4/100),BF73),0) -> 264 | AC73: 2600 | AE73: 2600 | AF73: 91 | AG73: 102 | AH73: 112 | AI73: 122 | AJ73: 132 | AK73: 143 | AL73: 153 | AM73: 163 | AN73: 174 | AO73: 184 | AP73: 194 | AQ73: 204 | AR73: 215 | AS73: 225 | AT73: 235 | AU73: 245 | AV73: 256 | AW73: 263 | AX73: 273 | AY73: 283 | AZ73: 292 | BA73: 302 | BB73: 312 | BC73: 322 | BD73: 332 | BE73: 342 | BF73: 352 | BG73: 362
A74: 2800 | B74: =ROUNDUP(IFERROR(AF74*(1+$AF$4/100),AF74),0) -> 72 | C74: =ROUNDUP(IFERROR(AG74*(1+$AF$4/100),AG74),0) -> 81 | D74: =ROUNDUP(IFERROR(AH74*(1+$AF$4/100),AH74),0) -> 89 | E74: =ROUNDUP(IFERROR(AI74*(1+$AF$4/100),AI74),0) -> 97 | F74: =ROUNDUP(IFERROR(AJ74*(1+$AF$4/100),AJ74),0) -> 105 | G74: =ROUNDUP(IFERROR(AK74*(1+$AF$4/100),AK74),0) -> 114 | H74: =ROUNDUP(IFERROR(AL74*(1+$AF$4/100),AL74),0) -> 122 | I74: =ROUNDUP(IFERROR(AM74*(1+$AF$4/100),AM74),0) -> 130 | ... AB74: =ROUNDUP(IFERROR(BF74*(1+$AF$4/100),BF74),0) -> 279 | AC74: 2800 | AE74: 2800 | AF74: 96 | AG74: 107 | AH74: 118 | AI74: 129 | AJ74: 140 | AK74: 151 | AL74: 162 | AM74: 173 | AN74: 184 | AO74: 195 | AP74: 206 | AQ74: 217 | AR74: 228 | AS74: 239 | AT74: 250 | AU74: 255 | AV74: 265 | AW74: 277 | AX74: 287 | AY74: 298 | AZ74: 308 | BA74: 318 | BB74: 328 | BC74: 339 | BD74: 350 | BE74: 361 | BF74: 372 | BG74: 383
... A76: 3200 | B76: =ROUNDUP(IFERROR(AF76*(1+$AF$4/100),AF76),0) -> 79 | C76: =ROUNDUP(IFERROR(AG76*(1+$AF$4/100),AG76),0) -> 89 | D76: =ROUNDUP(IFERROR(AH76*(1+$AF$4/100),AH76),0) -> 98 | E76: =ROUNDUP(IFERROR(AI76*(1+$AF$4/100),AI76),0) -> 108 | F76: =ROUNDUP(IFERROR(AJ76*(1+$AF$4/100),AJ76),0) -> 117 | G76: =ROUNDUP(IFERROR(AK76*(1+$AF$4/100),AK76),0) -> 126 | H76: =ROUNDUP(IFERROR(AL76*(1+$AF$4/100),AL76),0) -> 135 | I76: =ROUNDUP(IFERROR(AM76*(1+$AF$4/100),AM76),0) -> 144 | ... AB76: =ROUNDUP(IFERROR(BF76*(1+$AF$4/100),BF76),0) -> 305 | AC76: 3200 | AE76: 3200 | AF76: 105 | AG76: 118 | AH76: 130 | AI76: 143 | AJ76: 155 | AK76: 167 | AL76: 180 | AM76: 192 | AN76: 205 | AO76: 217 | AP76: 230 | AQ76: 242 | AR76: 254 | AS76: 257 | AT76: 269 | AU76: 280 | AV76: 291 | AW76: 305 | AX76: 316 | AY76: 327 | AZ76: 339 | BA76: 350 | BB76: 362 | BC76: 373 | BD76: 384 | BE76: 395 | BF76: 406 | BG76: 417
A79: Category Two
B80: 610 | C80: 710 | D80: 810 | E80: 910 | F80: 1010 | G80: 1110 | H80: 1210 | I80: 1310 | J80: 1410 | K80: 1510 | L80: 1610 | M80: 1710 | N80: 1810 | O80: 1910 | P80: 2010 | Q80: 2110 | R80: 2210 | S80: 2310 | T80: 2410 | U80: 2510 | V80: 2610 | W80: 2710 | X80: 2810 | Y80: 2910 | Z80: 3010 | AA80: 3110 | AB80: 3210 | AF80: 610 | AG80: 710 | AH80: 810 | AI80: 910 | AJ80: 1010 | AK80: 1110 | AL80: 1210 | AM80: 1310 | AN80: 1410 | AO80: 1510 | AP80: 1610 | AQ80: 1710 | AR80: 1810 | AS80: 1910 | AT80: 2010 | AU80: 2110 | AV80: 2210 | AW80: 2310 | AX80: 2410 | AY80: 2510 | AZ80: 2610 | BA80: 2710 | BB80: 2810 | BC80: 2910 | BD80: 3010 | BE80: 3110 | BF80: 3210 | BG80: 3310
A81: 600 | B81: =ROUNDUP(IFERROR(AF81*(1+$AF$5/100),AF81),0) -> 42 | C81: =ROUNDUP(IFERROR(AG81*(1+$AF$5/100),AG81),0) -> 45 | D81: =ROUNDUP(IFERROR(AH81*(1+$AF$5/100),AH81),0) -> 48 | E81: =ROUNDUP(IFERROR(AI81*(1+$AF$5/100),AI81),0) -> 51 | F81: =ROUNDUP(IFERROR(AJ81*(1+$AF$5/100),AJ81),0) -> 54 | G81: =ROUNDUP(IFERROR(AK81*(1+$AF$5/100),AK81),0) -> 57 | H81: =ROUNDUP(IFERROR(AL81*(1+$AF$5/100),AL81),0) -> 60 | I81: =ROUNDUP(IFERROR(AM81*(1+$AF$5/100),AM81),0) -> 63 | ... AB81: =ROUNDUP(IFERROR(BF81*(1+$AF$5/100),BF81),0) -> 123 | AC81: 600 | AE81: 600 | AF81: 55 | AG81: 59 | AH81: 63 | AI81: 68 | AJ81: 72 | AK81: 76 | AL81: 80 | AM81: 84 | AN81: 88 | AO81: 92 | AP81: 96 | AQ81: 96 | AR81: 100 | AS81: 103 | AT81: 107 | AU81: 111 | AV81: 115 | AW81: 119 | AX81: 123 | AY81: 130 | AZ81: 135 | BA81: 139 | BB81: 143 | BC81: 148 | BD81: 153 | BE81: 158 | BF81: 163 | BG81: 168
A82: 800 | B82: =ROUNDUP(IFERROR(AF82*(1+$AF$5/100),AF82),0) -> 46 | C82: =ROUNDUP(IFERROR(AG82*(1+$AF$5/100),AG82),0) -> 50 | D82: =ROUNDUP(IFERROR(AH82*(1+$AF$5/100),AH82),0) -> 54 | E82: =ROUNDUP(IFERROR(AI82*(1+$AF$5/100),AI82),0) -> 58 | F82: =ROUNDUP(IFERROR(AJ82*(1+$AF$5/100),AJ82),0) -> 62 | G82: =ROUNDUP(IFERROR(AK82*(1+$AF$5/100),AK82),0) -> 66 | H82: =ROUNDUP(IFERROR(AL82*(1+$AF$5/100),AL82),0) -> 69 | I82: =ROUNDUP(IFERROR(AM82*(1+$AF$5/100),AM82),0) -> 69 | ... AB82: =ROUNDUP(IFERROR(BF82*(1+$AF$5/100),BF82),0) -> 142 | AC82: 800 | AE82: 800 | AF82: 61 | AG82: 66 | AH82: 71 | AI82: 77 | AJ82: 82 | AK82: 87 | AL82: 92 | AM82: 92 | AN82: 97 | AO82: 102 | AP82: 107 | AQ82: 111 | AR82: 116 | AS82: 121 | AT82: 126 | AU82: 130 | AV82: 135 | AW82: 140 | AX82: 145 | AY82: 153 | AZ82: 159 | BA82: 164 | BB82: 169 | BC82: 174 | BD82: 179 | BE82: 184 | BF82: 189 | BG82: 194
A83: 1000 | B83: =ROUNDUP(IFERROR(AF83*(1+$AF$5/100),AF83),0) -> 51 | C83: =ROUNDUP(IFERROR(AG83*(1+$AF$5/100),AG83),0) -> 56 | D83: =ROUNDUP(IFERROR(AH83*(1+$AF$5/100),AH83),0) -> 60 | E83: =ROUNDUP(IFERROR(AI83*(1+$AF$5/100),AI83),0) -> 65 | F83: =ROUNDUP(IFERROR(AJ83*(1+$AF$5/100),AJ83),0) -> 66 | G83: =ROUNDUP(IFERROR(AK83*(1+$AF$5/100),AK83),0) -> 70 | H83: =ROUNDUP(IFERROR(AL83*(1+$AF$5/100),AL83),0) -> 75 | I83: =ROUNDUP(IFERROR(AM83*(1+$AF$5/100),AM83),0) -> 79 | ... AB83: =ROUNDUP(IFERROR(BF83*(1+$AF$5/100),BF83),0) -> 165 | AC83: 1000 | AE83: 1000 | AF83: 68 | AG83: 74 | AH83: 80 | AI83: 86 | AJ83: 88 | AK83: 93 | AL83: 99 | AM83: 105 | AN83: 110 | AO83: 116 | AP83: 121 | AQ83: 127 | AR83: 133 | AS83: 138 | AT83: 144 | AU83: 150 | AV83: 155 | AW83: 161 | AX83: 167 | AY83: 176 | AZ83: 182 | BA83: 188 | BB83: 195 | BC83: 201 | BD83: 207 | BE83: 213 | BF83: 219 | BG83: 225
A84: 1200 | B84: =ROUNDUP(IFERROR(AF84*(1+$AF$5/100),AF84),0) -> 56 | C84: =ROUNDUP(IFERROR(AG84*(1+$AF$5/100),AG84),0) -> 61 | D84: =ROUNDUP(IFERROR(AH84*(1+$AF$5/100),AH84),0) -> 66 | E84: =ROUNDUP(IFERROR(AI84*(1+$AF$5/100),AI84),0) -> 68 | F84: =ROUNDUP(IFERROR(AJ84*(1+$AF$5/100),AJ84),0) -> 73 | G84: =ROUNDUP(IFERROR(AK84*(1+$AF$5/100),AK84),0) -> 78 | H84: =ROUNDUP(IFERROR(AL84*(1+$AF$5/100),AL84),0) -> 83 | I84: =ROUNDUP(IFERROR(AM84*(1+$AF$5/100),AM84),0) -> 88 | ... AB84: =ROUNDUP(IFERROR(BF84*(1+$AF$5/100),BF84),0) -> 186 | AC84: 1200 | AE84: 1200 | AF84: 74 | AG84: 81 | AH84: 88 | AI84: 90 | AJ84: 97 | AK84: 103 | AL84: 110 | AM84: 117 | AN84: 123 | AO84: 130 | AP84: 136 | AQ84: 143 | AR84: 149 | AS84: 156 | AT84: 163 | AU84: 169 | AV84: 176 | AW84: 182 | AX84: 189 | AY84: 199 | AZ84: 206 | BA84: 213 | BB84: 220 | BC84: 227 | BD84: 234 | BE84: 241 | BF84: 248 | BG84: 255
A85: 1400 | B85: =ROUNDUP(IFERROR(AF85*(1+$AF$5/100),AF85),0) -> 60 | C85: =ROUNDUP(IFERROR(AG85*(1+$AF$5/100),AG85),0) -> 66 | D85: =ROUNDUP(IFERROR(AH85*(1+$AF$5/100),AH85),0) -> 69 | E85: =ROUNDUP(IFERROR(AI85*(1+$AF$5/100),AI85),0) -> 75 | F85: =ROUNDUP(IFERROR(AJ85*(1+$AF$5/100),AJ85),0) -> 80 | G85: =ROUNDUP(IFERROR(AK85*(1+$AF$5/100),AK85),0) -> 86 | H85: =ROUNDUP(IFERROR(AL85*(1+$AF$5/100),AL85),0) -> 91 | I85: =ROUNDUP(IFERROR(AM85*(1+$AF$5/100),AM85),0) -> 97 | ... AB85: =ROUNDUP(IFERROR(BF85*(1+$AF$5/100),BF85),0) -> 209 | AC85: 1400 | AE85: 1400 | AF85: 80 | AG85: 88 | AH85: 91 | AI85: 99 | AJ85: 106 | AK85: 114 | AL85: 121 | AM85: 129 | AN85: 136 | AO85: 144 | AP85: 151 | AQ85: 159 | AR85: 166 | AS85: 173 | AT85: 181 | AU85: 188 | AV85: 196 | AW85: 203 | AX85: 211 | AY85: 222 | AZ85: 230 | BA85: 238 | BB85: 246 | BC85: 254 | BD85: 262 | BE85: 270 | BF85: 278 | BG85: 286
A86: 1600 | B86: =ROUNDUP(IFERROR(AF86*(1+$AF$5/100),AF86),0) -> 65 | C86: =ROUNDUP(IFERROR(AG86*(1+$AF$5/100),AG86),0) -> 69 | D86: =ROUNDUP(IFERROR(AH86*(1+$AF$5/100),AH86),0) -> 75 | E86: =ROUNDUP(IFERROR(AI86*(1+$AF$5/100),AI86),0) -> 81 | F86: =ROUNDUP(IFERROR(AJ86*(1+$AF$5/100),AJ86),0) -> 87 | G86: =ROUNDUP(IFERROR(AK86*(1+$AF$5/100),AK86),0) -> 93 | H86: =ROUNDUP(IFERROR(AL86*(1+$AF$5/100),AL86),0) -> 99 | I86: =ROUNDUP(IFERROR(AM86*(1+$AF$5/100),AM86),0) -> 106 | ... AB86: =ROUNDUP(IFERROR(BF86*(1+$AF$5/100),BF86),0) -> 231 | AC86: 1600 | AE86: 1600 | AF86: 86 | AG86: 91 | AH86: 99 | AI86: 107 | AJ86: 116 | AK86: 124 | AL86: 132 | AM86: 141 | AN86: 149 | AO86: 158 | AP86: 166 | AQ86: 174 | AR86: 183 | AS86: 191 | AT86: 199 | AU86: 208 | AV86: 216 | AW86: 224 | AX86: 233 | AY86: 245 | AZ86: 254 | BA86: 263 | BB86: 271 | BC86: 280 | BD86: 289 | BE86: 298 | BF86: 307 | BG86: 316
A87: 1800 | B87: =ROUNDUP(IFERROR(AF87*(1+$AF$5/100),AF87),0) -> 66 | C87: =ROUNDUP(IFERROR(AG87*(1+$AF$5/100),AG87),0) -> 73 | D87: =ROUNDUP(IFERROR(AH87*(1+$AF$5/100),AH87),0) -> 81 | E87: =ROUNDUP(IFERROR(AI87*(1+$AF$5/100),AI87),0) -> 87 | F87: =ROUNDUP(IFERROR(AJ87*(1+$AF$5/100),AJ87),0) -> 94 | G87: =ROUNDUP(IFERROR(AK87*(1+$AF$5/100),AK87),0) -> 101 | H87: =ROUNDUP(IFERROR(AL87*(1+$AF$5/100),AL87),0) -> 108 | I87: =ROUNDUP(IFERROR(AM87*(1+$AF$5/100),AM87),0) -> 115 | ... AB87: =ROUNDUP(IFERROR(BF87*(1+$AF$5/100),BF87),0) -> 253 | AC87: 1800 | AE87: 1800 | AF87: 88 | AG87: 97 | AH87: 107 | AI87: 116 | AJ87: 125 | AK87: 134 | AL87: 144 | AM87: 153 | AN87: 162 | AO87: 171 | AP87: 181 | AQ87: 190 | AR87: 199 | AS87: 208 | AT87: 218 | AU87: 227 | AV87: 236 | AW87: 246 | AX87: 255 | AY87: 268 | AZ87: 278 | BA87: 287 | BB87: 297 | BC87: 307 | BD87: 317 | BE87: 327 | BF87: 337 | BG87: 347
A88: 2000 | B88: =ROUNDUP(IFERROR(AF88*(1+$AF$5/100),AF88),0) -> 71 | C88: =ROUNDUP(IFERROR(AG88*(1+$AF$5/100),AG88),0) -> 78 | D88: =ROUNDUP(IFERROR(AH88*(1+$AF$5/100),AH88),0) -> 86 | E88: =ROUNDUP(IFERROR(AI88*(1+$AF$5/100),AI88),0) -> 93 | F88: =ROUNDUP(IFERROR(AJ88*(1+$AF$5/100),AJ88),0) -> 102 | G88: =ROUNDUP(IFERROR(AK88*(1+$AF$5/100),AK88),0) -> 109 | H88: =ROUNDUP(IFERROR(AL88*(1+$AF$5/100),AL88),0) -> 117 | I88: =ROUNDUP(IFERROR(AM88*(1+$AF$5/100),AM88),0) -> 124 | ... AB88: =ROUNDUP(IFERROR(BF88*(1+$AF$5/100),BF88),0) -> 273 | AC88: 2000 | AE88: 2000 | AF88: 94 | AG88: 104 | AH88: 114 | AI88: 124 | AJ88: 135 | AK88: 145 | AL88: 155 | AM88: 165 | AN88: 175 | AO88: 185 | AP88: 196 | AQ88: 206 | AR88: 216 | AS88: 226 | AT88: 236 | AU88: 246 | AV88: 256 | AW88: 267 | AX88: 277 | AY88: 291 | AZ88: 301 | BA88: 312 | BB88: 323 | BC88: 333 | BD88: 343 | BE88: 353 | BF88: 363 | BG88: 373
A89: 2200 | B89: =ROUNDUP(IFERROR(AF89*(1+$AF$5/100),AF89),0) -> 75 | C89: =ROUNDUP(IFERROR(AG89*(1+$AF$5/100),AG89),0) -> 84 | D89: =ROUNDUP(IFERROR(AH89*(1+$AF$5/100),AH89),0) -> 92 | E89: =ROUNDUP(IFERROR(AI89*(1+$AF$5/100),AI89),0) -> 100 | F89: =ROUNDUP(IFERROR(AJ89*(1+$AF$5/100),AJ89),0) -> 108 | G89: =ROUNDUP(IFERROR(AK89*(1+$AF$5/100),AK89),0) -> 117 | H89: =ROUNDUP(IFERROR(AL89*(1+$AF$5/100),AL89),0) -> 125 | I89: =ROUNDUP(IFERROR(AM89*(1+$AF$5/100),AM89),0) -> 133 | ... AB89: =ROUNDUP(IFERROR(BF89*(1+$AF$5/100),BF89),0) -> 296 | AC89: 2200 | AE89: 2200 | AF89: 100 | AG89: 111 | AH89: 122 | AI89: 133 | AJ89: 144 | AK89: 155 | AL89: 166 | AM89: 177 | AN89: 188 | AO89: 199 | AP89: 210 | AQ89: 221 | AR89: 232 | AS89: 243 | AT89: 255 | AU89: 266 | AV89: 277 | AW89: 288 | AX89: 299 | AY89: 314 | AZ89: 325 | BA89: 339 | BB89: 350 | BC89: 361 | BD89: 372 | BE89: 383 | BF89: 394 | BG89: 405
A90: 2400 | B90: =ROUNDUP(IFERROR(AF90*(1+$AF$5/100),AF90),0) -> 80 | C90: =ROUNDUP(IFERROR(AG90*(1+$AF$5/100),AG90),0) -> 89 | D90: =ROUNDUP(IFERROR(AH90*(1+$AF$5/100),AH90),0) -> 97 | E90: =ROUNDUP(IFERROR(AI90*(1+$AF$5/100),AI90),0) -> 106 | F90: =ROUNDUP(IFERROR(AJ90*(1+$AF$5/100),AJ90),0) -> 115 | G90: =ROUNDUP(IFERROR(AK90*(1+$AF$5/100),AK90),0) -> 124 | H90: =ROUNDUP(IFERROR(AL90*(1+$AF$5/100),AL90),0) -> 133 | I90: =ROUNDUP(IFERROR(AM90*(1+$AF$5/100),AM90),0) -> 142 | ... AB90: =ROUNDUP(IFERROR(BF90*(1+$AF$5/100),BF90),0) -> 315 | AC90: 2400 | AE90: 2400 | AF90: 106 | AG90: 118 | AH90: 129 | AI90: 141 | AJ90: 153 | AK90: 165 | AL90: 177 | AM90: 189 | AN90: 201 | AO90: 213 | AP90: 225 | AQ90: 237 | AR90: 249 | AS90: 261 | AT90: 273 | AU90: 285 | AV90: 297 | AW90: 309 | AX90: 321 | AY90: 336 | AZ90: 348 | BA90: 360 | BB90: 371 | BC90: 383 | BD90: 395 | BE90: 407 | BF90: 419 | BG90: 431
A91: 2600 | B91: =ROUNDUP(IFERROR(AF91*(1+$AF$5/100),AF91),0) -> 84 | C91: =ROUNDUP(IFERROR(AG91*(1+$AF$5/100),AG91),0) -> 93 | D91: =ROUNDUP(IFERROR(AH91*(1+$AF$5/100),AH91),0) -> 103 | E91: =ROUNDUP(IFERROR(AI91*(1+$AF$5/100),AI91),0) -> 113 | F91: =ROUNDUP(IFERROR(AJ91*(1+$AF$5/100),AJ91),0) -> 123 | G91: =ROUNDUP(IFERROR(AK91*(1+$AF$5/100),AK91),0) -> 132 | H91: =ROUNDUP(IFERROR(AL91*(1+$AF$5/100),AL91),0) -> 142 | I91: =ROUNDUP(IFERROR(AM91*(1+$AF$5/100),AM91),0) -> 151 | ... AB91: =ROUNDUP(IFERROR(BF91*(1+$AF$5/100),BF91),0) -> 331 | AC91: 2600 | AE91: 2600 | AF91: 111 | AG91: 124 | AH91: 137 | AI91: 150 | AJ91: 163 | AK91: 176 | AL91: 189 | AM91: 201 | AN91: 214 | AO91: 227 | AP91: 240 | AQ91: 253 | AR91: 266 | AS91: 278 | AT91: 291 | AU91: 304 | AV91: 317 | AW91: 331 | AX91: 343 | AY91: 356 | AZ91: 368 | BA91: 380 | BB91: 393 | BC91: 405 | BD91: 417 | BE91: 429 | BF91: 441 | BG91: 453
A92: 2800 | B92: =ROUNDUP(IFERROR(AF92*(1+$AF$5/100),AF92),0) -> 88 | C92: =ROUNDUP(IFERROR(AG92*(1+$AF$5/100),AG92),0) -> 99 | D92: =ROUNDUP(IFERROR(AH92*(1+$AF$5/100),AH92),0) -> 109 | E92: =ROUNDUP(IFERROR(AI92*(1+$AF$5/100),AI92),0) -> 119 | F92: =ROUNDUP(IFERROR(AJ92*(1+$AF$5/100),AJ92),0) -> 129 | G92: =ROUNDUP(IFERROR(AK92*(1+$AF$5/100),AK92),0) -> 140 | H92: =ROUNDUP(IFERROR(AL92*(1+$AF$5/100),AL92),0) -> 150 | I92: =ROUNDUP(IFERROR(AM92*(1+$AF$5/100),AM92),0) -> 160 | ... AB92: =ROUNDUP(IFERROR(BF92*(1+$AF$5/100),BF92),0) -> 350 | AC92: 2800 | AE92: 2800 | AF92: 117 | AG92: 131 | AH92: 145 | AI92: 158 | AJ92: 172 | AK92: 186 | AL92: 200 | AM92: 213 | AN92: 227 | AO92: 241 | AP92: 255 | AQ92: 268 | AR92: 282 | AS92: 296 | AT92: 310 | AU92: 320 | AV92: 333 | AW92: 349 | AX92: 362 | AY92: 375 | AZ92: 388 | BA92: 401 | BB92: 414 | BC92: 427 | BD92: 440 | BE92: 453 | BF92: 466 | BG92: 479
... A94: 3200 | B94: =ROUNDUP(IFERROR(AF94*(1+$AF$5/100),AF94),0) -> 97 | C94: =ROUNDUP(IFERROR(AG94*(1+$AF$5/100),AG94),0) -> 108 | D94: =ROUNDUP(IFERROR(AH94*(1+$AF$5/100),AH94),0) -> 120 | E94: =ROUNDUP(IFERROR(AI94*(1+$AF$5/100),AI94),0) -> 132 | F94: =ROUNDUP(IFERROR(AJ94*(1+$AF$5/100),AJ94),0) -> 144 | G94: =ROUNDUP(IFERROR(AK94*(1+$AF$5/100),AK94),0) -> 156 | H94: =ROUNDUP(IFERROR(AL94*(1+$AF$5/100),AL94),0) -> 167 | I94: =ROUNDUP(IFERROR(AM94*(1+$AF$5/100),AM94),0) -> 179 | ... AB94: =ROUNDUP(IFERROR(BF94*(1+$AF$5/100),BF94),0) -> 388 | AC94: 3200 | AE94: 3200 | AF94: 129 | AG94: 144 | AH94: 160 | AI94: 176 | AJ94: 191 | AK94: 207 | AL94: 222 | AM94: 238 | AN94: 253 | AO94: 269 | AP94: 284 | AQ94: 300 | AR94: 315 | AS94: 324 | AT94: 338 | AU94: 353 | AV94: 367 | AW94: 384 | AX94: 399 | AY94: 413 | AZ94: 428 | BA94: 443 | BB94: 457 | BC94: 472 | BD94: 487 | BE94: 502 | BF94: 517 | BG94: 532
A97: Category Three
B98: 610 | C98: 710 | D98: 810 | E98: 910 | F98: 1010 | G98: 1110 | H98: 1210 | I98: 1310 | J98: 1410 | K98: 1510 | L98: 1610 | M98: 1710 | N98: 1810 | O98: 1910 | P98: 2010 | Q98: 2110 | R98: 2210 | S98: 2310 | T98: 2410 | U98: 2510 | V98: 2610 | W98: 2710 | X98: 2810 | Y98: 2910 | Z98: 3010 | AA98: 3110 | AB98: 3210 | AF98: 610 | AG98: 710 | AH98: 810 | AI98: 910 | AJ98: 1010 | AK98: 1110 | AL98: 1210 | AM98: 1310 | AN98: 1410 | AO98: 1510 | AP98: 1610 | AQ98: 1710 | AR98: 1810 | AS98: 1910 | AT98: 2010 | AU98: 2110 | AV98: 2210 | AW98: 2310 | AX98: 2410 | AY98: 2510 | AZ98: 2610 | BA98: 2710 | BB98: 2810 | BC98: 2910 | BD98: 3010 | BE98: 3110 | BF98: 3210 | BG98: 3310
A99: 600 | B99: =ROUNDUP(IFERROR(AF99*(1+$AF$6/100),AF99),0) -> 48 | C99: =ROUNDUP(IFERROR(AG99*(1+$AF$6/100),AG99),0) -> 51 | D99: =ROUNDUP(IFERROR(AH99*(1+$AF$6/100),AH99),0) -> 55 | E99: =ROUNDUP(IFERROR(AI99*(1+$AF$6/100),AI99),0) -> 59 | F99: =ROUNDUP(IFERROR(AJ99*(1+$AF$6/100),AJ99),0) -> 63 | G99: =ROUNDUP(IFERROR(AK99*(1+$AF$6/100),AK99),0) -> 66 | H99: =ROUNDUP(IFERROR(AL99*(1+$AF$6/100),AL99),0) -> 70 | I99: =ROUNDUP(IFERROR(AM99*(1+$AF$6/100),AM99),0) -> 74 | ... AB99: =ROUNDUP(IFERROR(BF99*(1+$AF$6/100),BF99),0) -> 144 | AC99: 600 | AE99: 600 | AF99: 63 | AG99: 68 | AH99: 73 | AI99: 78 | AJ99: 83 | AK99: 88 | AL99: 93 | AM99: 98 | AN99: 102 | AO99: 107 | AP99: 112 | AQ99: 112 | AR99: 116 | AS99: 121 | AT99: 126 | AU99: 130 | AV99: 135 | AW99: 139 | AX99: 144 | AY99: 156 | AZ99: 161 | BA99: 166 | BB99: 171 | BC99: 176 | BD99: 181 | BE99: 186 | BF99: 191 | BG99: 196
A100: 800 | B100: =ROUNDUP(IFERROR(AF100*(1+$AF$6/100),AF100),0) -> 54 | C100: =ROUNDUP(IFERROR(AG100*(1+$AF$6/100),AG100),0) -> 58 | D100: =ROUNDUP(IFERROR(AH100*(1+$AF$6/100),AH100),0) -> 63 | E100: =ROUNDUP(IFERROR(AI100*(1+$AF$6/100),AI100),0) -> 67 | F100: =ROUNDUP(IFERROR(AJ100*(1+$AF$6/100),AJ100),0) -> 72 | G100: =ROUNDUP(IFERROR(AK100*(1+$AF$6/100),AK100),0) -> 76 | H100: =ROUNDUP(IFERROR(AL100*(1+$AF$6/100),AL100),0) -> 81 | I100: =ROUNDUP(IFERROR(AM100*(1+$AF$6/100),AM100),0) -> 81 | ... AB100: =ROUNDUP(IFERROR(BF100*(1+$AF$6/100),BF100),0) -> 170 | AC100: 800 | AE100: 800 | AF100: 71 | AG100: 77 | AH100: 83 | AI100: 89 | AJ100: 95 | AK100: 101 | AL100: 107 | AM100: 108 | AN100: 113 | AO100: 119 | AP100: 125 | AQ100: 130 | AR100: 136 | AS100: 142 | AT100: 147 | AU100: 153 | AV100: 159 | AW100: 164 | AX100: 170 | AY100: 183 | AZ100: 189 | BA100: 195 | BB100: 202 | BC100: 208 | BD100: 214 | BE100: 220 | BF100: 226 | BG100: 232
A101: 1000 | B101: =ROUNDUP(IFERROR(AF101*(1+$AF$6/100),AF101),0) -> 59 | C101: =ROUNDUP(IFERROR(AG101*(1+$AF$6/100),AG101),0) -> 64 | D101: =ROUNDUP(IFERROR(AH101*(1+$AF$6/100),AH101),0) -> 69 | E101: =ROUNDUP(IFERROR(AI101*(1+$AF$6/100),AI101),0) -> 75 | F101: =ROUNDUP(IFERROR(AJ101*(1+$AF$6/100),AJ101),0) -> 77 | G101: =ROUNDUP(IFERROR(AK101*(1+$AF$6/100),AK101),0) -> 82 | H101: =ROUNDUP(IFERROR(AL101*(1+$AF$6/100),AL101),0) -> 87 | I101: =ROUNDUP(IFERROR(AM101*(1+$AF$6/100),AM101),0) -> 92 | ... AB101: =ROUNDUP(IFERROR(BF101*(1+$AF$6/100),BF101),0) -> 195 | AC101: 1000 | AE101: 1000 | AF101: 78 | AG101: 85 | AH101: 92 | AI101: 100 | AJ101: 102 | AK101: 109 | AL101: 115 | AM101: 122 | AN101: 129 | AO101: 136 | AP101: 142 | AQ101: 149 | AR101: 156 | AS101: 163 | AT101: 169 | AU101: 176 | AV101: 183 | AW101: 190 | AX101: 196 | AY101: 210 | AZ101: 218 | BA101: 225 | BB101: 232 | BC101: 239 | BD101: 246 | BE101: 253 | BF101: 260 | BG101: 267
A102: 1200 | B102: =ROUNDUP(IFERROR(AF102*(1+$AF$6/100),AF102),0) -> 65 | C102: =ROUNDUP(IFERROR(AG102*(1+$AF$6/100),AG102),0) -> 71 | D102: =ROUNDUP(IFERROR(AH102*(1+$AF$6/100),AH102),0) -> 77 | E102: =ROUNDUP(IFERROR(AI102*(1+$AF$6/100),AI102),0) -> 79 | F102: =ROUNDUP(IFERROR(AJ102*(1+$AF$6/100),AJ102),0) -> 85 | G102: =ROUNDUP(IFERROR(AK102*(1+$AF$6/100),AK102),0) -> 91 | H102: =ROUNDUP(IFERROR(AL102*(1+$AF$6/100),AL102),0) -> 97 | I102: =ROUNDUP(IFERROR(AM102*(1+$AF$6/100),AM102),0) -> 103 | ... AB102: =ROUNDUP(IFERROR(BF102*(1+$AF$6/100),BF102),0) -> 222 | AC102: 1200 | AE102: 1200 | AF102: 86 | AG102: 94 | AH102: 102 | AI102: 105 | AJ102: 113 | AK102: 121 | AL102: 129 | AM102: 137 | AN102: 144 | AO102: 152 | AP102: 160 | AQ102: 168 | AR102: 176 | AS102: 183 | AT102: 191 | AU102: 199 | AV102: 207 | AW102: 215 | AX102: 223 | AY102: 238 | AZ102: 246 | BA102: 254 | BB102: 263 | BC102: 271 | BD102: 279 | BE102: 287 | BF102: 295 | BG102: 303
A103: 1400 | B103: =ROUNDUP(IFERROR(AF103*(1+$AF$6/100),AF103),0) -> 70 | C103: =ROUNDUP(IFERROR(AG103*(1+$AF$6/100),AG103),0) -> 77 | D103: =ROUNDUP(IFERROR(AH103*(1+$AF$6/100),AH103),0) -> 81 | E103: =ROUNDUP(IFERROR(AI103*(1+$AF$6/100),AI103),0) -> 87 | F103: =ROUNDUP(IFERROR(AJ103*(1+$AF$6/100),AJ103),0) -> 93 | G103: =ROUNDUP(IFERROR(AK103*(1+$AF$6/100),AK103),0) -> 100 | H103: =ROUNDUP(IFERROR(AL103*(1+$AF$6/100),AL103),0) -> 107 | I103: =ROUNDUP(IFERROR(AM103*(1+$AF$6/100),AM103),0) -> 114 | ... AB103: =ROUNDUP(IFERROR(BF103*(1+$AF$6/100),BF103),0) -> 250 | AC103: 1400 | AE103: 1400 | AF103: 93 | AG103: 102 | AH103: 107 | AI103: 115 | AJ103: 124 | AK103: 133 | AL103: 142 | AM103: 151 | AN103: 160 | AO103: 169 | AP103: 178 | AQ103: 187 | AR103: 195 | AS103: 204 | AT103: 213 | AU103: 222 | AV103: 231 | AW103: 240 | AX103: 249 | AY103: 265 | AZ103: 274 | BA103: 284 | BB103: 293 | BC103: 303 | BD103: 313 | BE103: 323 | BF103: 333 | BG103: 343
A104: 1600 | B104: =ROUNDUP(IFERROR(AF104*(1+$AF$6/100),AF104),0) -> 75 | C104: =ROUNDUP(IFERROR(AG104*(1+$AF$6/100),AG104),0) -> 80 | D104: =ROUNDUP(IFERROR(AH104*(1+$AF$6/100),AH104),0) -> 87 | E104: =ROUNDUP(IFERROR(AI104*(1+$AF$6/100),AI104),0) -> 95 | F104: =ROUNDUP(IFERROR(AJ104*(1+$AF$6/100),AJ104),0) -> 102 | G104: =ROUNDUP(IFERROR(AK104*(1+$AF$6/100),AK104),0) -> 110 | H104: =ROUNDUP(IFERROR(AL104*(1+$AF$6/100),AL104),0) -> 117 | I104: =ROUNDUP(IFERROR(AM104*(1+$AF$6/100),AM104),0) -> 124 | ... AB104: =ROUNDUP(IFERROR(BF104*(1+$AF$6/100),BF104),0) -> 273 | AC104: 1600 | AE104: 1600 | AF104: 100 | AG104: 106 | AH104: 116 | AI104: 126 | AJ104: 136 | AK104: 146 | AL104: 155 | AM104: 165 | AN104: 175 | AO104: 185 | AP104: 195 | AQ104: 205 | AR104: 215 | AS104: 225 | AT104: 235 | AU104: 245 | AV104: 255 | AW104: 265 | AX104: 275 | AY104: 292 | AZ104: 303 | BA104: 313 | BB104: 324 | BC104: 334 | BD104: 344 | BE104: 354 | BF104: 364 | BG104: 374
A105: 1800 | B105: =ROUNDUP(IFERROR(AF105*(1+$AF$6/100),AF105),0) -> 78 | C105: =ROUNDUP(IFERROR(AG105*(1+$AF$6/100),AG105),0) -> 86 | D105: =ROUNDUP(IFERROR(AH105*(1+$AF$6/100),AH105),0) -> 94 | E105: =ROUNDUP(IFERROR(AI105*(1+$AF$6/100),AI105),0) -> 102 | F105: =ROUNDUP(IFERROR(AJ105*(1+$AF$6/100),AJ105),0) -> 111 | G105: =ROUNDUP(IFERROR(AK105*(1+$AF$6/100),AK105),0) -> 119 | H105: =ROUNDUP(IFERROR(AL105*(1+$AF$6/100),AL105),0) -> 127 | I105: =ROUNDUP(IFERROR(AM105*(1+$AF$6/100),AM105),0) -> 135 | ... AB105: =ROUNDUP(IFERROR(BF105*(1+$AF$6/100),BF105),0) -> 302 | AC105: 1800 | AE105: 1800 | AF105: 103 | AG105: 114 | AH105: 125 | AI105: 136 | AJ105: 147 | AK105: 158 | AL105: 169 | AM105: 180 | AN105: 191 | AO105: 202 | AP105: 213 | AQ105: 224 | AR105: 235 | AS105: 246 | AT105: 257 | AU105: 268 | AV105: 279 | AW105: 290 | AX105: 301 | AY105: 319 | AZ105: 331 | BA105: 343 | BB105: 354 | BC105: 366 | BD105: 378 | BE105: 390 | BF105: 402 | BG105: 414
A106: 2000 | B106: =ROUNDUP(IFERROR(AF106*(1+$AF$6/100),AF106),0) -> 83 | C106: =ROUNDUP(IFERROR(AG106*(1+$AF$6/100),AG106),0) -> 92 | D106: =ROUNDUP(IFERROR(AH106*(1+$AF$6/100),AH106),0) -> 101 | E106: =ROUNDUP(IFERROR(AI106*(1+$AF$6/100),AI106),0) -> 110 | F106: =ROUNDUP(IFERROR(AJ106*(1+$AF$6/100),AJ106),0) -> 119 | G106: =ROUNDUP(IFERROR(AK106*(1+$AF$6/100),AK106),0) -> 128 | H106: =ROUNDUP(IFERROR(AL106*(1+$AF$6/100),AL106),0) -> 137 | I106: =ROUNDUP(IFERROR(AM106*(1+$AF$6/100),AM106),0) -> 146 | ... AB106: =ROUNDUP(IFERROR(BF106*(1+$AF$6/100),BF106),0) -> 325 | AC106: 2000 | AE106: 2000 | AF106: 110 | AG106: 122 | AH106: 134 | AI106: 146 | AJ106: 158 | AK106: 170 | AL106: 182 | AM106: 194 | AN106: 206 | AO106: 218 | AP106: 231 | AQ106: 243 | AR106: 255 | AS106: 267 | AT106: 279 | AU106: 291 | AV106: 303 | AW106: 315 | AX106: 327 | AY106: 347 | AZ106: 359 | BA106: 372 | BB106: 385 | BC106: 397 | BD106: 409 | BE106: 421 | BF106: 433 | BG106: 445
A107: 2200 | B107: =ROUNDUP(IFERROR(AF107*(1+$AF$6/100),AF107),0) -> 88 | C107: =ROUNDUP(IFERROR(AG107*(1+$AF$6/100),AG107),0) -> 98 | D107: =ROUNDUP(IFERROR(AH107*(1+$AF$6/100),AH107),0) -> 108 | E107: =ROUNDUP(IFERROR(AI107*(1+$AF$6/100),AI107),0) -> 117 | F107: =ROUNDUP(IFERROR(AJ107*(1+$AF$6/100),AJ107),0) -> 127 | G107: =ROUNDUP(IFERROR(AK107*(1+$AF$6/100),AK107),0) -> 137 | H107: =ROUNDUP(IFERROR(AL107*(1+$AF$6/100),AL107),0) -> 147 | I107: =ROUNDUP(IFERROR(AM107*(1+$AF$6/100),AM107),0) -> 157 | ... AB107: =ROUNDUP(IFERROR(BF107*(1+$AF$6/100),BF107),0) -> 341 | AC107: 2200 | AE107: 2200 | AF107: 117 | AG107: 130 | AH107: 143 | AI107: 156 | AJ107: 169 | AK107: 182 | AL107: 196 | AM107: 209 | AN107: 222 | AO107: 235 | AP107: 248 | AQ107: 261 | AR107: 275 | AS107: 288 | AT107: 301 | AU107: 314 | AV107: 327 | AW107: 340 | AX107: 354 | AY107: 374 | AZ107: 388 | BA107: 390 | BB107: 402 | BC107: 415 | BD107: 428 | BE107: 441 | BF107: 454 | BG107: 467
A108: 2400 | B108: =ROUNDUP(IFERROR(AF108*(1+$AF$6/100),AF108),0) -> 93 | C108: =ROUNDUP(IFERROR(AG108*(1+$AF$6/100),AG108),0) -> 104 | D108: =ROUNDUP(IFERROR(AH108*(1+$AF$6/100),AH108),0) -> 114 | E108: =ROUNDUP(IFERROR(AI108*(1+$AF$6/100),AI108),0) -> 125 | F108: =ROUNDUP(IFERROR(AJ108*(1+$AF$6/100),AJ108),0) -> 135 | G108: =ROUNDUP(IFERROR(AK108*(1+$AF$6/100),AK108),0) -> 147 | H108: =ROUNDUP(IFERROR(AL108*(1+$AF$6/100),AL108),0) -> 157 | I108: =ROUNDUP(IFERROR(AM108*(1+$AF$6/100),AM108),0) -> 168 | ... AB108: =ROUNDUP(IFERROR(BF108*(1+$AF$6/100),BF108),0) -> 360 | AC108: 2400 | AE108: 2400 | AF108: 123 | AG108: 138 | AH108: 152 | AI108: 166 | AJ108: 180 | AK108: 195 | AL108: 209 | AM108: 223 | AN108: 237 | AO108: 252 | AP108: 266 | AQ108: 280 | AR108: 294 | AS108: 309 | AT108: 323 | AU108: 337 | AV108: 351 | AW108: 366 | AX108: 380 | AY108: 387 | AZ108: 400 | BA108: 414 | BB108: 427 | BC108: 440 | BD108: 453 | BE108: 466 | BF108: 479 | BG108: 492
A109: 2600 | B109: =ROUNDUP(IFERROR(AF109*(1+$AF$6/100),AF109),0) -> 98 | C109: =ROUNDUP(IFERROR(AG109*(1+$AF$6/100),AG109),0) -> 110 | D109: =ROUNDUP(IFERROR(AH109*(1+$AF$6/100),AH109),0) -> 121 | E109: =ROUNDUP(IFERROR(AI109*(1+$AF$6/100),AI109),0) -> 132 | F109: =ROUNDUP(IFERROR(AJ109*(1+$AF$6/100),AJ109),0) -> 144 | G109: =ROUNDUP(IFERROR(AK109*(1+$AF$6/100),AK109),0) -> 156 | H109: =ROUNDUP(IFERROR(AL109*(1+$AF$6/100),AL109),0) -> 167 | I109: =ROUNDUP(IFERROR(AM109*(1+$AF$6/100),AM109),0) -> 179 | ... AB109: =ROUNDUP(IFERROR(BF109*(1+$AF$6/100),BF109),0) -> 381 | AC109: 2600 | AE109: 2600 | AF109: 130 | AG109: 146 | AH109: 161 | AI109: 176 | AJ109: 192 | AK109: 207 | AL109: 222 | AM109: 238 | AN109: 253 | AO109: 268 | AP109: 283 | AQ109: 299 | AR109: 314 | AS109: 329 | AT109: 345 | AU109: 360 | AV109: 375 | AW109: 381 | AX109: 395 | AY109: 409 | AZ109: 423 | BA109: 438 | BB109: 452 | BC109: 466 | BD109: 480 | BE109: 494 | BF109: 508 | BG109: 522
A110: 2800 | B110: =ROUNDUP(IFERROR(AF110*(1+$AF$6/100),AF110),0) -> 103 | C110: =ROUNDUP(IFERROR(AG110*(1+$AF$6/100),AG110),0) -> 116 | D110: =ROUNDUP(IFERROR(AH110*(1+$AF$6/100),AH110),0) -> 128 | E110: =ROUNDUP(IFERROR(AI110*(1+$AF$6/100),AI110),0) -> 140 | F110: =ROUNDUP(IFERROR(AJ110*(1+$AF$6/100),AJ110),0) -> 153 | G110: =ROUNDUP(IFERROR(AK110*(1+$AF$6/100),AK110),0) -> 165 | H110: =ROUNDUP(IFERROR(AL110*(1+$AF$6/100),AL110),0) -> 177 | I110: =ROUNDUP(IFERROR(AM110*(1+$AF$6/100),AM110),0) -> 189 | ... AB110: =ROUNDUP(IFERROR(BF110*(1+$AF$6/100),BF110),0) -> 403 | AC110: 2800 | AE110: 2800 | AF110: 137 | AG110: 154 | AH110: 170 | AI110: 186 | AJ110: 203 | AK110: 219 | AL110: 236 | AM110: 252 | AN110: 268 | AO110: 285 | AP110: 301 | AQ110: 318 | AR110: 334 | AS110: 350 | AT110: 367 | AU110: 368 | AV110: 384 | AW110: 401 | AX110: 416 | AY110: 431 | AZ110: 446 | BA110: 461 | BB110: 477 | BC110: 492 | BD110: 507 | BE110: 522 | BF110: 537 | BG110: 552
... A112: 3200 | B112: =ROUNDUP(IFERROR(AF112*(1+$AF$6/100),AF112),0) -> 114 | C112: =ROUNDUP(IFERROR(AG112*(1+$AF$6/100),AG112),0) -> 128 | D112: =ROUNDUP(IFERROR(AH112*(1+$AF$6/100),AH112),0) -> 141 | E112: =ROUNDUP(IFERROR(AI112*(1+$AF$6/100),AI112),0) -> 156 | F112: =ROUNDUP(IFERROR(AJ112*(1+$AF$6/100),AJ112),0) -> 169 | G112: =ROUNDUP(IFERROR(AK112*(1+$AF$6/100),AK112),0) -> 183 | H112: =ROUNDUP(IFERROR(AL112*(1+$AF$6/100),AL112),0) -> 197 | I112: =ROUNDUP(IFERROR(AM112*(1+$AF$6/100),AM112),0) -> 211 | ... AB112: =ROUNDUP(IFERROR(BF112*(1+$AF$6/100),BF112),0) -> 446 | AC112: 3200 | AE112: 3200 | AF112: 151 | AG112: 170 | AH112: 188 | AI112: 207 | AJ112: 225 | AK112: 244 | AL112: 262 | AM112: 281 | AN112: 299 | AO112: 318 | AP112: 336 | AQ112: 355 | AR112: 373 | AS112: 372 | AT112: 389 | AU112: 406 | AV112: 423 | AW112: 442 | AX112: 459 | AY112: 476 | AZ112: 492 | BA112: 509 | BB112: 526 | BC112: 543 | BD112: 560 | BE112: 577 | BF112: 594 | BG112: 611
A114: Standard Warranty is 3 Years
...

Sheet Roller Blinds | Wattle
B2: Blinds | W2: As of | X2: =Cover!I59 -> 46113
A3: Roller Blinds -Wattle Collection | W3: Luxe Blinds Shutters Awnings
V4: =IF(AC4="","","Discount already applied to the prices below") -> Discount already applied to the prices below | AB4: Cat 1 Discount | AC4: -25
AB5: Cat 2 Discount | AC5: -25
AB6: Cat 3 Discount | AC6: -25
A7: Fabric Categories - Wattle Collection | O7: Motorisation
A8: Fabric Name | D8: Fabric Type | G8: Category | J8: Max Width | O8: Somfy
A9: Murray | D9: Blockout | G9: Category 1 | J9: 3000mm | O9: Motors
A10: Barossa | D10: Screen 5% & 10% | G10: Category 2 | J10: 3000mm | O10: Power Source | Q10: Control | S10: Description | W10: Price | Y10: Price Per
A11: Bilby | D11: Light Filtering | G11: Category 2 | J11: 2910mm | O11: Battery | Q11: RTS | S11: Sonesse 30 2/20 | W11: 280 | Y11: Each
A12: Fraser | D12: Blockout | G12: Category 2 | J12: 3000mm | O12: 240V (Hardwired) | Q12: RTS | S12: Altus 40 3/30 | W12: 230 | Y12: Each
A13: Kakadu | D13: Light Filtering | G13: Category 2 | J13: 3000mm | O13: 240V (Hardwired) | Q13: RTS | S13: Sonesse 40 3/30 | W13: 370 | Y13: Each
A14: Kakadu | D14: Blockout | G14: Category 2 | J14: 3000mm | O14: 240V (Hardwired) | Q14: WC | S14: LS 40 3/30 | W14: 200 | Y14: Each
A15: Kimberley | D15: Light Filtering | G15: Category 2 | J15: 2910mm | O15: 240V (Hardwired) | Q15: WC | S15: Sonesse 40 3/30 | W15: 345 | Y15: Each
A16: Nullarbor | D16: Blockout | G16: Category 2 | J16: 2800mm | O16: Remotes
A17: Tasman | D17: Light Filtering | G17: Category 2 | J17: 2910mm | O17: Type | Q17: Description | W17: Price | Y17: Price Per
A18: Bilby | D18: Blockout | G18: Category 3 | J18: 2910mm | O18: Handheld | Q18: 1 Channel Situo White | W18: 85 | X18: Each | Y18: Each
A19: Kimberley | D19: Blockout | G19: Category 3 | J19: 2910mm | O19: Handheld | Q19: 5 Channel Situo White | U19: $100 | W19: 100 | X19: Each | Y19: Each
O20: Handheld | Q20: 16 Channel Telis White | U20: $260 | W20: 260 | X20: Each | Y20: Each
A21: Hardware & Components | O21: Wall mount | Q21: 1 Channel White | U21: $90 | W21: 90 | X21: Each | Y21: Each
O22: Accessories
A23: General | O23: Description | W23: Price | Y23: Price Per
A24: Description | I24: Price | K24: Price Per | O24: Connexoon | W24: 180 | Y24: Each
A25: Double Brackets | I25: 12 | K25: Each | O25: Tahoma Switch | W25: 250 | Y25: Each
A26: Slimline Double Brackets (no suitable for linked) | I26: 16 | K26: Each | O26: Somfy Charger | U26: $25 | W26: 25 | X26: Each | Y26: Each
A27: Stainless Steel Chain | I27: 10 | K27: Each | O27: Automate
A28: White/Black Metal Chain | I28: 10 | K28: Each | O28: Motors
A29: Extension Bracket | I29: 4.5 | K29: Blind | O29: Power Source | Q29: Control | S29: Description | W29: Price | Y29: Price Per
A30: Spring Assist Booster | I30: 24 | K30: Blind | O30: Battery | Q30: RTS | S30: Zero Li-ion Q 1.1/28 | W30: 200 | Y30: Each
A31: Flat Bottom Rail | I31: 1.5 | K31: Metre | O31: Battery | Q31: RTS | S31: Zero Li-ion Q 2/28 | W31: 240 | Y31: Each
A32: Silent Bottom Rail | I32: 9 | K32: Metre | O32: Battery | Q32: Wand | S32: Magnetic Wand Motor | W32: 70 | Y32: Each
A33: Fabric Wrapped Bottom Rail | I33: 25 | K33: Metre | O33: 240V (Hardwired) | Q33: RTS | S33: E6 6/33 | W33: 170 | Y33: Each
A34: Bracket Cover | I34: 1.5 | K34: Blind | O34: 240V (Hardwired) | Q34: WC | S34: M6 6/33 | W34: 140 | Y34: Each
A35: Acmeda CF90 Cassette Only | I35: Matrix Priced Below | K35: Blind
A36: Acmeda CF90 Cassette Complete | K36: Blind | O36: Remotes
O37: Type | Q37: Description | W37: Price | Y37: Price Per
O38: Handheld | Q38: 1 Channel White or Black | W38: 65 | Y38: Each
O39: Handheld | Q39: 5 Channel White or Black | W39: 70 | Y39: Each
O40: Handheld | Q40: 15 Channel White or Black | W40: 80 | Y40: Each
O41: Handheld | Q41: 30 Channel White "Push Pro" | W41: 145 | Y41: Each
O42: Wall mount | Q42: 5 Channel White or Black | W42: 90 | Y42: Each
O43: Wand | Q43: Control Wand White | W43: 12 | Y43: Each
O44: Accessories
O45: Description | W45: Price | Y45: Price Per
O46: Motor Cap White or Black to Suit | Q46: Pulse Hub for App & Automation Control | W46: 6 | Y46: Each
O47: Interior Sun Sensor | Q47: Acmeda DC USB Charger | W47: 65 | Y47: Each
O48: Rechargable Motor Charger | W48: 26 | Y48: Each
O49: Solar Panel | W49: 180 | Y49: Each
A51: Single Roller Blind
A52: Category 1 - (1 Blind)
C53: 1000 | E53: 1200 | G53: 1400 | I53: 1600 | K53: 1800 | M53: 2000 | O53: 2200 | Q53: 2400 | S53: 2600 | U53: 2800 | W53: 3000 | AD53: 1000 | AF53: 1200 | AH53: 1400 | AJ53: 1600 | AL53: 1800 | AN53: 2000 | AP53: 2200 | AR53: 2400 | AT53: 2600 | AV53: 2800 | AX53: 3000
A54: 1000 | C54: =ROUNDUP(IFERROR(AD54*+(1+$AC$4/100),AD54),0) -> 48 | E54: =ROUNDUP(IFERROR(AF54*+(1+$AC$4/100),AF54),0) -> 56 | G54: =ROUNDUP(IFERROR(AH54*+(1+$AC$4/100),AH54),0) -> 63 | I54: =ROUNDUP(IFERROR(AJ54*+(1+$AC$4/100),AJ54),0) -> 72 | K54: =ROUNDUP(IFERROR(AL54*+(1+$AC$4/100),AL54),0) -> 79 | M54: =ROUNDUP(IFERROR(AN54*+(1+$AC$4/100),AN54),0) -> 92 | O54: =ROUNDUP(IFERROR(AP54*+(1+$AC$4/100),AP54),0) -> 100 | Q54: =ROUNDUP(IFERROR(AR54*+(1+$AC$4/100),AR54),0) -> 108 | S54: =ROUNDUP(IFERROR(AT54*+(1+$AC$4/100),AT54),0) -> 116 | U54: =ROUNDUP(IFERROR(AV54*+(1+$AC$4/100),AV54),0) -> 130 | W54: =ROUNDUP(IFERROR(AX54*+(1+$AC$4/100),AX54),0) -> 143 | Y54: 1000 | AB54: 1000 | AD54: 64 | AF54: 74 | AH54: 84 | AJ54: 95 | AL54: 105 | AN54: 122 | AP54: 133 | AR54: 143 | AT54: 154 | AV54: 173 | AX54: 190
A55: 1200 | C55: =ROUNDUP(IFERROR(AD55*+(1+$AC$4/100),AD55),0) -> 54 | E55: =ROUNDUP(IFERROR(AF55*+(1+$AC$4/100),AF55),0) -> 63 | G55: =ROUNDUP(IFERROR(AH55*+(1+$AC$4/100),AH55),0) -> 72 | I55: =ROUNDUP(IFERROR(AJ55*+(1+$AC$4/100),AJ55),0) -> 81 | K55: =ROUNDUP(IFERROR(AL55*+(1+$AC$4/100),AL55),0) -> 89 | M55: =ROUNDUP(IFERROR(AN55*+(1+$AC$4/100),AN55),0) -> 103 | O55: =ROUNDUP(IFERROR(AP55*+(1+$AC$4/100),AP55),0) -> 113 | Q55: =ROUNDUP(IFERROR(AR55*+(1+$AC$4/100),AR55),0) -> 122 | S55: =ROUNDUP(IFERROR(AT55*+(1+$AC$4/100),AT55),0) -> 131 | U55: =ROUNDUP(IFERROR(AV55*+(1+$AC$4/100),AV55),0) -> 147 | W55: =ROUNDUP(IFERROR(AX55*+(1+$AC$4/100),AX55),0) -> 160 | Y55: 1200 | AB55: 1200 | AD55: 72 | AF55: 84 | AH55: 95 | AJ55: 107 | AL55: 118 | AN55: 137 | AP55: 150 | AR55: 162 | AT55: 174 | AV55: 195 | AX55: 213
A56: 1400 | C56: =ROUNDUP(IFERROR(AD56*+(1+$AC$4/100),AD56),0) -> 60 | E56: =ROUNDUP(IFERROR(AF56*+(1+$AC$4/100),AF56),0) -> 70 | G56: =ROUNDUP(IFERROR(AH56*+(1+$AC$4/100),AH56),0) -> 80 | I56: =ROUNDUP(IFERROR(AJ56*+(1+$AC$4/100),AJ56),0) -> 90 | K56: =ROUNDUP(IFERROR(AL56*+(1+$AC$4/100),AL56),0) -> 99 | M56: =ROUNDUP(IFERROR(AN56*+(1+$AC$4/100),AN56),0) -> 115 | O56: =ROUNDUP(IFERROR(AP56*+(1+$AC$4/100),AP56),0) -> 125 | Q56: =ROUNDUP(IFERROR(AR56*+(1+$AC$4/100),AR56),0) -> 135 | S56: =ROUNDUP(IFERROR(AT56*+(1+$AC$4/100),AT56),0) -> 146 | U56: =ROUNDUP(IFERROR(AV56*+(1+$AC$4/100),AV56),0) -> 162 | W56: =ROUNDUP(IFERROR(AX56*+(1+$AC$4/100),AX56),0) -> 177 | Y56: 1400 | AB56: 1400 | AD56: 80 | AF56: 93 | AH56: 106 | AJ56: 119 | AL56: 132 | AN56: 153 | AP56: 166 | AR56: 180 | AT56: 194 | AV56: 216 | AX56: 236
A57: 1600 | C57: =ROUNDUP(IFERROR(AD57*+(1+$AC$4/100),AD57),0) -> 66 | E57: =ROUNDUP(IFERROR(AF57*+(1+$AC$4/100),AF57),0) -> 77 | G57: =ROUNDUP(IFERROR(AH57*+(1+$AC$4/100),AH57),0) -> 88 | I57: =ROUNDUP(IFERROR(AJ57*+(1+$AC$4/100),AJ57),0) -> 99 | K57: =ROUNDUP(IFERROR(AL57*+(1+$AC$4/100),AL57),0) -> 110 | M57: =ROUNDUP(IFERROR(AN57*+(1+$AC$4/100),AN57),0) -> 126 | O57: =ROUNDUP(IFERROR(AP57*+(1+$AC$4/100),AP57),0) -> 138 | Q57: =ROUNDUP(IFERROR(AR57*+(1+$AC$4/100),AR57),0) -> 150 | S57: =ROUNDUP(IFERROR(AT57*+(1+$AC$4/100),AT57),0) -> 161 | U57: =ROUNDUP(IFERROR(AV57*+(1+$AC$4/100),AV57),0) -> 179 | W57: =ROUNDUP(IFERROR(AX57*+(1+$AC$4/100),AX57),0) -> 195 | Y57: 1600 | AB57: 1600 | AD57: 87 | AF57: 102 | AH57: 117 | AJ57: 131 | AL57: 146 | AN57: 168 | AP57: 183 | AR57: 199 | AT57: 214 | AV57: 238 | AX57: 259
A58: 1800 | C58: =ROUNDUP(IFERROR(AD58*+(1+$AC$4/100),AD58),0) -> 72 | E58: =ROUNDUP(IFERROR(AF58*+(1+$AC$4/100),AF58),0) -> 84 | G58: =ROUNDUP(IFERROR(AH58*+(1+$AC$4/100),AH58),0) -> 96 | I58: =ROUNDUP(IFERROR(AJ58*+(1+$AC$4/100),AJ58),0) -> 108 | K58: =ROUNDUP(IFERROR(AL58*+(1+$AC$4/100),AL58),0) -> 120 | M58: =ROUNDUP(IFERROR(AN58*+(1+$AC$4/100),AN58),0) -> 138 | O58: =ROUNDUP(IFERROR(AP58*+(1+$AC$4/100),AP58),0) -> 150 | Q58: =ROUNDUP(IFERROR(AR58*+(1+$AC$4/100),AR58),0) -> 163 | S58: =ROUNDUP(IFERROR(AT58*+(1+$AC$4/100),AT58),0) -> 176 | U58: =ROUNDUP(IFERROR(AV58*+(1+$AC$4/100),AV58),0) -> 195 | W58: =ROUNDUP(IFERROR(AX58*+(1+$AC$4/100),AX58),0) -> 212 | Y58: 1800 | AB58: 1800 | AD58: 95 | AF58: 111 | AH58: 127 | AJ58: 144 | AL58: 160 | AN58: 183 | AP58: 200 | AR58: 217 | AT58: 234 | AV58: 259 | AX58: 282
A59: 2000 | C59: =ROUNDUP(IFERROR(AD59*+(1+$AC$4/100),AD59),0) -> 78 | E59: =ROUNDUP(IFERROR(AF59*+(1+$AC$4/100),AF59),0) -> 90 | G59: =ROUNDUP(IFERROR(AH59*+(1+$AC$4/100),AH59),0) -> 104 | I59: =ROUNDUP(IFERROR(AJ59*+(1+$AC$4/100),AJ59),0) -> 117 | K59: =ROUNDUP(IFERROR(AL59*+(1+$AC$4/100),AL59),0) -> 131 | M59: =ROUNDUP(IFERROR(AN59*+(1+$AC$4/100),AN59),0) -> 150 | O59: =ROUNDUP(IFERROR(AP59*+(1+$AC$4/100),AP59),0) -> 163 | Q59: =ROUNDUP(IFERROR(AR59*+(1+$AC$4/100),AR59),0) -> 177 | S59: =ROUNDUP(IFERROR(AT59*+(1+$AC$4/100),AT59),0) -> 191 | U59: =ROUNDUP(IFERROR(AV59*+(1+$AC$4/100),AV59),0) -> 211 | W59: =ROUNDUP(IFERROR(AX59*+(1+$AC$4/100),AX59),0) -> 228 | Y59: 2000 | AB59: 2000 | AD59: 103 | AF59: 120 | AH59: 138 | AJ59: 156 | AL59: 174 | AN59: 199 | AP59: 217 | AR59: 235 | AT59: 254 | AV59: 281 | AX59: 304
A60: 2200 | C60: =ROUNDUP(IFERROR(AD60*+(1+$AC$4/100),AD60),0) -> 83 | E60: =ROUNDUP(IFERROR(AF60*+(1+$AC$4/100),AF60),0) -> 98 | G60: =ROUNDUP(IFERROR(AH60*+(1+$AC$4/100),AH60),0) -> 112 | I60: =ROUNDUP(IFERROR(AJ60*+(1+$AC$4/100),AJ60),0) -> 126 | K60: =ROUNDUP(IFERROR(AL60*+(1+$AC$4/100),AL60),0) -> 141 | M60: =ROUNDUP(IFERROR(AN60*+(1+$AC$4/100),AN60),0) -> 161 | O60: =ROUNDUP(IFERROR(AP60*+(1+$AC$4/100),AP60),0) -> 176 | Q60: =ROUNDUP(IFERROR(AR60*+(1+$AC$4/100),AR60),0) -> 191 | S60: =ROUNDUP(IFERROR(AT60*+(1+$AC$4/100),AT60),0) -> 206 | U60: =ROUNDUP(IFERROR(AV60*+(1+$AC$4/100),AV60),0) -> 227 | W60: =ROUNDUP(IFERROR(AX60*+(1+$AC$4/100),AX60),0) -> 246 | Y60: 2200 | AB60: 2200 | AD60: 110 | AF60: 130 | AH60: 149 | AJ60: 168 | AL60: 187 | AN60: 214 | AP60: 234 | AR60: 254 | AT60: 274 | AV60: 302 | AX60: 327
A61: 2400 | C61: =ROUNDUP(IFERROR(AD61*+(1+$AC$4/100),AD61),0) -> 89 | E61: =ROUNDUP(IFERROR(AF61*+(1+$AC$4/100),AF61),0) -> 105 | G61: =ROUNDUP(IFERROR(AH61*+(1+$AC$4/100),AH61),0) -> 120 | I61: =ROUNDUP(IFERROR(AJ61*+(1+$AC$4/100),AJ61),0) -> 135 | K61: =ROUNDUP(IFERROR(AL61*+(1+$AC$4/100),AL61),0) -> 151 | M61: =ROUNDUP(IFERROR(AN61*+(1+$AC$4/100),AN61),0) -> 172 | O61: =ROUNDUP(IFERROR(AP61*+(1+$AC$4/100),AP61),0) -> 189 | Q61: =ROUNDUP(IFERROR(AR61*+(1+$AC$4/100),AR61),0) -> 204 | S61: =ROUNDUP(IFERROR(AT61*+(1+$AC$4/100),AT61),0) -> 221 | U61: =ROUNDUP(IFERROR(AV61*+(1+$AC$4/100),AV61),0) -> 243 | W61: =ROUNDUP(IFERROR(AX61*+(1+$AC$4/100),AX61),0) -> 263 | Y61: 2400 | AB61: 2400 | AD61: 118 | AF61: 139 | AH61: 160 | AJ61: 180 | AL61: 201 | AN61: 229 | AP61: 251 | AR61: 272 | AT61: 294 | AV61: 323 | AX61: 350
A62: 2600 | C62: =ROUNDUP(IFERROR(AD62*+(1+$AC$4/100),AD62),0) -> 95 | E62: =ROUNDUP(IFERROR(AF62*+(1+$AC$4/100),AF62),0) -> 111 | G62: =ROUNDUP(IFERROR(AH62*+(1+$AC$4/100),AH62),0) -> 128 | I62: =ROUNDUP(IFERROR(AJ62*+(1+$AC$4/100),AJ62),0) -> 145 | K62: =ROUNDUP(IFERROR(AL62*+(1+$AC$4/100),AL62),0) -> 162 | M62: =ROUNDUP(IFERROR(AN62*+(1+$AC$4/100),AN62),0) -> 184 | O62: =ROUNDUP(IFERROR(AP62*+(1+$AC$4/100),AP62),0) -> 201 | Q62: =ROUNDUP(IFERROR(AR62*+(1+$AC$4/100),AR62),0) -> 219 | S62: =ROUNDUP(IFERROR(AT62*+(1+$AC$4/100),AT62),0) -> 236 | U62: =ROUNDUP(IFERROR(AV62*+(1+$AC$4/100),AV62),0) -> 259 | W62: =ROUNDUP(IFERROR(AX62*+(1+$AC$4/100),AX62),0) -> 280 | Y62: 2600 | AB62: 2600 | AD62: 126 | AF62: 148 | AH62: 170 | AJ62: 193 | AL62: 215 | AN62: 245 | AP62: 268 | AR62: 291 | AT62: 314 | AV62: 345 | AX62: 373
A63: 2800 | C63: =ROUNDUP(IFERROR(AD63*+(1+$AC$4/100),AD63),0) -> 100 | E63: =ROUNDUP(IFERROR(AF63*+(1+$AC$4/100),AF63),0) -> 118 | G63: =ROUNDUP(IFERROR(AH63*+(1+$AC$4/100),AH63),0) -> 136 | I63: =ROUNDUP(IFERROR(AJ63*+(1+$AC$4/100),AJ63),0) -> 154 | K63: =ROUNDUP(IFERROR(AL63*+(1+$AC$4/100),AL63),0) -> 172 | M63: =ROUNDUP(IFERROR(AN63*+(1+$AC$4/100),AN63),0) -> 195 | O63: =ROUNDUP(IFERROR(AP63*+(1+$AC$4/100),AP63),0) -> 213 | Q63: =ROUNDUP(IFERROR(AR63*+(1+$AC$4/100),AR63),0) -> 232 | S63: =ROUNDUP(IFERROR(AT63*+(1+$AC$4/100),AT63),0) -> 251 | U63: =ROUNDUP(IFERROR(AV63*+(1+$AC$4/100),AV63),0) -> 275 | W63: =ROUNDUP(IFERROR(AX63*+(1+$AC$4/100),AX63),0) -> 297 | Y63: 2800 | AB63: 2800 | AD63: 133 | AF63: 157 | AH63: 181 | AJ63: 205 | AL63: 229 | AN63: 260 | AP63: 284 | AR63: 309 | AT63: 334 | AV63: 366 | AX63: 396
A64: 3000 | C64: =ROUNDUP(IFERROR(AD64*+(1+$AC$4/100),AD64),0) -> 106 | E64: =ROUNDUP(IFERROR(AF64*+(1+$AC$4/100),AF64),0) -> 125 | G64: =ROUNDUP(IFERROR(AH64*+(1+$AC$4/100),AH64),0) -> 148 | I64: =ROUNDUP(IFERROR(AJ64*+(1+$AC$4/100),AJ64),0) -> 168 | K64: =ROUNDUP(IFERROR(AL64*+(1+$AC$4/100),AL64),0) -> 187 | M64: =ROUNDUP(IFERROR(AN64*+(1+$AC$4/100),AN64),0) -> 207 | O64: =ROUNDUP(IFERROR(AP64*+(1+$AC$4/100),AP64),0) -> 231 | Q64: =ROUNDUP(IFERROR(AR64*+(1+$AC$4/100),AR64),0) -> 251 | S64: =ROUNDUP(IFERROR(AT64*+(1+$AC$4/100),AT64),0) -> 271 | U64: =ROUNDUP(IFERROR(AV64*+(1+$AC$4/100),AV64),0) -> 291 | W64: =ROUNDUP(IFERROR(AX64*+(1+$AC$4/100),AX64),0) -> 315 | Y64: 3000 | AB64: 3000 | AD64: 141 | AF64: 166 | AH64: 197 | AJ64: 223 | AL64: 249 | AN64: 275 | AP64: 308 | AR64: 334 | AT64: 361 | AV64: 388 | AX64: 419
A65: 3200 | C65: =ROUNDUP(IFERROR(AD65*+(1+$AC$4/100),AD65),0) -> 112 | E65: =ROUNDUP(IFERROR(AF65*+(1+$AC$4/100),AF65),0) -> 132 | G65: =ROUNDUP(IFERROR(AH65*+(1+$AC$4/100),AH65),0) -> 156 | I65: =ROUNDUP(IFERROR(AJ65*+(1+$AC$4/100),AJ65),0) -> 177 | K65: =ROUNDUP(IFERROR(AL65*+(1+$AC$4/100),AL65),0) -> 198 | M65: =ROUNDUP(IFERROR(AN65*+(1+$AC$4/100),AN65),0) -> 219 | O65: =ROUNDUP(IFERROR(AP65*+(1+$AC$4/100),AP65),0) -> 244 | Q65: =ROUNDUP(IFERROR(AR65*+(1+$AC$4/100),AR65),0) -> 265 | S65: =ROUNDUP(IFERROR(AT65*+(1+$AC$4/100),AT65),0) -> 286 | U65: =ROUNDUP(IFERROR(AV65*+(1+$AC$4/100),AV65),0) -> 307 | W65: =ROUNDUP(IFERROR(AX65*+(1+$AC$4/100),AX65),0) -> 332 | Y65: 3200 | AB65: 3200 | AD65: 149 | AF65: 176 | AH65: 208 | AJ65: 235 | AL65: 263 | AN65: 291 | AP65: 325 | AR65: 353 | AT65: 381 | AV65: 409 | AX65: 442
A66: 3400 | C66: =ROUNDUP(IFERROR(AD66*+(1+$AC$4/100),AD66),0) -> 117 | E66: =ROUNDUP(IFERROR(AF66*+(1+$AC$4/100),AF66),0) -> 139 | G66: =ROUNDUP(IFERROR(AH66*+(1+$AC$4/100),AH66),0) -> 164 | I66: =ROUNDUP(IFERROR(AJ66*+(1+$AC$4/100),AJ66),0) -> 186 | K66: =ROUNDUP(IFERROR(AL66*+(1+$AC$4/100),AL66),0) -> 208 | M66: =ROUNDUP(IFERROR(AN66*+(1+$AC$4/100),AN66),0) -> 230 | O66: =ROUNDUP(IFERROR(AP66*+(1+$AC$4/100),AP66),0) -> 256 | Q66: =ROUNDUP(IFERROR(AR66*+(1+$AC$4/100),AR66),0) -> 279 | S66: =ROUNDUP(IFERROR(AT66*+(1+$AC$4/100),AT66),0) -> 301 | U66: =ROUNDUP(IFERROR(AV66*+(1+$AC$4/100),AV66),0) -> 324 | W66: =ROUNDUP(IFERROR(AX66*+(1+$AC$4/100),AX66),0) -> 349 | Y66: 3400 | AB66: 3400 | AD66: 156 | AF66: 185 | AH66: 218 | AJ66: 248 | AL66: 277 | AN66: 306 | AP66: 341 | AR66: 371 | AT66: 401 | AV66: 431 | AX66: 465
A69: Category 2 - (1 Blind)
C70: 1000 | E70: 1200 | G70: 1400 | I70: 1600 | K70: 1800 | M70: 2000 | O70: 2200 | Q70: 2400 | S70: 2600 | U70: 2800 | W70: 3000 | AD70: 1000 | AF70: 1200 | AH70: 1400 | AJ70: 1600 | AL70: 1800 | AN70: 2000 | AP70: 2200 | AR70: 2400 | AT70: 2600 | AV70: 2800 | AX70: 3000
A71: 1000 | C71: =ROUNDUP(IFERROR(AD71*(1+$AC$5/100),AD71),0) -> 56 | E71: =ROUNDUP(IFERROR(AF71*(1+$AC$5/100),AF71),0) -> 64 | G71: =ROUNDUP(IFERROR(AH71*(1+$AC$5/100),AH71),0) -> 73 | I71: =ROUNDUP(IFERROR(AJ71*(1+$AC$5/100),AJ71),0) -> 81 | K71: =ROUNDUP(IFERROR(AL71*(1+$AC$5/100),AL71),0) -> 90 | M71: =ROUNDUP(IFERROR(AN71*(1+$AC$5/100),AN71),0) -> 105 | O71: =ROUNDUP(IFERROR(AP71*(1+$AC$5/100),AP71),0) -> 114 | Q71: =ROUNDUP(IFERROR(AR71*(1+$AC$5/100),AR71),0) -> 124 | S71: =ROUNDUP(IFERROR(AT71*(1+$AC$5/100),AT71),0) -> 133 | U71: =ROUNDUP(IFERROR(AV71*(1+$AC$5/100),AV71),0) -> 150 | W71: =ROUNDUP(IFERROR(AX71*(1+$AC$5/100),AX71),0) -> 163 | Y71: 1000 | AB71: 1000 | AD71: 74 | AF71: 85 | AH71: 97 | AJ71: 108 | AL71: 120 | AN71: 140 | AP71: 152 | AR71: 165 | AT71: 177 | AV71: 199 | AX71: 217
A72: 1200 | C72: =ROUNDUP(IFERROR(AD72*(1+$AC$5/100),AD72),0) -> 63 | E72: =ROUNDUP(IFERROR(AF72*(1+$AC$5/100),AF72),0) -> 72 | G72: =ROUNDUP(IFERROR(AH72*(1+$AC$5/100),AH72),0) -> 82 | I72: =ROUNDUP(IFERROR(AJ72*(1+$AC$5/100),AJ72),0) -> 93 | K72: =ROUNDUP(IFERROR(AL72*(1+$AC$5/100),AL72),0) -> 102 | M72: =ROUNDUP(IFERROR(AN72*(1+$AC$5/100),AN72),0) -> 118 | O72: =ROUNDUP(IFERROR(AP72*(1+$AC$5/100),AP72),0) -> 129 | Q72: =ROUNDUP(IFERROR(AR72*(1+$AC$5/100),AR72),0) -> 140 | S72: =ROUNDUP(IFERROR(AT72*(1+$AC$5/100),AT72),0) -> 150 | U72: =ROUNDUP(IFERROR(AV72*(1+$AC$5/100),AV72),0) -> 168 | W72: =ROUNDUP(IFERROR(AX72*(1+$AC$5/100),AX72),0) -> 183 | Y72: 1200 | AB72: 1200 | AD72: 83 | AF72: 96 | AH72: 109 | AJ72: 123 | AL72: 136 | AN72: 157 | AP72: 172 | AR72: 186 | AT72: 200 | AV72: 223 | AX72: 244
A73: 1400 | C73: =ROUNDUP(IFERROR(AD73*(1+$AC$5/100),AD73),0) -> 69 | E73: =ROUNDUP(IFERROR(AF73*(1+$AC$5/100),AF73),0) -> 81 | G73: =ROUNDUP(IFERROR(AH73*(1+$AC$5/100),AH73),0) -> 92 | I73: =ROUNDUP(IFERROR(AJ73*(1+$AC$5/100),AJ73),0) -> 103 | K73: =ROUNDUP(IFERROR(AL73*(1+$AC$5/100),AL73),0) -> 114 | M73: =ROUNDUP(IFERROR(AN73*(1+$AC$5/100),AN73),0) -> 132 | O73: =ROUNDUP(IFERROR(AP73*(1+$AC$5/100),AP73),0) -> 144 | Q73: =ROUNDUP(IFERROR(AR73*(1+$AC$5/100),AR73),0) -> 156 | S73: =ROUNDUP(IFERROR(AT73*(1+$AC$5/100),AT73),0) -> 168 | U73: =ROUNDUP(IFERROR(AV73*(1+$AC$5/100),AV73),0) -> 186 | W73: =ROUNDUP(IFERROR(AX73*(1+$AC$5/100),AX73),0) -> 203 | Y73: 1400 | AB73: 1400 | AD73: 91 | AF73: 107 | AH73: 122 | AJ73: 137 | AL73: 152 | AN73: 175 | AP73: 191 | AR73: 207 | AT73: 223 | AV73: 248 | AX73: 270
A74: 1600 | C74: =ROUNDUP(IFERROR(AD74*(1+$AC$5/100),AD74),0) -> 75 | E74: =ROUNDUP(IFERROR(AF74*(1+$AC$5/100),AF74),0) -> 88 | G74: =ROUNDUP(IFERROR(AH74*(1+$AC$5/100),AH74),0) -> 101 | I74: =ROUNDUP(IFERROR(AJ74*(1+$AC$5/100),AJ74),0) -> 114 | K74: =ROUNDUP(IFERROR(AL74*(1+$AC$5/100),AL74),0) -> 126 | M74: =ROUNDUP(IFERROR(AN74*(1+$AC$5/100),AN74),0) -> 145 | O74: =ROUNDUP(IFERROR(AP74*(1+$AC$5/100),AP74),0) -> 158 | Q74: =ROUNDUP(IFERROR(AR74*(1+$AC$5/100),AR74),0) -> 171 | S74: =ROUNDUP(IFERROR(AT74*(1+$AC$5/100),AT74),0) -> 185 | U74: =ROUNDUP(IFERROR(AV74*(1+$AC$5/100),AV74),0) -> 205 | W74: =ROUNDUP(IFERROR(AX74*(1+$AC$5/100),AX74),0) -> 223 | Y74: 1600 | AB74: 1600 | AD74: 100 | AF74: 117 | AH74: 134 | AJ74: 151 | AL74: 167 | AN74: 193 | AP74: 210 | AR74: 228 | AT74: 246 | AV74: 273 | AX74: 297
A75: 1800 | C75: =ROUNDUP(IFERROR(AD75*(1+$AC$5/100),AD75),0) -> 82 | E75: =ROUNDUP(IFERROR(AF75*(1+$AC$5/100),AF75),0) -> 96 | G75: =ROUNDUP(IFERROR(AH75*(1+$AC$5/100),AH75),0) -> 110 | I75: =ROUNDUP(IFERROR(AJ75*(1+$AC$5/100),AJ75),0) -> 124 | K75: =ROUNDUP(IFERROR(AL75*(1+$AC$5/100),AL75),0) -> 138 | M75: =ROUNDUP(IFERROR(AN75*(1+$AC$5/100),AN75),0) -> 158 | O75: =ROUNDUP(IFERROR(AP75*(1+$AC$5/100),AP75),0) -> 173 | Q75: =ROUNDUP(IFERROR(AR75*(1+$AC$5/100),AR75),0) -> 187 | S75: =ROUNDUP(IFERROR(AT75*(1+$AC$5/100),AT75),0) -> 201 | U75: =ROUNDUP(IFERROR(AV75*(1+$AC$5/100),AV75),0) -> 223 | W75: =ROUNDUP(IFERROR(AX75*(1+$AC$5/100),AX75),0) -> 243 | Y75: 1800 | AB75: 1800 | AD75: 109 | AF75: 128 | AH75: 146 | AJ75: 165 | AL75: 183 | AN75: 210 | AP75: 230 | AR75: 249 | AT75: 268 | AV75: 297 | AX75: 323
A76: 2000 | C76: =ROUNDUP(IFERROR(AD76*(1+$AC$5/100),AD76),0) -> 89 | E76: =ROUNDUP(IFERROR(AF76*(1+$AC$5/100),AF76),0) -> 104 | G76: =ROUNDUP(IFERROR(AH76*(1+$AC$5/100),AH76),0) -> 119 | I76: =ROUNDUP(IFERROR(AJ76*(1+$AC$5/100),AJ76),0) -> 135 | K76: =ROUNDUP(IFERROR(AL76*(1+$AC$5/100),AL76),0) -> 150 | M76: =ROUNDUP(IFERROR(AN76*(1+$AC$5/100),AN76),0) -> 171 | O76: =ROUNDUP(IFERROR(AP76*(1+$AC$5/100),AP76),0) -> 187 | Q76: =ROUNDUP(IFERROR(AR76*(1+$AC$5/100),AR76),0) -> 203 | S76: =ROUNDUP(IFERROR(AT76*(1+$AC$5/100),AT76),0) -> 219 | U76: =ROUNDUP(IFERROR(AV76*(1+$AC$5/100),AV76),0) -> 242 | W76: =ROUNDUP(IFERROR(AX76*(1+$AC$5/100),AX76),0) -> 262 | Y76: 2000 | AB76: 2000 | AD76: 118 | AF76: 138 | AH76: 158 | AJ76: 179 | AL76: 199 | AN76: 228 | AP76: 249 | AR76: 270 | AT76: 291 | AV76: 322 | AX76: 349
A77: 2200 | C77: =ROUNDUP(IFERROR(AD77*(1+$AC$5/100),AD77),0) -> 96 | E77: =ROUNDUP(IFERROR(AF77*(1+$AC$5/100),AF77),0) -> 112 | G77: =ROUNDUP(IFERROR(AH77*(1+$AC$5/100),AH77),0) -> 129 | I77: =ROUNDUP(IFERROR(AJ77*(1+$AC$5/100),AJ77),0) -> 145 | K77: =ROUNDUP(IFERROR(AL77*(1+$AC$5/100),AL77),0) -> 162 | M77: =ROUNDUP(IFERROR(AN77*(1+$AC$5/100),AN77),0) -> 184 | O77: =ROUNDUP(IFERROR(AP77*(1+$AC$5/100),AP77),0) -> 201 | Q77: =ROUNDUP(IFERROR(AR77*(1+$AC$5/100),AR77),0) -> 219 | S77: =ROUNDUP(IFERROR(AT77*(1+$AC$5/100),AT77),0) -> 236 | U77: =ROUNDUP(IFERROR(AV77*(1+$AC$5/100),AV77),0) -> 261 | W77: =ROUNDUP(IFERROR(AX77*(1+$AC$5/100),AX77),0) -> 282 | Y77: 2200 | AB77: 2200 | AD77: 127 | AF77: 149 | AH77: 171 | AJ77: 193 | AL77: 215 | AN77: 245 | AP77: 268 | AR77: 291 | AT77: 314 | AV77: 347 | AX77: 376
A78: 2400 | C78: =ROUNDUP(IFERROR(AD78*(1+$AC$5/100),AD78),0) -> 102 | E78: =ROUNDUP(IFERROR(AF78*(1+$AC$5/100),AF78),0) -> 120 | G78: =ROUNDUP(IFERROR(AH78*(1+$AC$5/100),AH78),0) -> 138 | I78: =ROUNDUP(IFERROR(AJ78*(1+$AC$5/100),AJ78),0) -> 156 | K78: =ROUNDUP(IFERROR(AL78*(1+$AC$5/100),AL78),0) -> 174 | M78: =ROUNDUP(IFERROR(AN78*(1+$AC$5/100),AN78),0) -> 198 | O78: =ROUNDUP(IFERROR(AP78*(1+$AC$5/100),AP78),0) -> 216 | Q78: =ROUNDUP(IFERROR(AR78*(1+$AC$5/100),AR78),0) -> 234 | S78: =ROUNDUP(IFERROR(AT78*(1+$AC$5/100),AT78),0) -> 253 | U78: =ROUNDUP(IFERROR(AV78*(1+$AC$5/100),AV78),0) -> 279 | W78: =ROUNDUP(IFERROR(AX78*(1+$AC$5/100),AX78),0) -> 302 | Y78: 2400 | AB78: 2400 | AD78: 135 | AF78: 159 | AH78: 183 | AJ78: 207 | AL78: 231 | AN78: 263 | AP78: 288 | AR78: 312 | AT78: 337 | AV78: 371 | AX78: 402
A79: 2600 | C79: =ROUNDUP(IFERROR(AD79*(1+$AC$5/100),AD79),0) -> 108 | E79: =ROUNDUP(IFERROR(AF79*(1+$AC$5/100),AF79),0) -> 128 | G79: =ROUNDUP(IFERROR(AH79*(1+$AC$5/100),AH79),0) -> 147 | I79: =ROUNDUP(IFERROR(AJ79*(1+$AC$5/100),AJ79),0) -> 166 | K79: =ROUNDUP(IFERROR(AL79*(1+$AC$5/100),AL79),0) -> 186 | M79: =ROUNDUP(IFERROR(AN79*(1+$AC$5/100),AN79),0) -> 211 | O79: =ROUNDUP(IFERROR(AP79*(1+$AC$5/100),AP79),0) -> 231 | Q79: =ROUNDUP(IFERROR(AR79*(1+$AC$5/100),AR79),0) -> 250 | S79: =ROUNDUP(IFERROR(AT79*(1+$AC$5/100),AT79),0) -> 270 | U79: =ROUNDUP(IFERROR(AV79*(1+$AC$5/100),AV79),0) -> 297 | W79: =ROUNDUP(IFERROR(AX79*(1+$AC$5/100),AX79),0) -> 322 | Y79: 2600 | AB79: 2600 | AD79: 144 | AF79: 170 | AH79: 195 | AJ79: 221 | AL79: 247 | AN79: 281 | AP79: 307 | AR79: 333 | AT79: 360 | AV79: 396 | AX79: 429
A80: 2800 | C80: =ROUNDUP(IFERROR(AD80*(1+$AC$5/100),AD80),0) -> 115 | E80: =ROUNDUP(IFERROR(AF80*(1+$AC$5/100),AF80),0) -> 135 | G80: =ROUNDUP(IFERROR(AH80*(1+$AC$5/100),AH80),0) -> 156 | I80: =ROUNDUP(IFERROR(AJ80*(1+$AC$5/100),AJ80),0) -> 177 | K80: =ROUNDUP(IFERROR(AL80*(1+$AC$5/100),AL80),0) -> 197 | M80: =ROUNDUP(IFERROR(AN80*(1+$AC$5/100),AN80),0) -> 224 | O80: =ROUNDUP(IFERROR(AP80*(1+$AC$5/100),AP80),0) -> 245 | Q80: =ROUNDUP(IFERROR(AR80*(1+$AC$5/100),AR80),0) -> 267 | S80: =ROUNDUP(IFERROR(AT80*(1+$AC$5/100),AT80),0) -> 288 | U80: =ROUNDUP(IFERROR(AV80*(1+$AC$5/100),AV80),0) -> 315 | W80: =ROUNDUP(IFERROR(AX80*(1+$AC$5/100),AX80),0) -> 342 | Y80: 2800 | AB80: 2800 | AD80: 153 | AF80: 180 | AH80: 208 | AJ80: 235 | AL80: 262 | AN80: 298 | AP80: 326 | AR80: 355 | AT80: 383 | AV80: 420 | AX80: 455
A81: 3000 | C81: =ROUNDUP(IFERROR(AD81*(1+$AC$5/100),AD81),0) -> 122 | E81: =ROUNDUP(IFERROR(AF81*(1+$AC$5/100),AF81),0) -> 144 | G81: =ROUNDUP(IFERROR(AH81*(1+$AC$5/100),AH81),0) -> 170 | I81: =ROUNDUP(IFERROR(AJ81*(1+$AC$5/100),AJ81),0) -> 192 | K81: =ROUNDUP(IFERROR(AL81*(1+$AC$5/100),AL81),0) -> 215 | M81: =ROUNDUP(IFERROR(AN81*(1+$AC$5/100),AN81),0) -> 237 | O81: =ROUNDUP(IFERROR(AP81*(1+$AC$5/100),AP81),0) -> 265 | Q81: =ROUNDUP(IFERROR(AR81*(1+$AC$5/100),AR81),0) -> 288 | S81: =ROUNDUP(IFERROR(AT81*(1+$AC$5/100),AT81),0) -> 311 | U81: =ROUNDUP(IFERROR(AV81*(1+$AC$5/100),AV81),0) -> 334 | W81: =ROUNDUP(IFERROR(AX81*(1+$AC$5/100),AX81),0) -> 361 | Y81: 3000 | AB81: 3000 | AD81: 162 | AF81: 191 | AH81: 226 | AJ81: 256 | AL81: 286 | AN81: 316 | AP81: 353 | AR81: 384 | AT81: 414 | AV81: 445 | AX81: 481
A82: 3200 | C82: =ROUNDUP(IFERROR(AD82*(1+$AC$5/100),AD82),0) -> 129 | E82: =ROUNDUP(IFERROR(AF82*(1+$AC$5/100),AF82),0) -> 151 | G82: =ROUNDUP(IFERROR(AH82*(1+$AC$5/100),AH82),0) -> 179 | I82: =ROUNDUP(IFERROR(AJ82*(1+$AC$5/100),AJ82),0) -> 203 | K82: =ROUNDUP(IFERROR(AL82*(1+$AC$5/100),AL82),0) -> 227 | M82: =ROUNDUP(IFERROR(AN82*(1+$AC$5/100),AN82),0) -> 250 | O82: =ROUNDUP(IFERROR(AP82*(1+$AC$5/100),AP82),0) -> 279 | Q82: =ROUNDUP(IFERROR(AR82*(1+$AC$5/100),AR82),0) -> 304 | S82: =ROUNDUP(IFERROR(AT82*(1+$AC$5/100),AT82),0) -> 328 | U82: =ROUNDUP(IFERROR(AV82*(1+$AC$5/100),AV82),0) -> 353 | W82: =ROUNDUP(IFERROR(AX82*(1+$AC$5/100),AX82),0) -> 381 | Y82: 3200 | AB82: 3200 | AD82: 171 | AF82: 201 | AH82: 238 | AJ82: 270 | AL82: 302 | AN82: 333 | AP82: 372 | AR82: 405 | AT82: 437 | AV82: 470 | AX82: 508
A83: 3400 | C83: =ROUNDUP(IFERROR(AD83*(1+$AC$5/100),AD83),0) -> 135 | E83: =ROUNDUP(IFERROR(AF83*(1+$AC$5/100),AF83),0) -> 159 | G83: =ROUNDUP(IFERROR(AH83*(1+$AC$5/100),AH83),0) -> 189 | I83: =ROUNDUP(IFERROR(AJ83*(1+$AC$5/100),AJ83),0) -> 213 | K83: =ROUNDUP(IFERROR(AL83*(1+$AC$5/100),AL83),0) -> 238 | M83: =ROUNDUP(IFERROR(AN83*(1+$AC$5/100),AN83),0) -> 264 | O83: =ROUNDUP(IFERROR(AP83*(1+$AC$5/100),AP83),0) -> 294 | Q83: =ROUNDUP(IFERROR(AR83*(1+$AC$5/100),AR83),0) -> 320 | S83: =ROUNDUP(IFERROR(AT83*(1+$AC$5/100),AT83),0) -> 345 | U83: =ROUNDUP(IFERROR(AV83*(1+$AC$5/100),AV83),0) -> 371 | W83: =ROUNDUP(IFERROR(AX83*(1+$AC$5/100),AX83),0) -> 401 | Y83: 3400 | AB83: 3400 | AD83: 179 | AF83: 212 | AH83: 251 | AJ83: 284 | AL83: 317 | AN83: 351 | AP83: 392 | AR83: 426 | AT83: 460 | AV83: 494 | AX83: 534
A86: Category 3 - (1 Blind)
C87: 1000 | E87: 1200 | G87: 1400 | I87: 1600 | K87: 1800 | M87: 2000 | O87: 2200 | Q87: 2400 | S87: 2600 | U87: 2800 | W87: 3000 | AD87: 1000 | AF87: 1200 | AH87: 1400 | AJ87: 1600 | AL87: 1800 | AN87: 2000 | AP87: 2200 | AR87: 2400 | AT87: 2600 | AV87: 2800 | AX87: 3000
A88: 1000 | C88: =ROUNDUP(IFERROR(AD88*(1+$AC$6/100),AD88),0) -> 57 | E88: =ROUNDUP(IFERROR(AF88*(1+$AC$6/100),AF88),0) -> 66 | G88: =ROUNDUP(IFERROR(AH88*(1+$AC$6/100),AH88),0) -> 75 | I88: =ROUNDUP(IFERROR(AJ88*(1+$AC$6/100),AJ88),0) -> 84 | K88: =ROUNDUP(IFERROR(AL88*(1+$AC$6/100),AL88),0) -> 93 | M88: =ROUNDUP(IFERROR(AN88*(1+$AC$6/100),AN88),0) -> 108 | O88: =ROUNDUP(IFERROR(AP88*(1+$AC$6/100),AP88),0) -> 118 | Q88: =ROUNDUP(IFERROR(AR88*(1+$AC$6/100),AR88),0) -> 127 | S88: =ROUNDUP(IFERROR(AT88*(1+$AC$6/100),AT88),0) -> 137 | U88: =ROUNDUP(IFERROR(AV88*(1+$AC$6/100),AV88),0) -> 153 | W88: =ROUNDUP(IFERROR(AX88*(1+$AC$6/100),AX88),0) -> 168 | Y88: 1000 | AB88: 1000 | AD88: 76 | AF88: 88 | AH88: 100 | AJ88: 112 | AL88: 124 | AN88: 144 | AP88: 157 | AR88: 169 | AT88: 182 | AV88: 204 | AX88: 224
A89: 1200 | C89: =ROUNDUP(IFERROR(AD89*(1+$AC$6/100),AD89),0) -> 64 | E89: =ROUNDUP(IFERROR(AF89*(1+$AC$6/100),AF89),0) -> 75 | G89: =ROUNDUP(IFERROR(AH89*(1+$AC$6/100),AH89),0) -> 85 | I89: =ROUNDUP(IFERROR(AJ89*(1+$AC$6/100),AJ89),0) -> 95 | K89: =ROUNDUP(IFERROR(AL89*(1+$AC$6/100),AL89),0) -> 105 | M89: =ROUNDUP(IFERROR(AN89*(1+$AC$6/100),AN89),0) -> 122 | O89: =ROUNDUP(IFERROR(AP89*(1+$AC$6/100),AP89),0) -> 133 | Q89: =ROUNDUP(IFERROR(AR89*(1+$AC$6/100),AR89),0) -> 144 | S89: =ROUNDUP(IFERROR(AT89*(1+$AC$6/100),AT89),0) -> 155 | U89: =ROUNDUP(IFERROR(AV89*(1+$AC$6/100),AV89),0) -> 173 | W89: =ROUNDUP(IFERROR(AX89*(1+$AC$6/100),AX89),0) -> 189 | Y89: 1200 | AB89: 1200 | AD89: 85 | AF89: 99 | AH89: 113 | AJ89: 126 | AL89: 140 | AN89: 162 | AP89: 177 | AR89: 192 | AT89: 206 | AV89: 230 | AX89: 251
A90: 1400 | C90: =ROUNDUP(IFERROR(AD90*(1+$AC$6/100),AD90),0) -> 71 | E90: =ROUNDUP(IFERROR(AF90*(1+$AC$6/100),AF90),0) -> 83 | G90: =ROUNDUP(IFERROR(AH90*(1+$AC$6/100),AH90),0) -> 95 | I90: =ROUNDUP(IFERROR(AJ90*(1+$AC$6/100),AJ90),0) -> 106 | K90: =ROUNDUP(IFERROR(AL90*(1+$AC$6/100),AL90),0) -> 118 | M90: =ROUNDUP(IFERROR(AN90*(1+$AC$6/100),AN90),0) -> 136 | O90: =ROUNDUP(IFERROR(AP90*(1+$AC$6/100),AP90),0) -> 148 | Q90: =ROUNDUP(IFERROR(AR90*(1+$AC$6/100),AR90),0) -> 161 | S90: =ROUNDUP(IFERROR(AT90*(1+$AC$6/100),AT90),0) -> 173 | U90: =ROUNDUP(IFERROR(AV90*(1+$AC$6/100),AV90),0) -> 192 | W90: =ROUNDUP(IFERROR(AX90*(1+$AC$6/100),AX90),0) -> 210 | Y90: 1400 | AB90: 1400 | AD90: 94 | AF90: 110 | AH90: 126 | AJ90: 141 | AL90: 157 | AN90: 181 | AP90: 197 | AR90: 214 | AT90: 230 | AV90: 256 | AX90: 279
A91: 1600 | C91: =ROUNDUP(IFERROR(AD91*(1+$AC$6/100),AD91),0) -> 78 | E91: =ROUNDUP(IFERROR(AF91*(1+$AC$6/100),AF91),0) -> 91 | G91: =ROUNDUP(IFERROR(AH91*(1+$AC$6/100),AH91),0) -> 104 | I91: =ROUNDUP(IFERROR(AJ91*(1+$AC$6/100),AJ91),0) -> 117 | K91: =ROUNDUP(IFERROR(AL91*(1+$AC$6/100),AL91),0) -> 130 | M91: =ROUNDUP(IFERROR(AN91*(1+$AC$6/100),AN91),0) -> 150 | O91: =ROUNDUP(IFERROR(AP91*(1+$AC$6/100),AP91),0) -> 163 | Q91: =ROUNDUP(IFERROR(AR91*(1+$AC$6/100),AR91),0) -> 177 | S91: =ROUNDUP(IFERROR(AT91*(1+$AC$6/100),AT91),0) -> 191 | U91: =ROUNDUP(IFERROR(AV91*(1+$AC$6/100),AV91),0) -> 212 | W91: =ROUNDUP(IFERROR(AX91*(1+$AC$6/100),AX91),0) -> 230 | Y91: 1600 | AB91: 1600 | AD91: 104 | AF91: 121 | AH91: 138 | AJ91: 156 | AL91: 173 | AN91: 199 | AP91: 217 | AR91: 236 | AT91: 254 | AV91: 282 | AX91: 306
A92: 1800 | C92: =ROUNDUP(IFERROR(AD92*(1+$AC$6/100),AD92),0) -> 85 | E92: =ROUNDUP(IFERROR(AF92*(1+$AC$6/100),AF92),0) -> 99 | G92: =ROUNDUP(IFERROR(AH92*(1+$AC$6/100),AH92),0) -> 114 | I92: =ROUNDUP(IFERROR(AJ92*(1+$AC$6/100),AJ92),0) -> 129 | K92: =ROUNDUP(IFERROR(AL92*(1+$AC$6/100),AL92),0) -> 143 | M92: =ROUNDUP(IFERROR(AN92*(1+$AC$6/100),AN92),0) -> 164 | O92: =ROUNDUP(IFERROR(AP92*(1+$AC$6/100),AP92),0) -> 179 | Q92: =ROUNDUP(IFERROR(AR92*(1+$AC$6/100),AR92),0) -> 194 | S92: =ROUNDUP(IFERROR(AT92*(1+$AC$6/100),AT92),0) -> 209 | U92: =ROUNDUP(IFERROR(AV92*(1+$AC$6/100),AV92),0) -> 231 | W92: =ROUNDUP(IFERROR(AX92*(1+$AC$6/100),AX92),0) -> 251 | Y92: 1800 | AB92: 1800 | AD92: 113 | AF92: 132 | AH92: 151 | AJ92: 171 | AL92: 190 | AN92: 218 | AP92: 238 | AR92: 258 | AT92: 278 | AV92: 308 | AX92: 334
A93: 2000 | C93: =ROUNDUP(IFERROR(AD93*(1+$AC$6/100),AD93),0) -> 92 | E93: =ROUNDUP(IFERROR(AF93*(1+$AC$6/100),AF93),0) -> 108 | G93: =ROUNDUP(IFERROR(AH93*(1+$AC$6/100),AH93),0) -> 123 | I93: =ROUNDUP(IFERROR(AJ93*(1+$AC$6/100),AJ93),0) -> 139 | K93: =ROUNDUP(IFERROR(AL93*(1+$AC$6/100),AL93),0) -> 155 | M93: =ROUNDUP(IFERROR(AN93*(1+$AC$6/100),AN93),0) -> 177 | O93: =ROUNDUP(IFERROR(AP93*(1+$AC$6/100),AP93),0) -> 194 | Q93: =ROUNDUP(IFERROR(AR93*(1+$AC$6/100),AR93),0) -> 210 | S93: =ROUNDUP(IFERROR(AT93*(1+$AC$6/100),AT93),0) -> 227 | U93: =ROUNDUP(IFERROR(AV93*(1+$AC$6/100),AV93),0) -> 250 | W93: =ROUNDUP(IFERROR(AX93*(1+$AC$6/100),AX93),0) -> 272 | Y93: 2000 | AB93: 2000 | AD93: 122 | AF93: 143 | AH93: 164 | AJ93: 185 | AL93: 206 | AN93: 236 | AP93: 258 | AR93: 280 | AT93: 302 | AV93: 333 | AX93: 362
A94: 2200 | C94: =ROUNDUP(IFERROR(AD94*(1+$AC$6/100),AD94),0) -> 99 | E94: =ROUNDUP(IFERROR(AF94*(1+$AC$6/100),AF94),0) -> 116 | G94: =ROUNDUP(IFERROR(AH94*(1+$AC$6/100),AH94),0) -> 133 | I94: =ROUNDUP(IFERROR(AJ94*(1+$AC$6/100),AJ94),0) -> 150 | K94: =ROUNDUP(IFERROR(AL94*(1+$AC$6/100),AL94),0) -> 168 | M94: =ROUNDUP(IFERROR(AN94*(1+$AC$6/100),AN94),0) -> 191 | O94: =ROUNDUP(IFERROR(AP94*(1+$AC$6/100),AP94),0) -> 209 | Q94: =ROUNDUP(IFERROR(AR94*(1+$AC$6/100),AR94),0) -> 227 | S94: =ROUNDUP(IFERROR(AT94*(1+$AC$6/100),AT94),0) -> 245 | U94: =ROUNDUP(IFERROR(AV94*(1+$AC$6/100),AV94),0) -> 270 | W94: =ROUNDUP(IFERROR(AX94*(1+$AC$6/100),AX94),0) -> 292 | Y94: 2200 | AB94: 2200 | AD94: 131 | AF94: 154 | AH94: 177 | AJ94: 200 | AL94: 223 | AN94: 254 | AP94: 278 | AR94: 302 | AT94: 326 | AV94: 359 | AX94: 389
A95: 2400 | C95: =ROUNDUP(IFERROR(AD95*(1+$AC$6/100),AD95),0) -> 105 | E95: =ROUNDUP(IFERROR(AF95*(1+$AC$6/100),AF95),0) -> 124 | G95: =ROUNDUP(IFERROR(AH95*(1+$AC$6/100),AH95),0) -> 143 | I95: =ROUNDUP(IFERROR(AJ95*(1+$AC$6/100),AJ95),0) -> 162 | K95: =ROUNDUP(IFERROR(AL95*(1+$AC$6/100),AL95),0) -> 180 | M95: =ROUNDUP(IFERROR(AN95*(1+$AC$6/100),AN95),0) -> 205 | O95: =ROUNDUP(IFERROR(AP95*(1+$AC$6/100),AP95),0) -> 224 | Q95: =ROUNDUP(IFERROR(AR95*(1+$AC$6/100),AR95),0) -> 243 | S95: =ROUNDUP(IFERROR(AT95*(1+$AC$6/100),AT95),0) -> 263 | U95: =ROUNDUP(IFERROR(AV95*(1+$AC$6/100),AV95),0) -> 289 | W95: =ROUNDUP(IFERROR(AX95*(1+$AC$6/100),AX95),0) -> 313 | Y95: 2400 | AB95: 2400 | AD95: 140 | AF95: 165 | AH95: 190 | AJ95: 215 | AL95: 240 | AN95: 273 | AP95: 298 | AR95: 324 | AT95: 350 | AV95: 385 | AX95: 417
A96: 2600 | C96: =ROUNDUP(IFERROR(AD96*(1+$AC$6/100),AD96),0) -> 113 | E96: =ROUNDUP(IFERROR(AF96*(1+$AC$6/100),AF96),0) -> 132 | G96: =ROUNDUP(IFERROR(AH96*(1+$AC$6/100),AH96),0) -> 153 | I96: =ROUNDUP(IFERROR(AJ96*(1+$AC$6/100),AJ96),0) -> 173 | K96: =ROUNDUP(IFERROR(AL96*(1+$AC$6/100),AL96),0) -> 192 | M96: =ROUNDUP(IFERROR(AN96*(1+$AC$6/100),AN96),0) -> 219 | O96: =ROUNDUP(IFERROR(AP96*(1+$AC$6/100),AP96),0) -> 240 | Q96: =ROUNDUP(IFERROR(AR96*(1+$AC$6/100),AR96),0) -> 260 | S96: =ROUNDUP(IFERROR(AT96*(1+$AC$6/100),AT96),0) -> 281 | U96: =ROUNDUP(IFERROR(AV96*(1+$AC$6/100),AV96),0) -> 309 | W96: =ROUNDUP(IFERROR(AX96*(1+$AC$6/100),AX96),0) -> 333 | Y96: 2600 | AB96: 2600 | AD96: 150 | AF96: 176 | AH96: 203 | AJ96: 230 | AL96: 256 | AN96: 291 | AP96: 319 | AR96: 346 | AT96: 374 | AV96: 411 | AX96: 444
A97: 2800 | C97: =ROUNDUP(IFERROR(AD97*(1+$AC$6/100),AD97),0) -> 120 | E97: =ROUNDUP(IFERROR(AF97*(1+$AC$6/100),AF97),0) -> 141 | G97: =ROUNDUP(IFERROR(AH97*(1+$AC$6/100),AH97),0) -> 162 | I97: =ROUNDUP(IFERROR(AJ97*(1+$AC$6/100),AJ97),0) -> 183 | K97: =ROUNDUP(IFERROR(AL97*(1+$AC$6/100),AL97),0) -> 205 | M97: =ROUNDUP(IFERROR(AN97*(1+$AC$6/100),AN97),0) -> 233 | O97: =ROUNDUP(IFERROR(AP97*(1+$AC$6/100),AP97),0) -> 255 | Q97: =ROUNDUP(IFERROR(AR97*(1+$AC$6/100),AR97),0) -> 276 | S97: =ROUNDUP(IFERROR(AT97*(1+$AC$6/100),AT97),0) -> 299 | U97: =ROUNDUP(IFERROR(AV97*(1+$AC$6/100),AV97),0) -> 327 | W97: =ROUNDUP(IFERROR(AX97*(1+$AC$6/100),AX97),0) -> 354 | Y97: 2800 | AB97: 2800 | AD97: 159 | AF97: 187 | AH97: 216 | AJ97: 244 | AL97: 273 | AN97: 310 | AP97: 339 | AR97: 368 | AT97: 398 | AV97: 436 | AX97: 472
A98: 3000 | C98: =ROUNDUP(IFERROR(AD98*(1+$AC$6/100),AD98),0) -> 126 | E98: =ROUNDUP(IFERROR(AF98*(1+$AC$6/100),AF98),0) -> 149 | G98: =ROUNDUP(IFERROR(AH98*(1+$AC$6/100),AH98),0) -> 176 | I98: =ROUNDUP(IFERROR(AJ98*(1+$AC$6/100),AJ98),0) -> 200 | K98: =ROUNDUP(IFERROR(AL98*(1+$AC$6/100),AL98),0) -> 223 | M98: =ROUNDUP(IFERROR(AN98*(1+$AC$6/100),AN98),0) -> 246 | O98: =ROUNDUP(IFERROR(AP98*(1+$AC$6/100),AP98),0) -> 276 | Q98: =ROUNDUP(IFERROR(AR98*(1+$AC$6/100),AR98),0) -> 299 | S98: =ROUNDUP(IFERROR(AT98*(1+$AC$6/100),AT98),0) -> 323 | U98: =ROUNDUP(IFERROR(AV98*(1+$AC$6/100),AV98),0) -> 347 | W98: =ROUNDUP(IFERROR(AX98*(1+$AC$6/100),AX98),0) -> 375 | Y98: 3000 | AB98: 3000 | AD98: 168 | AF98: 198 | AH98: 234 | AJ98: 266 | AL98: 297 | AN98: 328 | AP98: 367 | AR98: 398 | AT98: 430 | AV98: 462 | AX98: 500
A99: 3200 | C99: =ROUNDUP(IFERROR(AD99*(1+$AC$6/100),AD99),0) -> 133 | E99: =ROUNDUP(IFERROR(AF99*(1+$AC$6/100),AF99),0) -> 157 | G99: =ROUNDUP(IFERROR(AH99*(1+$AC$6/100),AH99),0) -> 186 | I99: =ROUNDUP(IFERROR(AJ99*(1+$AC$6/100),AJ99),0) -> 210 | K99: =ROUNDUP(IFERROR(AL99*(1+$AC$6/100),AL99),0) -> 235 | M99: =ROUNDUP(IFERROR(AN99*(1+$AC$6/100),AN99),0) -> 260 | O99: =ROUNDUP(IFERROR(AP99*(1+$AC$6/100),AP99),0) -> 291 | Q99: =ROUNDUP(IFERROR(AR99*(1+$AC$6/100),AR99),0) -> 316 | S99: =ROUNDUP(IFERROR(AT99*(1+$AC$6/100),AT99),0) -> 341 | U99: =ROUNDUP(IFERROR(AV99*(1+$AC$6/100),AV99),0) -> 366 | W99: =ROUNDUP(IFERROR(AX99*(1+$AC$6/100),AX99),0) -> 396 | Y99: 3200 | AB99: 3200 | AD99: 177 | AF99: 209 | AH99: 247 | AJ99: 280 | AL99: 313 | AN99: 346 | AP99: 387 | AR99: 421 | AT99: 454 | AV99: 488 | AX99: 527
A100: 3400 | C100: =ROUNDUP(IFERROR(AD100*(1+$AC$6/100),AD100),0) -> 140 | E100: =ROUNDUP(IFERROR(AF100*(1+$AC$6/100),AF100),0) -> 165 | G100: =ROUNDUP(IFERROR(AH100*(1+$AC$6/100),AH100),0) -> 195 | I100: =ROUNDUP(IFERROR(AJ100*(1+$AC$6/100),AJ100),0) -> 222 | K100: =ROUNDUP(IFERROR(AL100*(1+$AC$6/100),AL100),0) -> 248 | M100: =ROUNDUP(IFERROR(AN100*(1+$AC$6/100),AN100),0) -> 274 | O100: =ROUNDUP(IFERROR(AP100*(1+$AC$6/100),AP100),0) -> 306 | Q100: =ROUNDUP(IFERROR(AR100*(1+$AC$6/100),AR100),0) -> 333 | S100: =ROUNDUP(IFERROR(AT100*(1+$AC$6/100),AT100),0) -> 359 | U100: =ROUNDUP(IFERROR(AV100*(1+$AC$6/100),AV100),0) -> 386 | W100: =ROUNDUP(IFERROR(AX100*(1+$AC$6/100),AX100),0) -> 417 | Y100: 3400 | AB100: 3400 | AD100: 186 | AF100: 220 | AH100: 260 | AJ100: 295 | AL100: 330 | AN100: 365 | AP100: 407 | AR100: 443 | AT100: 478 | AV100: 514 | AX100: 555
A103: Acmeda CF90 Cassette
C104: 1000 | E104: 1200 | G104: 1400 | I104: 1600 | K104: 1800 | M104: 2000 | O104: 2200 | Q104: 2400 | S104: 2600 | U104: 2800 | W104: 3000 | AD104: 1000 | AF104: 1200 | AH104: 1400 | AJ104: 1600 | AL104: 1800 | AN104: 2000 | AP104: 2200 | AR104: 2400 | AT104: 2600 | AV104: 2800 | AX104: 3000
A105: Cassette ONLY | C105: 180 | E105: 186 | G105: 210 | I105: 233 | K105: 259 | M105: 280 | O105: 304 | Q105: 328 | S105: 351 | U105: 375 | W105: 399
A106: (Prices are in addition to single blind cost)
A107: Acmeda CF90 Cassette with Side Channels
A108: (Prices are in addition to single blind cost)
...

Sheet IB - Venetians
C2: Blinds | W2: Luxe Blinds Shutters Awnings
A4: Venetians Collection | W4: =Cover!I59 -> 46113
AD6: -25
B8: Ultraslat
B10: Ultraslat 50mm
C11: 610 | D11: 710 | E11: 810 | F11: 910 | G11: 1010 | H11: 1110 | I11: 1210 | J11: 1310 | K11: 1410 | L11: 1510 | M11: 1610 | N11: 1710 | O11: 1810 | P11: 1910 | Q11: 2010 | R11: 2110 | S11: 2210 | T11: 2310 | U11: 2410 | V11: 2510 | W11: 2610 | X11: 2710 | AD11: 610 | AE11: 710 | AF11: 810 | AG11: 910 | AH11: 1010 | AI11: 1110 | AJ11: 1210 | AK11: 1310 | AL11: 1410 | AM11: 1510 | AN11: 1610 | AO11: 1710 | AP11: 1810 | AQ11: 1910 | AR11: 2010 | AS11: 2110 | AT11: 2210 | AU11: 2310 | AV11: 2410 | AW11: 2510 | AX11: 2610 | AY11: 2710
B12: 600 | C12: =ROUNDUP(IFERROR(AD12*(1+$AD$6/100),AD12),0) -> 57 | D12: =ROUNDUP(IFERROR(AE12*(1+$AD$6/100),AE12),0) -> 65 | E12: =ROUNDUP(IFERROR(AF12*(1+$AD$6/100),AF12),0) -> 71 | F12: =ROUNDUP(IFERROR(AG12*(1+$AD$6/100),AG12),0) -> 77 | G12: =ROUNDUP(IFERROR(AH12*(1+$AD$6/100),AH12),0) -> 85 | H12: =ROUNDUP(IFERROR(AI12*(1+$AD$6/100),AI12),0) -> 90 | I12: =ROUNDUP(IFERROR(AJ12*(1+$AD$6/100),AJ12),0) -> 96 | J12: =ROUNDUP(IFERROR(AK12*(1+$AD$6/100),AK12),0) -> 106 | ... X12: =ROUNDUP(IFERROR(AY12*(1+$AD$6/100),AY12),0) -> 184 | Y12: 600 | AD12: 76 | AE12: 86 | AF12: 94 | AG12: 102 | AH12: 113 | AI12: 120 | AJ12: 128 | AK12: 141 | AL12: 149 | AM12: 157 | AN12: 164 | AO12: 169 | AP12: 179 | AQ12: 187 | AR12: 194 | AS12: 201 | AT12: 209 | AU12: 216 | AV12: 223 | AW12: 231 | AX12: 238 | AY12: 245
B13: 800 | C13: =ROUNDUP(IFERROR(AD13*(1+$AD$6/100),AD13),0) -> 65 | D13: =ROUNDUP(IFERROR(AE13*(1+$AD$6/100),AE13),0) -> 75 | E13: =ROUNDUP(IFERROR(AF13*(1+$AD$6/100),AF13),0) -> 81 | F13: =ROUNDUP(IFERROR(AG13*(1+$AD$6/100),AG13),0) -> 89 | G13: =ROUNDUP(IFERROR(AH13*(1+$AD$6/100),AH13),0) -> 98 | H13: =ROUNDUP(IFERROR(AI13*(1+$AD$6/100),AI13),0) -> 105 | I13: =ROUNDUP(IFERROR(AJ13*(1+$AD$6/100),AJ13),0) -> 112 | J13: =ROUNDUP(IFERROR(AK13*(1+$AD$6/100),AK13),0) -> 117 | ... X13: =ROUNDUP(IFERROR(AY13*(1+$AD$6/100),AY13),0) -> 216 | Y13: 800 | AD13: 86 | AE13: 99 | AF13: 108 | AG13: 118 | AH13: 130 | AI13: 140 | AJ13: 149 | AK13: 155 | AL13: 164 | AM13: 173 | AN13: 182 | AO13: 196 | AP13: 209 | AQ13: 218 | AR13: 226 | AS13: 235 | AT13: 244 | AU13: 253 | AV13: 262 | AW13: 271 | AX13: 280 | AY13: 288
B14: 1000 | C14: =ROUNDUP(IFERROR(AD14*(1+$AD$6/100),AD14),0) -> 73 | D14: =ROUNDUP(IFERROR(AE14*(1+$AD$6/100),AE14),0) -> 84 | E14: =ROUNDUP(IFERROR(AF14*(1+$AD$6/100),AF14),0) -> 92 | F14: =ROUNDUP(IFERROR(AG14*(1+$AD$6/100),AG14),0) -> 100 | G14: =ROUNDUP(IFERROR(AH14*(1+$AD$6/100),AH14),0) -> 105 | H14: =ROUNDUP(IFERROR(AI14*(1+$AD$6/100),AI14),0) -> 113 | I14: =ROUNDUP(IFERROR(AJ14*(1+$AD$6/100),AJ14),0) -> 120 | J14: =ROUNDUP(IFERROR(AK14*(1+$AD$6/100),AK14),0) -> 132 | ... X14: =ROUNDUP(IFERROR(AY14*(1+$AD$6/100),AY14),0) -> 249 | Y14: 1000 | AD14: 97 | AE14: 111 | AF14: 122 | AG14: 133 | AH14: 140 | AI14: 150 | AJ14: 160 | AK14: 176 | AL14: 187 | AM14: 197 | AN14: 207 | AO14: 224 | AP14: 238 | AQ14: 248 | AR14: 259 | AS14: 269 | AT14: 279 | AU14: 290 | AV14: 300 | AW14: 311 | AX14: 321 | AY14: 332
B15: 1200 | C15: =ROUNDUP(IFERROR(AD15*(1+$AD$6/100),AD15),0) -> 81 | D15: =ROUNDUP(IFERROR(AE15*(1+$AD$6/100),AE15),0) -> 93 | E15: =ROUNDUP(IFERROR(AF15*(1+$AD$6/100),AF15),0) -> 102 | F15: =ROUNDUP(IFERROR(AG15*(1+$AD$6/100),AG15),0) -> 106 | G15: =ROUNDUP(IFERROR(AH15*(1+$AD$6/100),AH15),0) -> 117 | H15: =ROUNDUP(IFERROR(AI15*(1+$AD$6/100),AI15),0) -> 126 | I15: =ROUNDUP(IFERROR(AJ15*(1+$AD$6/100),AJ15),0) -> 135 | J15: =ROUNDUP(IFERROR(AK15*(1+$AD$6/100),AK15),0) -> 148 | ... X15: =ROUNDUP(IFERROR(AY15*(1+$AD$6/100),AY15),0) -> 282 | Y15: 1200 | AD15: 107 | AE15: 123 | AF15: 136 | AG15: 141 | AH15: 156 | AI15: 168 | AJ15: 180 | AK15: 197 | AL15: 209 | AM15: 221 | AN15: 233 | AO15: 252 | AP15: 267 | AQ15: 279 | AR15: 291 | AS15: 303 | AT15: 315 | AU15: 327 | AV15: 339 | AW15: 351 | AX15: 363 | AY15: 375
B16: 1400 | C16: =ROUNDUP(IFERROR(AD16*(1+$AD$6/100),AD16),0) -> 89 | D16: =ROUNDUP(IFERROR(AE16*(1+$AD$6/100),AE16),0) -> 102 | E16: =ROUNDUP(IFERROR(AF16*(1+$AD$6/100),AF16),0) -> 107 | F16: =ROUNDUP(IFERROR(AG16*(1+$AD$6/100),AG16),0) -> 117 | G16: =ROUNDUP(IFERROR(AH16*(1+$AD$6/100),AH16),0) -> 130 | H16: =ROUNDUP(IFERROR(AI16*(1+$AD$6/100),AI16),0) -> 140 | I16: =ROUNDUP(IFERROR(AJ16*(1+$AD$6/100),AJ16),0) -> 150 | J16: =ROUNDUP(IFERROR(AK16*(1+$AD$6/100),AK16),0) -> 165 | ... X16: =ROUNDUP(IFERROR(AY16*(1+$AD$6/100),AY16),0) -> 314 | Y16: 1400 | AD16: 118 | AE16: 136 | AF16: 142 | AG16: 156 | AH16: 173 | AI16: 186 | AJ16: 200 | AK16: 219 | AL16: 232 | AM16: 246 | AN16: 259 | AO16: 279 | AP16: 296 | AQ16: 310 | AR16: 323 | AS16: 337 | AT16: 350 | AU16: 364 | AV16: 377 | AW16: 391 | AX16: 404 | AY16: 418
B17: 1600 | C17: =ROUNDUP(IFERROR(AD17*(1+$AD$6/100),AD17),0) -> 97 | D17: =ROUNDUP(IFERROR(AE17*(1+$AD$6/100),AE17),0) -> 105 | E17: =ROUNDUP(IFERROR(AF17*(1+$AD$6/100),AF17),0) -> 117 | F17: =ROUNDUP(IFERROR(AG17*(1+$AD$6/100),AG17),0) -> 128 | G17: =ROUNDUP(IFERROR(AH17*(1+$AD$6/100),AH17),0) -> 142 | H17: =ROUNDUP(IFERROR(AI17*(1+$AD$6/100),AI17),0) -> 153 | I17: =ROUNDUP(IFERROR(AJ17*(1+$AD$6/100),AJ17),0) -> 165 | J17: =ROUNDUP(IFERROR(AK17*(1+$AD$6/100),AK17),0) -> 180 | ... X17: =ROUNDUP(IFERROR(AY17*(1+$AD$6/100),AY17),0) -> 346 | Y17: 1600 | AD17: 129 | AE17: 140 | AF17: 155 | AG17: 170 | AH17: 189 | AI17: 204 | AJ17: 219 | AK17: 240 | AL17: 255 | AM17: 270 | AN17: 285 | AO17: 307 | AP17: 325 | AQ17: 340 | AR17: 355 | AS17: 371 | AT17: 386 | AU17: 401 | AV17: 416 | AW17: 431 | AX17: 446 | AY17: 461
B18: 1800 | C18: =ROUNDUP(IFERROR(AD18*(1+$AD$6/100),AD18),0) -> 101 | D18: =ROUNDUP(IFERROR(AE18*(1+$AD$6/100),AE18),0) -> 116 | E18: =ROUNDUP(IFERROR(AF18*(1+$AD$6/100),AF18),0) -> 129 | F18: =ROUNDUP(IFERROR(AG18*(1+$AD$6/100),AG18),0) -> 141 | G18: =ROUNDUP(IFERROR(AH18*(1+$AD$6/100),AH18),0) -> 156 | H18: =ROUNDUP(IFERROR(AI18*(1+$AD$6/100),AI18),0) -> 168 | I18: =ROUNDUP(IFERROR(AJ18*(1+$AD$6/100),AJ18),0) -> 181 | J18: =ROUNDUP(IFERROR(AK18*(1+$AD$6/100),AK18),0) -> 196 | ... X18: =ROUNDUP(IFERROR(AY18*(1+$AD$6/100),AY18),0) -> 378 | Y18: 1800 | AD18: 134 | AE18: 154 | AF18: 171 | AG18: 187 | AH18: 208 | AI18: 224 | AJ18: 241 | AK18: 261 | AL18: 278 | AM18: 294 | AN18: 311 | AO18: 335 | AP18: 354 | AQ18: 371 | AR18: 388 | AS18: 404 | AT18: 421 | AU18: 438 | AV18: 454 | AW18: 471 | AX18: 488 | AY18: 504
B19: 2000 | C19: =ROUNDUP(IFERROR(AD19*(1+$AD$6/100),AD19),0) -> 108 | D19: =ROUNDUP(IFERROR(AE19*(1+$AD$6/100),AE19),0) -> 125 | E19: =ROUNDUP(IFERROR(AF19*(1+$AD$6/100),AF19),0) -> 138 | F19: =ROUNDUP(IFERROR(AG19*(1+$AD$6/100),AG19),0) -> 152 | G19: =ROUNDUP(IFERROR(AH19*(1+$AD$6/100),AH19),0) -> 168 | H19: =ROUNDUP(IFERROR(AI19*(1+$AD$6/100),AI19),0) -> 182 | I19: =ROUNDUP(IFERROR(AJ19*(1+$AD$6/100),AJ19),0) -> 195 | J19: =ROUNDUP(IFERROR(AK19*(1+$AD$6/100),AK19),0) -> 212 | ... X19: =ROUNDUP(IFERROR(AY19*(1+$AD$6/100),AY19),0) -> 411 | Y19: 2000 | AD19: 144 | AE19: 166 | AF19: 184 | AG19: 202 | AH19: 224 | AI19: 242 | AJ19: 260 | AK19: 282 | AL19: 300 | AM19: 319 | AN19: 337 | AO19: 362 | AP19: 384 | AQ19: 402 | AR19: 420 | AS19: 438 | AT19: 456 | AU19: 475 | AV19: 493 | AW19: 511 | AX19: 529 | AY19: 547
B20: 2200 | C20: =ROUNDUP(IFERROR(AD20*(1+$AD$6/100),AD20),0) -> 116 | D20: =ROUNDUP(IFERROR(AE20*(1+$AD$6/100),AE20),0) -> 133 | E20: =ROUNDUP(IFERROR(AF20*(1+$AD$6/100),AF20),0) -> 148 | F20: =ROUNDUP(IFERROR(AG20*(1+$AD$6/100),AG20),0) -> 163 | G20: =ROUNDUP(IFERROR(AH20*(1+$AD$6/100),AH20),0) -> 180 | H20: =ROUNDUP(IFERROR(AI20*(1+$AD$6/100),AI20),0) -> 195 | I20: =ROUNDUP(IFERROR(AJ20*(1+$AD$6/100),AJ20),0) -> 210 | J20: =ROUNDUP(IFERROR(AK20*(1+$AD$6/100),AK20),0) -> 228 | ... X20: =ROUNDUP(IFERROR(AY20*(1+$AD$6/100),AY20),0) -> 444 | Y20: 2200 | AD20: 154 | AE20: 177 | AF20: 197 | AG20: 217 | AH20: 240 | AI20: 260 | AJ20: 280 | AK20: 303 | AL20: 323 | AM20: 343 | AN20: 363 | AO20: 390 | AP20: 413 | AQ20: 433 | AR20: 452 | AS20: 472 | AT20: 492 | AU20: 512 | AV20: 531 | AW20: 551 | AX20: 571 | AY20: 591
B21: 2400 | C21: =ROUNDUP(IFERROR(AD21*(1+$AD$6/100),AD21),0) -> 126 | D21: =ROUNDUP(IFERROR(AE21*(1+$AD$6/100),AE21),0) -> 144 | E21: =ROUNDUP(IFERROR(AF21*(1+$AD$6/100),AF21),0) -> 161 | F21: =ROUNDUP(IFERROR(AG21*(1+$AD$6/100),AG21),0) -> 177 | G21: =ROUNDUP(IFERROR(AH21*(1+$AD$6/100),AH21),0) -> 195 | H21: =ROUNDUP(IFERROR(AI21*(1+$AD$6/100),AI21),0) -> 211 | I21: =ROUNDUP(IFERROR(AJ21*(1+$AD$6/100),AJ21),0) -> 228 | J21: =ROUNDUP(IFERROR(AK21*(1+$AD$6/100),AK21),0) -> 246 | ... U21: =ROUNDUP(IFERROR(AV21*(1+$AD$6/100),AV21),0) -> 428 | V21: N/A | W21: N/A | X21: N/A | Y21: 2400 | AD21: 167 | AE21: 192 | AF21: 214 | AG21: 235 | AH21: 260 | AI21: 281 | AJ21: 303 | AK21: 328 | AL21: 349 | AM21: 370 | AN21: 392 | AO21: 421 | AP21: 442 | AQ21: 463 | AR21: 485 | AS21: 506 | AT21: 527 | AU21: 549 | AV21: 570 | AW21: 0 | AX21: 0 | AY21: 0
B22: 2600 | C22: =ROUNDUP(IFERROR(AD22*(1+$AD$6/100),AD22),0) -> 133 | D22: =ROUNDUP(IFERROR(AE22*(1+$AD$6/100),AE22),0) -> 153 | E22: =ROUNDUP(IFERROR(AF22*(1+$AD$6/100),AF22),0) -> 171 | F22: =ROUNDUP(IFERROR(AG22*(1+$AD$6/100),AG22),0) -> 188 | G22: =ROUNDUP(IFERROR(AH22*(1+$AD$6/100),AH22),0) -> 207 | H22: =ROUNDUP(IFERROR(AI22*(1+$AD$6/100),AI22),0) -> 225 | I22: =ROUNDUP(IFERROR(AJ22*(1+$AD$6/100),AJ22),0) -> 242 | J22: =ROUNDUP(IFERROR(AK22*(1+$AD$6/100),AK22),0) -> 262 | ... S22: =ROUNDUP(IFERROR(AT22*(1+$AD$6/100),AT22),0) -> 423 | T22: N/A | U22: N/A | V22: N/A | W22: N/A | X22: N/A | Y22: 2600 | AD22: 177 | AE22: 204 | AF22: 227 | AG22: 250 | AH22: 276 | AI22: 299 | AJ22: 322 | AK22: 349 | AL22: 372 | AM22: 395 | AN22: 418 | AO22: 448 | AP22: 471 | AQ22: 494 | AR22: 517 | AS22: 540 | AT22: 563 | AU22: 0 | AV22: 0 | AW22: 0 | AX22: 0 | AY22: 0
B23: 2800 | C23: =ROUNDUP(IFERROR(AD23*(1+$AD$6/100),AD23),0) -> 141 | D23: =ROUNDUP(IFERROR(AE23*(1+$AD$6/100),AE23),0) -> 162 | E23: =ROUNDUP(IFERROR(AF23*(1+$AD$6/100),AF23),0) -> 180 | F23: =ROUNDUP(IFERROR(AG23*(1+$AD$6/100),AG23),0) -> 198 | G23: =ROUNDUP(IFERROR(AH23*(1+$AD$6/100),AH23),0) -> 220 | H23: =ROUNDUP(IFERROR(AI23*(1+$AD$6/100),AI23),0) -> 238 | I23: =ROUNDUP(IFERROR(AJ23*(1+$AD$6/100),AJ23),0) -> 257 | J23: =ROUNDUP(IFERROR(AK23*(1+$AD$6/100),AK23),0) -> 278 | ... R23: =ROUNDUP(IFERROR(AS23*(1+$AD$6/100),AS23),0) -> 431 | S23: N/A | T23: N/A | U23: N/A | V23: N/A | W23: N/A | X23: N/A | Y23: 2800 | AD23: 187 | AE23: 216 | AF23: 240 | AG23: 264 | AH23: 293 | AI23: 317 | AJ23: 342 | AK23: 370 | AL23: 395 | AM23: 419 | AN23: 444 | AO23: 476 | AP23: 500 | AQ23: 525 | AR23: 549 | AS23: 574 | AT23: 0 | AU23: 0 | AV23: 0 | AW23: 0 | AX23: 0 | AY23: 0
B24: 3000 | C24: =ROUNDUP(IFERROR(AD24*(1+$AD$6/100),AD24),0) -> 148 | D24: =ROUNDUP(IFERROR(AE24*(1+$AD$6/100),AE24),0) -> 171 | E24: =ROUNDUP(IFERROR(AF24*(1+$AD$6/100),AF24),0) -> 190 | F24: =ROUNDUP(IFERROR(AG24*(1+$AD$6/100),AG24),0) -> 210 | G24: =ROUNDUP(IFERROR(AH24*(1+$AD$6/100),AH24),0) -> 232 | H24: =ROUNDUP(IFERROR(AI24*(1+$AD$6/100),AI24),0) -> 252 | I24: =ROUNDUP(IFERROR(AJ24*(1+$AD$6/100),AJ24),0) -> 271 | J24: =ROUNDUP(IFERROR(AK24*(1+$AD$6/100),AK24),0) -> 294 | ... P24: =ROUNDUP(IFERROR(AQ24*(1+$AD$6/100),AQ24),0) -> 417 | Q24: N/A | R24: N/A | S24: N/A | T24: N/A | U24: N/A | V24: N/A | W24: N/A | X24: N/A | Y24: 3000 | AD24: 197 | AE24: 227 | AF24: 253 | AG24: 279 | AH24: 309 | AI24: 335 | AJ24: 361 | AK24: 391 | AL24: 417 | AM24: 443 | AN24: 469 | AO24: 503 | AP24: 529 | AQ24: 555 | AR24: 0 | AS24: 0 | AT24: 0 | AU24: 0 | AV24: 0 | AW24: 0 | AX24: 0 | AY24: 0
B25: 3200 | C25: =ROUNDUP(IFERROR(AD25*(1+$AD$6/100),AD25),0) -> 156 | D25: =ROUNDUP(IFERROR(AE25*(1+$AD$6/100),AE25),0) -> 180 | E25: =ROUNDUP(IFERROR(AF25*(1+$AD$6/100),AF25),0) -> 200 | F25: =ROUNDUP(IFERROR(AG25*(1+$AD$6/100),AG25),0) -> 221 | G25: =ROUNDUP(IFERROR(AH25*(1+$AD$6/100),AH25),0) -> 245 | H25: =ROUNDUP(IFERROR(AI25*(1+$AD$6/100),AI25),0) -> 265 | I25: =ROUNDUP(IFERROR(AJ25*(1+$AD$6/100),AJ25),0) -> 286 | J25: =ROUNDUP(IFERROR(AK25*(1+$AD$6/100),AK25),0) -> 310 | ... O25: =ROUNDUP(IFERROR(AP25*(1+$AD$6/100),AP25),0) -> 420 | P25: N/A | Q25: N/A | R25: N/A | S25: N/A | T25: N/A | U25: N/A | V25: N/A | W25: N/A | X25: N/A | Y25: 3200 | AD25: 207 | AE25: 239 | AF25: 266 | AG25: 294 | AH25: 326 | AI25: 353 | AJ25: 381 | AK25: 413 | AL25: 440 | AM25: 468 | AN25: 495 | AO25: 531 | AP25: 559 | AQ25: 0 | AR25: 0 | AS25: 0 | AT25: 0 | AU25: 0 | AV25: 0 | AW25: 0 | AX25: 0 | AY25: 0
AD27: 0 | AE27: 0 | AF27: 0 | AG27: 0 | AH27: 0 | AI27: 0 | AJ27: 0 | AK27: 0 | AL27: 0 | AM27: 0 | AN27: 0 | AO27: 0 | AP27: 0 | AQ27: 0 | AR27: 0 | AS27: 0 | AT27: 0 | AU27: 0 | AV27: 0 | AW27: 0 | AX27: 0 | AY27: 0
B28: Ultraslat 63mm | AD28: 0 | AE28: 0 | AF28: 0 | AG28: 0 | AH28: 0 | AI28: 0 | AJ28: 0 | AK28: 0 | AL28: 0 | AM28: 0 | AN28: 0 | AO28: 0 | AP28: 0 | AQ28: 0 | AR28: 0 | AS28: 0 | AT28: 0 | AU28: 0 | AV28: 0 | AW28: 0 | AX28: 0 | AY28: 0
C29: 610 | D29: 710 | E29: 810 | F29: 910 | G29: 1010 | H29: 1110 | I29: 1210 | J29: 1310 | K29: 1410 | L29: 1510 | M29: 1610 | N29: 1710 | O29: 1810 | P29: 1910 | Q29: 2010 | R29: 2110 | S29: 2210 | T29: 2310 | U29: 2410 | V29: 2510 | W29: 2610 | X29: 2710 | AD29: 610 | AE29: 710 | AF29: 810 | AG29: 910 | AH29: 1010 | AI29: 1110 | AJ29: 1210 | AK29: 1310 | AL29: 1410 | AM29: 1510 | AN29: 1610 | AO29: 1710 | AP29: 1810 | AQ29: 1910 | AR29: 2010 | AS29: 2110 | AT29: 2210 | AU29: 2310 | AV29: 2410 | AW29: 2510 | AX29: 2610 | AY29: 2710
B30: 600 | C30: =ROUNDUP(IFERROR(AD30*(1+$AD$6/100),AD30),0) -> 68 | D30: =ROUNDUP(IFERROR(AE30*(1+$AD$6/100),AE30),0) -> 78 | E30: =ROUNDUP(IFERROR(AF30*(1+$AD$6/100),AF30),0) -> 84 | F30: =ROUNDUP(IFERROR(AG30*(1+$AD$6/100),AG30),0) -> 92 | G30: =ROUNDUP(IFERROR(AH30*(1+$AD$6/100),AH30),0) -> 102 | H30: =ROUNDUP(IFERROR(AI30*(1+$AD$6/100),AI30),0) -> 108 | I30: =ROUNDUP(IFERROR(AJ30*(1+$AD$6/100),AJ30),0) -> 115 | J30: =ROUNDUP(IFERROR(AK30*(1+$AD$6/100),AK30),0) -> 127 | ... X30: =ROUNDUP(IFERROR(AY30*(1+$AD$6/100),AY30),0) -> 220 | AD30: 90 | AE30: 103 | AF30: 112 | AG30: 122 | AH30: 135 | AI30: 144 | AJ30: 153 | AK30: 169 | AL30: 178 | AM30: 187 | AN30: 197 | AO30: 202 | AP30: 214 | AQ30: 223 | AR30: 232 | AS30: 241 | AT30: 249 | AU30: 258 | AV30: 267 | AW30: 276 | AX30: 284 | AY30: 293
B31: 800 | C31: =ROUNDUP(IFERROR(AD31*(1+$AD$6/100),AD31),0) -> 78 | D31: =ROUNDUP(IFERROR(AE31*(1+$AD$6/100),AE31),0) -> 89 | E31: =ROUNDUP(IFERROR(AF31*(1+$AD$6/100),AF31),0) -> 97 | F31: =ROUNDUP(IFERROR(AG31*(1+$AD$6/100),AG31),0) -> 105 | G31: =ROUNDUP(IFERROR(AH31*(1+$AD$6/100),AH31),0) -> 117 | H31: =ROUNDUP(IFERROR(AI31*(1+$AD$6/100),AI31),0) -> 126 | I31: =ROUNDUP(IFERROR(AJ31*(1+$AD$6/100),AJ31),0) -> 134 | J31: =ROUNDUP(IFERROR(AK31*(1+$AD$6/100),AK31),0) -> 139 | ... X31: =ROUNDUP(IFERROR(AY31*(1+$AD$6/100),AY31),0) -> 259 | AD31: 103 | AE31: 118 | AF31: 129 | AG31: 140 | AH31: 156 | AI31: 167 | AJ31: 178 | AK31: 185 | AL31: 196 | AM31: 206 | AN31: 217 | AO31: 235 | AP31: 249 | AQ31: 260 | AR31: 271 | AS31: 281 | AT31: 292 | AU31: 302 | AV31: 313 | AW31: 324 | AX31: 334 | AY31: 345
B32: 1000 | C32: =ROUNDUP(IFERROR(AD32*(1+$AD$6/100),AD32),0) -> 87 | D32: =ROUNDUP(IFERROR(AE32*(1+$AD$6/100),AE32),0) -> 100 | E32: =ROUNDUP(IFERROR(AF32*(1+$AD$6/100),AF32),0) -> 110 | F32: =ROUNDUP(IFERROR(AG32*(1+$AD$6/100),AG32),0) -> 120 | G32: =ROUNDUP(IFERROR(AH32*(1+$AD$6/100),AH32),0) -> 126 | H32: =ROUNDUP(IFERROR(AI32*(1+$AD$6/100),AI32),0) -> 135 | I32: =ROUNDUP(IFERROR(AJ32*(1+$AD$6/100),AJ32),0) -> 144 | J32: =ROUNDUP(IFERROR(AK32*(1+$AD$6/100),AK32),0) -> 159 | ... X32: =ROUNDUP(IFERROR(AY32*(1+$AD$6/100),AY32),0) -> 297 | AD32: 116 | AE32: 133 | AF32: 146 | AG32: 159 | AH32: 167 | AI32: 179 | AJ32: 192 | AK32: 211 | AL32: 223 | AM32: 236 | AN32: 248 | AO32: 268 | AP32: 284 | AQ32: 297 | AR32: 309 | AS32: 322 | AT32: 334 | AU32: 347 | AV32: 359 | AW32: 371 | AX32: 384 | AY32: 396
B33: 1200 | C33: =ROUNDUP(IFERROR(AD33*(1+$AD$6/100),AD33),0) -> 96 | D33: =ROUNDUP(IFERROR(AE33*(1+$AD$6/100),AE33),0) -> 111 | E33: =ROUNDUP(IFERROR(AF33*(1+$AD$6/100),AF33),0) -> 123 | F33: =ROUNDUP(IFERROR(AG33*(1+$AD$6/100),AG33),0) -> 126 | G33: =ROUNDUP(IFERROR(AH33*(1+$AD$6/100),AH33),0) -> 141 | H33: =ROUNDUP(IFERROR(AI33*(1+$AD$6/100),AI33),0) -> 151 | I33: =ROUNDUP(IFERROR(AJ33*(1+$AD$6/100),AJ33),0) -> 162 | J33: =ROUNDUP(IFERROR(AK33*(1+$AD$6/100),AK33),0) -> 177 | ... X33: =ROUNDUP(IFERROR(AY33*(1+$AD$6/100),AY33),0) -> 336 | AD33: 128 | AE33: 148 | AF33: 163 | AG33: 168 | AH33: 187 | AI33: 201 | AJ33: 215 | AK33: 236 | AL33: 250 | AM33: 265 | AN33: 279 | AO33: 301 | AP33: 319 | AQ33: 333 | AR33: 348 | AS33: 362 | AT33: 376 | AU33: 391 | AV33: 405 | AW33: 419 | AX33: 434 | AY33: 448
B34: 1400 | C34: =ROUNDUP(IFERROR(AD34*(1+$AD$6/100),AD34),0) -> 106 | D34: =ROUNDUP(IFERROR(AE34*(1+$AD$6/100),AE34),0) -> 122 | E34: =ROUNDUP(IFERROR(AF34*(1+$AD$6/100),AF34),0) -> 128 | F34: =ROUNDUP(IFERROR(AG34*(1+$AD$6/100),AG34),0) -> 140 | G34: =ROUNDUP(IFERROR(AH34*(1+$AD$6/100),AH34),0) -> 155 | H34: =ROUNDUP(IFERROR(AI34*(1+$AD$6/100),AI34),0) -> 167 | I34: =ROUNDUP(IFERROR(AJ34*(1+$AD$6/100),AJ34),0) -> 180 | J34: =ROUNDUP(IFERROR(AK34*(1+$AD$6/100),AK34),0) -> 196 | ... X34: =ROUNDUP(IFERROR(AY34*(1+$AD$6/100),AY34),0) -> 375 | AD34: 141 | AE34: 162 | AF34: 170 | AG34: 186 | AH34: 206 | AI34: 222 | AJ34: 239 | AK34: 261 | AL34: 277 | AM34: 294 | AN34: 310 | AO34: 334 | AP34: 354 | AQ34: 370 | AR34: 386 | AS34: 403 | AT34: 419 | AU34: 435 | AV34: 451 | AW34: 467 | AX34: 483 | AY34: 500
B35: 1600 | C35: =ROUNDUP(IFERROR(AD35*(1+$AD$6/100),AD35),0) -> 116 | D35: =ROUNDUP(IFERROR(AE35*(1+$AD$6/100),AE35),0) -> 126 | E35: =ROUNDUP(IFERROR(AF35*(1+$AD$6/100),AF35),0) -> 140 | F35: =ROUNDUP(IFERROR(AG35*(1+$AD$6/100),AG35),0) -> 153 | G35: =ROUNDUP(IFERROR(AH35*(1+$AD$6/100),AH35),0) -> 170 | H35: =ROUNDUP(IFERROR(AI35*(1+$AD$6/100),AI35),0) -> 183 | I35: =ROUNDUP(IFERROR(AJ35*(1+$AD$6/100),AJ35),0) -> 197 | J35: =ROUNDUP(IFERROR(AK35*(1+$AD$6/100),AK35),0) -> 216 | ... X35: =ROUNDUP(IFERROR(AY35*(1+$AD$6/100),AY35),0) -> 414 | AD35: 154 | AE35: 168 | AF35: 186 | AG35: 204 | AH35: 226 | AI35: 244 | AJ35: 262 | AK35: 287 | AL35: 305 | AM35: 323 | AN35: 341 | AO35: 367 | AP35: 389 | AQ35: 407 | AR35: 425 | AS35: 443 | AT35: 461 | AU35: 479 | AV35: 497 | AW35: 515 | AX35: 533 | AY35: 551
B36: 1800 | C36: =ROUNDUP(IFERROR(AD36*(1+$AD$6/100),AD36),0) -> 120 | D36: =ROUNDUP(IFERROR(AE36*(1+$AD$6/100),AE36),0) -> 138 | E36: =ROUNDUP(IFERROR(AF36*(1+$AD$6/100),AF36),0) -> 153 | F36: =ROUNDUP(IFERROR(AG36*(1+$AD$6/100),AG36),0) -> 168 | G36: =ROUNDUP(IFERROR(AH36*(1+$AD$6/100),AH36),0) -> 186 | H36: =ROUNDUP(IFERROR(AI36*(1+$AD$6/100),AI36),0) -> 201 | I36: =ROUNDUP(IFERROR(AJ36*(1+$AD$6/100),AJ36),0) -> 216 | J36: =ROUNDUP(IFERROR(AK36*(1+$AD$6/100),AK36),0) -> 234 | ... X36: =ROUNDUP(IFERROR(AY36*(1+$AD$6/100),AY36),0) -> 453 | AD36: 160 | AE36: 184 | AF36: 204 | AG36: 224 | AH36: 248 | AI36: 268 | AJ36: 288 | AK36: 312 | AL36: 332 | AM36: 352 | AN36: 372 | AO36: 400 | AP36: 424 | AQ36: 444 | AR36: 464 | AS36: 483 | AT36: 503 | AU36: 523 | AV36: 543 | AW36: 563 | AX36: 583 | AY36: 603
B37: 2000 | C37: =ROUNDUP(IFERROR(AD37*(1+$AD$6/100),AD37),0) -> 129 | D37: =ROUNDUP(IFERROR(AE37*(1+$AD$6/100),AE37),0) -> 149 | E37: =ROUNDUP(IFERROR(AF37*(1+$AD$6/100),AF37),0) -> 165 | F37: =ROUNDUP(IFERROR(AG37*(1+$AD$6/100),AG37),0) -> 182 | G37: =ROUNDUP(IFERROR(AH37*(1+$AD$6/100),AH37),0) -> 201 | H37: =ROUNDUP(IFERROR(AI37*(1+$AD$6/100),AI37),0) -> 217 | I37: =ROUNDUP(IFERROR(AJ37*(1+$AD$6/100),AJ37),0) -> 234 | J37: =ROUNDUP(IFERROR(AK37*(1+$AD$6/100),AK37),0) -> 253 | ... X37: =ROUNDUP(IFERROR(AY37*(1+$AD$6/100),AY37),0) -> 491 | AD37: 172 | AE37: 198 | AF37: 220 | AG37: 242 | AH37: 268 | AI37: 289 | AJ37: 311 | AK37: 337 | AL37: 359 | AM37: 381 | AN37: 403 | AO37: 433 | AP37: 459 | AQ37: 480 | AR37: 502 | AS37: 524 | AT37: 546 | AU37: 567 | AV37: 589 | AW37: 611 | AX37: 633 | AY37: 654
B38: 2200 | C38: =ROUNDUP(IFERROR(AD38*(1+$AD$6/100),AD38),0) -> 138 | D38: =ROUNDUP(IFERROR(AE38*(1+$AD$6/100),AE38),0) -> 159 | E38: =ROUNDUP(IFERROR(AF38*(1+$AD$6/100),AF38),0) -> 177 | F38: =ROUNDUP(IFERROR(AG38*(1+$AD$6/100),AG38),0) -> 195 | G38: =ROUNDUP(IFERROR(AH38*(1+$AD$6/100),AH38),0) -> 216 | H38: =ROUNDUP(IFERROR(AI38*(1+$AD$6/100),AI38),0) -> 234 | I38: =ROUNDUP(IFERROR(AJ38*(1+$AD$6/100),AJ38),0) -> 252 | J38: =ROUNDUP(IFERROR(AK38*(1+$AD$6/100),AK38),0) -> 273 | ... X38: =ROUNDUP(IFERROR(AY38*(1+$AD$6/100),AY38),0) -> 530 | AD38: 184 | AE38: 212 | AF38: 236 | AG38: 259 | AH38: 287 | AI38: 311 | AJ38: 335 | AK38: 363 | AL38: 386 | AM38: 410 | AN38: 434 | AO38: 466 | AP38: 493 | AQ38: 517 | AR38: 541 | AS38: 564 | AT38: 588 | AU38: 612 | AV38: 635 | AW38: 659 | AX38: 683 | AY38: 706
B39: 2400 | C39: =ROUNDUP(IFERROR(AD39*(1+$AD$6/100),AD39),0) -> 150 | D39: =ROUNDUP(IFERROR(AE39*(1+$AD$6/100),AE39),0) -> 173 | E39: =ROUNDUP(IFERROR(AF39*(1+$AD$6/100),AF39),0) -> 192 | F39: =ROUNDUP(IFERROR(AG39*(1+$AD$6/100),AG39),0) -> 211 | G39: =ROUNDUP(IFERROR(AH39*(1+$AD$6/100),AH39),0) -> 234 | H39: =ROUNDUP(IFERROR(AI39*(1+$AD$6/100),AI39),0) -> 252 | I39: =ROUNDUP(IFERROR(AJ39*(1+$AD$6/100),AJ39),0) -> 272 | J39: =ROUNDUP(IFERROR(AK39*(1+$AD$6/100),AK39),0) -> 294 | ... U39: =ROUNDUP(IFERROR(AV39*(1+$AD$6/100),AV39),0) -> 511 | V39: N/A | W39: N/A | X39: N/A | AD39: 200 | AE39: 230 | AF39: 255 | AG39: 281 | AH39: 311 | AI39: 336 | AJ39: 362 | AK39: 392 | AL39: 417 | AM39: 443 | AN39: 468 | AO39: 503 | AP39: 528 | AQ39: 554 | AR39: 579 | AS39: 605 | AT39: 630 | AU39: 656 | AV39: 681 | AW39: 0 | AX39: 0 | AY39: 0
B40: 2600 | C40: =ROUNDUP(IFERROR(AD40*(1+$AD$6/100),AD40),0) -> 159 | D40: =ROUNDUP(IFERROR(AE40*(1+$AD$6/100),AE40),0) -> 183 | E40: =ROUNDUP(IFERROR(AF40*(1+$AD$6/100),AF40),0) -> 204 | F40: =ROUNDUP(IFERROR(AG40*(1+$AD$6/100),AG40),0) -> 224 | G40: =ROUNDUP(IFERROR(AH40*(1+$AD$6/100),AH40),0) -> 248 | H40: =ROUNDUP(IFERROR(AI40*(1+$AD$6/100),AI40),0) -> 269 | I40: =ROUNDUP(IFERROR(AJ40*(1+$AD$6/100),AJ40),0) -> 289 | J40: =ROUNDUP(IFERROR(AK40*(1+$AD$6/100),AK40),0) -> 313 | ... S40: =ROUNDUP(IFERROR(AT40*(1+$AD$6/100),AT40),0) -> 505 | T40: N/A | U40: N/A | V40: N/A | W40: N/A | X40: N/A | AD40: 212 | AE40: 244 | AF40: 271 | AG40: 298 | AH40: 330 | AI40: 358 | AJ40: 385 | AK40: 417 | AL40: 445 | AM40: 472 | AN40: 499 | AO40: 536 | AP40: 563 | AQ40: 591 | AR40: 618 | AS40: 645 | AT40: 673 | AU40: 0 | AV40: 0 | AW40: 0 | AX40: 0 | AY40: 0
B41: 2800 | C41: =ROUNDUP(IFERROR(AD41*(1+$AD$6/100),AD41),0) -> 168 | D41: =ROUNDUP(IFERROR(AE41*(1+$AD$6/100),AE41),0) -> 194 | E41: =ROUNDUP(IFERROR(AF41*(1+$AD$6/100),AF41),0) -> 216 | F41: =ROUNDUP(IFERROR(AG41*(1+$AD$6/100),AG41),0) -> 237 | G41: =ROUNDUP(IFERROR(AH41*(1+$AD$6/100),AH41),0) -> 263 | H41: =ROUNDUP(IFERROR(AI41*(1+$AD$6/100),AI41),0) -> 285 | I41: =ROUNDUP(IFERROR(AJ41*(1+$AD$6/100),AJ41),0) -> 307 | J41: =ROUNDUP(IFERROR(AK41*(1+$AD$6/100),AK41),0) -> 332 | ... R41: =ROUNDUP(IFERROR(AS41*(1+$AD$6/100),AS41),0) -> 515 | S41: N/A | T41: N/A | U41: N/A | V41: N/A | W41: N/A | X41: N/A | AD41: 224 | AE41: 258 | AF41: 287 | AG41: 316 | AH41: 350 | AI41: 379 | AJ41: 409 | AK41: 442 | AL41: 472 | AM41: 501 | AN41: 530 | AO41: 569 | AP41: 598 | AQ41: 627 | AR41: 657 | AS41: 686 | AT41: 0 | AU41: 0 | AV41: 0 | AW41: 0 | AX41: 0 | AY41: 0
B42: 3000 | C42: =ROUNDUP(IFERROR(AD42*(1+$AD$6/100),AD42),0) -> 177 | D42: =ROUNDUP(IFERROR(AE42*(1+$AD$6/100),AE42),0) -> 204 | E42: =ROUNDUP(IFERROR(AF42*(1+$AD$6/100),AF42),0) -> 228 | F42: =ROUNDUP(IFERROR(AG42*(1+$AD$6/100),AG42),0) -> 251 | G42: =ROUNDUP(IFERROR(AH42*(1+$AD$6/100),AH42),0) -> 278 | H42: =ROUNDUP(IFERROR(AI42*(1+$AD$6/100),AI42),0) -> 301 | I42: =ROUNDUP(IFERROR(AJ42*(1+$AD$6/100),AJ42),0) -> 324 | J42: =ROUNDUP(IFERROR(AK42*(1+$AD$6/100),AK42),0) -> 351 | ... P42: =ROUNDUP(IFERROR(AQ42*(1+$AD$6/100),AQ42),0) -> 498 | Q42: N/A | R42: N/A | S42: N/A | T42: N/A | U42: N/A | V42: N/A | W42: N/A | X42: N/A | AD42: 236 | AE42: 272 | AF42: 303 | AG42: 334 | AH42: 370 | AI42: 401 | AJ42: 432 | AK42: 468 | AL42: 499 | AM42: 530 | AN42: 561 | AO42: 602 | AP42: 633 | AQ42: 664 | AR42: 0 | AS42: 0 | AT42: 0 | AU42: 0 | AV42: 0 | AW42: 0 | AX42: 0 | AY42: 0
B43: 3200 | C43: =ROUNDUP(IFERROR(AD43*(1+$AD$6/100),AD43),0) -> 186 | D43: =ROUNDUP(IFERROR(AE43*(1+$AD$6/100),AE43),0) -> 215 | E43: =ROUNDUP(IFERROR(AF43*(1+$AD$6/100),AF43),0) -> 240 | F43: =ROUNDUP(IFERROR(AG43*(1+$AD$6/100),AG43),0) -> 264 | G43: =ROUNDUP(IFERROR(AH43*(1+$AD$6/100),AH43),0) -> 292 | H43: =ROUNDUP(IFERROR(AI43*(1+$AD$6/100),AI43),0) -> 317 | I43: =ROUNDUP(IFERROR(AJ43*(1+$AD$6/100),AJ43),0) -> 342 | J43: =ROUNDUP(IFERROR(AK43*(1+$AD$6/100),AK43),0) -> 370 | ... O43: =ROUNDUP(IFERROR(AP43*(1+$AD$6/100),AP43),0) -> 501 | P43: N/A | Q43: N/A | R43: N/A | S43: N/A | T43: N/A | U43: N/A | V43: N/A | W43: N/A | X43: N/A | AD43: 248 | AE43: 286 | AF43: 319 | AG43: 351 | AH43: 389 | AI43: 422 | AJ43: 455 | AK43: 493 | AL43: 526 | AM43: 559 | AN43: 592 | AO43: 635 | AP43: 668 | AQ43: 0 | AR43: 0 | AS43: 0 | AT43: 0 | AU43: 0 | AV43: 0 | AW43: 0 | AX43: 0 | AY43: 0
B45: Standard Warranty is 3 Years
B46: All prices are subject to 10% GST. Prices subject to change without notice. All prices subject to CW Systems’ General Terms & Conditions - Prices do not include any applicable shipping/handling fees
B47: Page 1 of 3 | AD47: 0 | AE47: 0 | AF47: 0 | AG47: 0 | AH47: 0 | AI47: 0 | AJ47: 0 | AK47: 0 | AL47: 0 | AM47: 0 | AN47: 0 | AO47: 0 | AP47: 0 | AQ47: 0 | AR47: 0 | AS47: 0 | AT47: 0 | AU47: 0 | AV47: 0 | AW47: 0 | AX47: 0 | AY47: 0
B48: Basswood
B50: Basswood 50mm | AD50: 0 | AE50: 0 | AF50: 0 | AG50: 0 | AH50: 0 | AI50: 0 | AJ50: 0 | AK50: 0 | AL50: 0 | AM50: 0 | AN50: 0 | AO50: 0 | AP50: 0 | AQ50: 0 | AR50: 0 | AS50: 0 | AT50: 0 | AU50: 0 | AV50: 0 | AW50: 0 | AX50: 0 | AY50: 0
C51: 610 | D51: 710 | E51: 810 | F51: 910 | G51: 1010 | H51: 1110 | I51: 1210 | J51: 1310 | K51: 1410 | L51: 1510 | M51: 1610 | N51: 1710 | O51: 1810 | P51: 1910 | Q51: 2010 | R51: 2110 | S51: 2210 | T51: 2310 | U51: 2410 | V51: 2510 | W51: 2610 | X51: 2710 | AD51: 610 | AE51: 710 | AF51: 810 | AG51: 910 | AH51: 1010 | AI51: 1110 | AJ51: 1210 | AK51: 1310 | AL51: 1410 | AM51: 1510 | AN51: 1610 | AO51: 1710 | AP51: 1810 | AQ51: 1910 | AR51: 2010 | AS51: 2110 | AT51: 2210 | AU51: 2310 | AV51: 2410 | AW51: 2510 | AX51: 2610 | AY51: 2710
B52: 600 | C52: =ROUNDUP(IFERROR(AD52*(1+$AD$6/100),AD52),0) -> 79 | D52: =ROUNDUP(IFERROR(AE52*(1+$AD$6/100),AE52),0) -> 90 | E52: =ROUNDUP(IFERROR(AF52*(1+$AD$6/100),AF52),0) -> 98 | F52: =ROUNDUP(IFERROR(AG52*(1+$AD$6/100),AG52),0) -> 106 | G52: =ROUNDUP(IFERROR(AH52*(1+$AD$6/100),AH52),0) -> 117 | H52: =ROUNDUP(IFERROR(AI52*(1+$AD$6/100),AI52),0) -> 126 | I52: =ROUNDUP(IFERROR(AJ52*(1+$AD$6/100),AJ52),0) -> 134 | J52: =ROUNDUP(IFERROR(AK52*(1+$AD$6/100),AK52),0) -> 147 | ... X52: =ROUNDUP(IFERROR(AY52*(1+$AD$6/100),AY52),0) -> 264 | AD52: 105 | AE52: 120 | AF52: 130 | AG52: 141 | AH52: 156 | AI52: 167 | AJ52: 178 | AK52: 196 | AL52: 206 | AM52: 217 | AN52: 228 | AO52: 234 | AP52: 249 | AQ52: 259 | AR52: 269 | AS52: 279 | AT52: 289 | AU52: 299 | AV52: 310 | AW52: 323 | AX52: 337 | AY52: 352
B53: 800 | C53: =ROUNDUP(IFERROR(AD53*(1+$AD$6/100),AD53),0) -> 90 | D53: =ROUNDUP(IFERROR(AE53*(1+$AD$6/100),AE53),0) -> 103 | E53: =ROUNDUP(IFERROR(AF53*(1+$AD$6/100),AF53),0) -> 113 | F53: =ROUNDUP(IFERROR(AG53*(1+$AD$6/100),AG53),0) -> 123 | G53: =ROUNDUP(IFERROR(AH53*(1+$AD$6/100),AH53),0) -> 135 | H53: =ROUNDUP(IFERROR(AI53*(1+$AD$6/100),AI53),0) -> 145 | I53: =ROUNDUP(IFERROR(AJ53*(1+$AD$6/100),AJ53),0) -> 155 | J53: =ROUNDUP(IFERROR(AK53*(1+$AD$6/100),AK53),0) -> 162 | ... X53: =ROUNDUP(IFERROR(AY53*(1+$AD$6/100),AY53),0) -> 312 | AD53: 119 | AE53: 137 | AF53: 150 | AG53: 163 | AH53: 180 | AI53: 193 | AJ53: 206 | AK53: 215 | AL53: 227 | AM53: 239 | AN53: 252 | AO53: 272 | AP53: 289 | AQ53: 301 | AR53: 314 | AS53: 326 | AT53: 338 | AU53: 351 | AV53: 363 | AW53: 379 | AX53: 396 | AY53: 415
B54: 1000 | C54: =ROUNDUP(IFERROR(AD54*(1+$AD$6/100),AD54),0) -> 101 | D54: =ROUNDUP(IFERROR(AE54*(1+$AD$6/100),AE54),0) -> 116 | E54: =ROUNDUP(IFERROR(AF54*(1+$AD$6/100),AF54),0) -> 127 | F54: =ROUNDUP(IFERROR(AG54*(1+$AD$6/100),AG54),0) -> 139 | G54: =ROUNDUP(IFERROR(AH54*(1+$AD$6/100),AH54),0) -> 146 | H54: =ROUNDUP(IFERROR(AI54*(1+$AD$6/100),AI54),0) -> 156 | I54: =ROUNDUP(IFERROR(AJ54*(1+$AD$6/100),AJ54),0) -> 167 | J54: =ROUNDUP(IFERROR(AK54*(1+$AD$6/100),AK54),0) -> 183 | ... X54: =ROUNDUP(IFERROR(AY54*(1+$AD$6/100),AY54),0) -> 358 | AD54: 134 | AE54: 154 | AF54: 169 | AG54: 185 | AH54: 194 | AI54: 208 | AJ54: 222 | AK54: 244 | AL54: 259 | AM54: 273 | AN54: 288 | AO54: 311 | AP54: 330 | AQ54: 344 | AR54: 359 | AS54: 373 | AT54: 387 | AU54: 402 | AV54: 416 | AW54: 435 | AX54: 455 | AY54: 477
B55: 1200 | C55: =ROUNDUP(IFERROR(AD55*(1+$AD$6/100),AD55),0) -> 112 | D55: =ROUNDUP(IFERROR(AE55*(1+$AD$6/100),AE55),0) -> 129 | E55: =ROUNDUP(IFERROR(AF55*(1+$AD$6/100),AF55),0) -> 142 | F55: =ROUNDUP(IFERROR(AG55*(1+$AD$6/100),AG55),0) -> 147 | G55: =ROUNDUP(IFERROR(AH55*(1+$AD$6/100),AH55),0) -> 162 | H55: =ROUNDUP(IFERROR(AI55*(1+$AD$6/100),AI55),0) -> 175 | I55: =ROUNDUP(IFERROR(AJ55*(1+$AD$6/100),AJ55),0) -> 188 | J55: =ROUNDUP(IFERROR(AK55*(1+$AD$6/100),AK55),0) -> 206 | ... X55: =ROUNDUP(IFERROR(AY55*(1+$AD$6/100),AY55),0) -> 405 | AD55: 149 | AE55: 171 | AF55: 189 | AG55: 195 | AH55: 216 | AI55: 233 | AJ55: 250 | AK55: 274 | AL55: 290 | AM55: 307 | AN55: 323 | AO55: 349 | AP55: 370 | AQ55: 387 | AR55: 403 | AS55: 420 | AT55: 437 | AU55: 453 | AV55: 470 | AW55: 491 | AX55: 515 | AY55: 539
B56: 1400 | C56: =ROUNDUP(IFERROR(AD56*(1+$AD$6/100),AD56),0) -> 123 | D56: =ROUNDUP(IFERROR(AE56*(1+$AD$6/100),AE56),0) -> 141 | E56: =ROUNDUP(IFERROR(AF56*(1+$AD$6/100),AF56),0) -> 148 | F56: =ROUNDUP(IFERROR(AG56*(1+$AD$6/100),AG56),0) -> 162 | G56: =ROUNDUP(IFERROR(AH56*(1+$AD$6/100),AH56),0) -> 180 | H56: =ROUNDUP(IFERROR(AI56*(1+$AD$6/100),AI56),0) -> 194 | I56: =ROUNDUP(IFERROR(AJ56*(1+$AD$6/100),AJ56),0) -> 208 | J56: =ROUNDUP(IFERROR(AK56*(1+$AD$6/100),AK56),0) -> 228 | ... X56: =ROUNDUP(IFERROR(AY56*(1+$AD$6/100),AY56),0) -> 452 | AD56: 163 | AE56: 188 | AF56: 197 | AG56: 216 | AH56: 239 | AI56: 258 | AJ56: 277 | AK56: 303 | AL56: 322 | AM56: 341 | AN56: 359 | AO56: 387 | AP56: 410 | AQ56: 429 | AR56: 448 | AS56: 467 | AT56: 486 | AU56: 504 | AV56: 523 | AW56: 548 | AX56: 574 | AY56: 602
B57: 1600 | C57: =ROUNDUP(IFERROR(AD57*(1+$AD$6/100),AD57),0) -> 134 | D57: =ROUNDUP(IFERROR(AE57*(1+$AD$6/100),AE57),0) -> 146 | E57: =ROUNDUP(IFERROR(AF57*(1+$AD$6/100),AF57),0) -> 162 | F57: =ROUNDUP(IFERROR(AG57*(1+$AD$6/100),AG57),0) -> 177 | G57: =ROUNDUP(IFERROR(AH57*(1+$AD$6/100),AH57),0) -> 197 | H57: =ROUNDUP(IFERROR(AI57*(1+$AD$6/100),AI57),0) -> 213 | I57: =ROUNDUP(IFERROR(AJ57*(1+$AD$6/100),AJ57),0) -> 228 | J57: =ROUNDUP(IFERROR(AK57*(1+$AD$6/100),AK57),0) -> 249 | ... X57: =ROUNDUP(IFERROR(AY57*(1+$AD$6/100),AY57),0) -> 498 | AD57: 178 | AE57: 194 | AF57: 215 | AG57: 236 | AH57: 262 | AI57: 283 | AJ57: 304 | AK57: 332 | AL57: 353 | AM57: 374 | AN57: 395 | AO57: 425 | AP57: 451 | AQ57: 472 | AR57: 493 | AS57: 514 | AT57: 535 | AU57: 556 | AV57: 577 | AW57: 604 | AX57: 633 | AY57: 664
B58: 1800 | C58: =ROUNDUP(IFERROR(AD58*(1+$AD$6/100),AD58),0) -> 140 | D58: =ROUNDUP(IFERROR(AE58*(1+$AD$6/100),AE58),0) -> 160 | E58: =ROUNDUP(IFERROR(AF58*(1+$AD$6/100),AF58),0) -> 178 | F58: =ROUNDUP(IFERROR(AG58*(1+$AD$6/100),AG58),0) -> 195 | G58: =ROUNDUP(IFERROR(AH58*(1+$AD$6/100),AH58),0) -> 216 | H58: =ROUNDUP(IFERROR(AI58*(1+$AD$6/100),AI58),0) -> 234 | I58: =ROUNDUP(IFERROR(AJ58*(1+$AD$6/100),AJ58),0) -> 251 | J58: =ROUNDUP(IFERROR(AK58*(1+$AD$6/100),AK58),0) -> 272 | ... X58: =ROUNDUP(IFERROR(AY58*(1+$AD$6/100),AY58),0) -> 546 | AD58: 186 | AE58: 213 | AF58: 237 | AG58: 260 | AH58: 288 | AI58: 311 | AJ58: 334 | AK58: 362 | AL58: 385 | AM58: 408 | AN58: 431 | AO58: 464 | AP58: 491 | AQ58: 515 | AR58: 538 | AS58: 561 | AT58: 584 | AU58: 607 | AV58: 630 | AW58: 660 | AX58: 692 | AY58: 727
B59: 2000 | C59: =ROUNDUP(IFERROR(AD59*(1+$AD$6/100),AD59),0) -> 150 | D59: =ROUNDUP(IFERROR(AE59*(1+$AD$6/100),AE59),0) -> 173 | E59: =ROUNDUP(IFERROR(AF59*(1+$AD$6/100),AF59),0) -> 192 | F59: =ROUNDUP(IFERROR(AG59*(1+$AD$6/100),AG59),0) -> 210 | G59: =ROUNDUP(IFERROR(AH59*(1+$AD$6/100),AH59),0) -> 233 | H59: =ROUNDUP(IFERROR(AI59*(1+$AD$6/100),AI59),0) -> 252 | I59: =ROUNDUP(IFERROR(AJ59*(1+$AD$6/100),AJ59),0) -> 271 | J59: =ROUNDUP(IFERROR(AK59*(1+$AD$6/100),AK59),0) -> 294 | ... X59: =ROUNDUP(IFERROR(AY59*(1+$AD$6/100),AY59),0) -> 592 | AD59: 199 | AE59: 230 | AF59: 255 | AG59: 280 | AH59: 310 | AI59: 336 | AJ59: 361 | AK59: 391 | AL59: 416 | AM59: 442 | AN59: 467 | AO59: 502 | AP59: 532 | AQ59: 557 | AR59: 582 | AS59: 608 | AT59: 633 | AU59: 658 | AV59: 683 | AW59: 716 | AX59: 752 | AY59: 789
B60: 2200 | C60: =ROUNDUP(IFERROR(AD60*(1+$AD$6/100),AD60),0) -> 160 | D60: =ROUNDUP(IFERROR(AE60*(1+$AD$6/100),AE60),0) -> 185 | E60: =ROUNDUP(IFERROR(AF60*(1+$AD$6/100),AF60),0) -> 205 | F60: =ROUNDUP(IFERROR(AG60*(1+$AD$6/100),AG60),0) -> 226 | G60: =ROUNDUP(IFERROR(AH60*(1+$AD$6/100),AH60),0) -> 250 | H60: =ROUNDUP(IFERROR(AI60*(1+$AD$6/100),AI60),0) -> 271 | I60: =ROUNDUP(IFERROR(AJ60*(1+$AD$6/100),AJ60),0) -> 291 | J60: =ROUNDUP(IFERROR(AK60*(1+$AD$6/100),AK60),0) -> 315 | ... X60: =ROUNDUP(IFERROR(AY60*(1+$AD$6/100),AY60),0) -> 639 | AD60: 213 | AE60: 246 | AF60: 273 | AG60: 301 | AH60: 333 | AI60: 361 | AJ60: 388 | AK60: 420 | AL60: 448 | AM60: 475 | AN60: 503 | AO60: 540 | AP60: 572 | AQ60: 600 | AR60: 627 | AS60: 655 | AT60: 682 | AU60: 709 | AV60: 737 | AW60: 772 | AX60: 811 | AY60: 852
B61: 2400 | C61: =ROUNDUP(IFERROR(AD61*(1+$AD$6/100),AD61),0) -> 174 | D61: =ROUNDUP(IFERROR(AE61*(1+$AD$6/100),AE61),0) -> 200 | E61: =ROUNDUP(IFERROR(AF61*(1+$AD$6/100),AF61),0) -> 222 | F61: =ROUNDUP(IFERROR(AG61*(1+$AD$6/100),AG61),0) -> 245 | G61: =ROUNDUP(IFERROR(AH61*(1+$AD$6/100),AH61),0) -> 270 | H61: =ROUNDUP(IFERROR(AI61*(1+$AD$6/100),AI61),0) -> 293 | I61: =ROUNDUP(IFERROR(AJ61*(1+$AD$6/100),AJ61),0) -> 315 | J61: =ROUNDUP(IFERROR(AK61*(1+$AD$6/100),AK61),0) -> 341 | ... U61: =ROUNDUP(IFERROR(AV61*(1+$AD$6/100),AV61),0) -> 593 | V61: N/A | W61: N/A | X61: N/A | AD61: 232 | AE61: 266 | AF61: 296 | AG61: 326 | AH61: 360 | AI61: 390 | AJ61: 420 | AK61: 454 | AL61: 484 | AM61: 514 | AN61: 543 | AO61: 583 | AP61: 613 | AQ61: 642 | AR61: 672 | AS61: 701 | AT61: 731 | AU61: 761 | AV61: 790 | AW61: 0 | AX61: 0 | AY61: 0
B62: 2600 | C62: =ROUNDUP(IFERROR(AD62*(1+$AD$6/100),AD62),0) -> 185 | D62: =ROUNDUP(IFERROR(AE62*(1+$AD$6/100),AE62),0) -> 213 | E62: =ROUNDUP(IFERROR(AF62*(1+$AD$6/100),AF62),0) -> 236 | F62: =ROUNDUP(IFERROR(AG62*(1+$AD$6/100),AG62),0) -> 260 | G62: =ROUNDUP(IFERROR(AH62*(1+$AD$6/100),AH62),0) -> 288 | H62: =ROUNDUP(IFERROR(AI62*(1+$AD$6/100),AI62),0) -> 312 | I62: =ROUNDUP(IFERROR(AJ62*(1+$AD$6/100),AJ62),0) -> 336 | J62: =ROUNDUP(IFERROR(AK62*(1+$AD$6/100),AK62),0) -> 363 | ... S62: =ROUNDUP(IFERROR(AT62*(1+$AD$6/100),AT62),0) -> 585 | T62: N/A | U62: N/A | V62: N/A | W62: N/A | X62: N/A | AD62: 246 | AE62: 283 | AF62: 314 | AG62: 346 | AH62: 383 | AI62: 415 | AJ62: 447 | AK62: 484 | AL62: 516 | AM62: 547 | AN62: 579 | AO62: 621 | AP62: 653 | AQ62: 685 | AR62: 717 | AS62: 748 | AT62: 780 | AU62: 0 | AV62: 0 | AW62: 0 | AX62: 0 | AY62: 0
B63: 2800 | C63: =ROUNDUP(IFERROR(AD63*(1+$AD$6/100),AD63),0) -> 195 | D63: =ROUNDUP(IFERROR(AE63*(1+$AD$6/100),AE63),0) -> 225 | E63: =ROUNDUP(IFERROR(AF63*(1+$AD$6/100),AF63),0) -> 250 | F63: =ROUNDUP(IFERROR(AG63*(1+$AD$6/100),AG63),0) -> 276 | G63: =ROUNDUP(IFERROR(AH63*(1+$AD$6/100),AH63),0) -> 305 | H63: =ROUNDUP(IFERROR(AI63*(1+$AD$6/100),AI63),0) -> 330 | I63: =ROUNDUP(IFERROR(AJ63*(1+$AD$6/100),AJ63),0) -> 356 | J63: =ROUNDUP(IFERROR(AK63*(1+$AD$6/100),AK63),0) -> 385 | ... R63: =ROUNDUP(IFERROR(AS63*(1+$AD$6/100),AS63),0) -> 597 | S63: N/A | T63: N/A | U63: N/A | V63: N/A | W63: N/A | X63: N/A | AD63: 260 | AE63: 299 | AF63: 333 | AG63: 367 | AH63: 406 | AI63: 440 | AJ63: 474 | AK63: 513 | AL63: 547 | AM63: 581 | AN63: 615 | AO63: 660 | AP63: 694 | AQ63: 728 | AR63: 761 | AS63: 795 | AT63: 0 | AU63: 0 | AV63: 0 | AW63: 0 | AX63: 0 | AY63: 0
B64: 3000 | C64: =ROUNDUP(IFERROR(AD64*(1+$AD$6/100),AD64),0) -> 205 | D64: =ROUNDUP(IFERROR(AE64*(1+$AD$6/100),AE64),0) -> 237 | E64: =ROUNDUP(IFERROR(AF64*(1+$AD$6/100),AF64),0) -> 264 | F64: =ROUNDUP(IFERROR(AG64*(1+$AD$6/100),AG64),0) -> 291 | G64: =ROUNDUP(IFERROR(AH64*(1+$AD$6/100),AH64),0) -> 322 | H64: =ROUNDUP(IFERROR(AI64*(1+$AD$6/100),AI64),0) -> 349 | I64: =ROUNDUP(IFERROR(AJ64*(1+$AD$6/100),AJ64),0) -> 376 | J64: =ROUNDUP(IFERROR(AK64*(1+$AD$6/100),AK64),0) -> 408 | ... P64: =ROUNDUP(IFERROR(AQ64*(1+$AD$6/100),AQ64),0) -> 578 | Q64: N/A | R64: N/A | S64: N/A | T64: N/A | U64: N/A | V64: N/A | W64: N/A | X64: N/A | AD64: 273 | AE64: 315 | AF64: 351 | AG64: 387 | AH64: 429 | AI64: 465 | AJ64: 501 | AK64: 543 | AL64: 579 | AM64: 615 | AN64: 651 | AO64: 698 | AP64: 734 | AQ64: 770 | AR64: 0 | AS64: 0 | AT64: 0 | AU64: 0 | AV64: 0 | AW64: 0 | AX64: 0 | AY64: 0
B65: 3200 | C65: =ROUNDUP(IFERROR(AD65*(1+$AD$6/100),AD65),0) -> 216 | D65: =ROUNDUP(IFERROR(AE65*(1+$AD$6/100),AE65),0) -> 249 | E65: =ROUNDUP(IFERROR(AF65*(1+$AD$6/100),AF65),0) -> 277 | F65: =ROUNDUP(IFERROR(AG65*(1+$AD$6/100),AG65),0) -> 306 | G65: =ROUNDUP(IFERROR(AH65*(1+$AD$6/100),AH65),0) -> 339 | H65: =ROUNDUP(IFERROR(AI65*(1+$AD$6/100),AI65),0) -> 368 | I65: =ROUNDUP(IFERROR(AJ65*(1+$AD$6/100),AJ65),0) -> 396 | J65: =ROUNDUP(IFERROR(AK65*(1+$AD$6/100),AK65),0) -> 429 | ... O65: =ROUNDUP(IFERROR(AP65*(1+$AD$6/100),AP65),0) -> 581 | P65: N/A | Q65: N/A | R65: N/A | S65: N/A | T65: N/A | U65: N/A | V65: N/A | W65: N/A | X65: N/A | AD65: 287 | AE65: 331 | AF65: 369 | AG65: 408 | AH65: 452 | AI65: 490 | AJ65: 528 | AK65: 572 | AL65: 610 | AM65: 648 | AN65: 687 | AO65: 736 | AP65: 774 | AQ65: 0 | AR65: 0 | AS65: 0 | AT65: 0 | AU65: 0 | AV65: 0 | AW65: 0 | AX65: 0 | AY65: 0
B68: Basswood 63mm | AD68: 0 | AE68: 0 | AF68: 0 | AG68: 0 | AH68: 0 | AI68: 0 | AJ68: 0 | AK68: 0 | AL68: 0 | AM68: 0 | AN68: 0 | AO68: 0 | AP68: 0 | AQ68: 0 | AR68: 0 | AS68: 0 | AT68: 0 | AU68: 0 | AV68: 0 | AW68: 0 | AX68: 0 | AY68: 0
C69: 610 | D69: 710 | E69: 810 | F69: 910 | G69: 1010 | H69: 1110 | I69: 1210 | J69: 1310 | K69: 1410 | L69: 1510 | M69: 1610 | N69: 1710 | O69: 1810 | P69: 1910 | Q69: 2010 | R69: 2110 | S69: 2210 | T69: 2310 | U69: 2410 | V69: 2510 | W69: 2610 | X69: 2710 | AD69: 610 | AE69: 710 | AF69: 810 | AG69: 910 | AH69: 1010 | AI69: 1110 | AJ69: 1210 | AK69: 1310 | AL69: 1410 | AM69: 1510 | AN69: 1610 | AO69: 1710 | AP69: 1810 | AQ69: 1910 | AR69: 2010 | AS69: 2110 | AT69: 2210 | AU69: 2310 | AV69: 2410 | AW69: 2510 | AX69: 2610 | AY69: 2710
B70: 600 | C70: =ROUNDUP(IFERROR(AD70*(1+$AD$6/100),AD70),0) -> 84 | D70: =ROUNDUP(IFERROR(AE70*(1+$AD$6/100),AE70),0) -> 96 | E70: =ROUNDUP(IFERROR(AF70*(1+$AD$6/100),AF70),0) -> 105 | F70: =ROUNDUP(IFERROR(AG70*(1+$AD$6/100),AG70),0) -> 114 | G70: =ROUNDUP(IFERROR(AH70*(1+$AD$6/100),AH70),0) -> 126 | H70: =ROUNDUP(IFERROR(AI70*(1+$AD$6/100),AI70),0) -> 134 | I70: =ROUNDUP(IFERROR(AJ70*(1+$AD$6/100),AJ70),0) -> 143 | J70: =ROUNDUP(IFERROR(AK70*(1+$AD$6/100),AK70),0) -> 157 | ... X70: =ROUNDUP(IFERROR(AY70*(1+$AD$6/100),AY70),0) -> 282 | AD70: 112 | AE70: 128 | AF70: 139 | AG70: 151 | AH70: 167 | AI70: 178 | AJ70: 190 | AK70: 209 | AL70: 220 | AM70: 232 | AN70: 243 | AO70: 250 | AP70: 265 | AQ70: 276 | AR70: 287 | AS70: 298 | AT70: 309 | AU70: 319 | AV70: 330 | AW70: 344 | AX70: 359 | AY70: 376
B71: 800 | C71: =ROUNDUP(IFERROR(AD71*(1+$AD$6/100),AD71),0) -> 96 | D71: =ROUNDUP(IFERROR(AE71*(1+$AD$6/100),AE71),0) -> 110 | E71: =ROUNDUP(IFERROR(AF71*(1+$AD$6/100),AF71),0) -> 120 | F71: =ROUNDUP(IFERROR(AG71*(1+$AD$6/100),AG71),0) -> 131 | G71: =ROUNDUP(IFERROR(AH71*(1+$AD$6/100),AH71),0) -> 144 | H71: =ROUNDUP(IFERROR(AI71*(1+$AD$6/100),AI71),0) -> 155 | I71: =ROUNDUP(IFERROR(AJ71*(1+$AD$6/100),AJ71),0) -> 165 | J71: =ROUNDUP(IFERROR(AK71*(1+$AD$6/100),AK71),0) -> 172 | ... X71: =ROUNDUP(IFERROR(AY71*(1+$AD$6/100),AY71),0) -> 332 | AD71: 127 | AE71: 146 | AF71: 160 | AG71: 174 | AH71: 192 | AI71: 206 | AJ71: 220 | AK71: 229 | AL71: 242 | AM71: 255 | AN71: 269 | AO71: 291 | AP71: 309 | AQ71: 322 | AR71: 335 | AS71: 348 | AT71: 361 | AU71: 374 | AV71: 387 | AW71: 404 | AX71: 423 | AY71: 442
B72: 1000 | C72: =ROUNDUP(IFERROR(AD72*(1+$AD$6/100),AD72),0) -> 108 | D72: =ROUNDUP(IFERROR(AE72*(1+$AD$6/100),AE72),0) -> 123 | E72: =ROUNDUP(IFERROR(AF72*(1+$AD$6/100),AF72),0) -> 136 | F72: =ROUNDUP(IFERROR(AG72*(1+$AD$6/100),AG72),0) -> 148 | G72: =ROUNDUP(IFERROR(AH72*(1+$AD$6/100),AH72),0) -> 156 | H72: =ROUNDUP(IFERROR(AI72*(1+$AD$6/100),AI72),0) -> 167 | I72: =ROUNDUP(IFERROR(AJ72*(1+$AD$6/100),AJ72),0) -> 178 | J72: =ROUNDUP(IFERROR(AK72*(1+$AD$6/100),AK72),0) -> 196 | ... X72: =ROUNDUP(IFERROR(AY72*(1+$AD$6/100),AY72),0) -> 382 | AD72: 143 | AE72: 164 | AF72: 181 | AG72: 197 | AH72: 207 | AI72: 222 | AJ72: 237 | AK72: 261 | AL72: 276 | AM72: 291 | AN72: 307 | AO72: 331 | AP72: 352 | AQ72: 367 | AR72: 383 | AS72: 398 | AT72: 413 | AU72: 429 | AV72: 444 | AW72: 464 | AX72: 486 | AY72: 509
B73: 1200 | C73: =ROUNDUP(IFERROR(AD73*(1+$AD$6/100),AD73),0) -> 120 | D73: =ROUNDUP(IFERROR(AE73*(1+$AD$6/100),AE73),0) -> 137 | E73: =ROUNDUP(IFERROR(AF73*(1+$AD$6/100),AF73),0) -> 151 | F73: =ROUNDUP(IFERROR(AG73*(1+$AD$6/100),AG73),0) -> 156 | G73: =ROUNDUP(IFERROR(AH73*(1+$AD$6/100),AH73),0) -> 174 | H73: =ROUNDUP(IFERROR(AI73*(1+$AD$6/100),AI73),0) -> 187 | I73: =ROUNDUP(IFERROR(AJ73*(1+$AD$6/100),AJ73),0) -> 200 | J73: =ROUNDUP(IFERROR(AK73*(1+$AD$6/100),AK73),0) -> 219 | ... X73: =ROUNDUP(IFERROR(AY73*(1+$AD$6/100),AY73),0) -> 432 | AD73: 159 | AE73: 182 | AF73: 201 | AG73: 208 | AH73: 231 | AI73: 249 | AJ73: 266 | AK73: 292 | AL73: 310 | AM73: 327 | AN73: 345 | AO73: 372 | AP73: 395 | AQ73: 413 | AR73: 430 | AS73: 448 | AT73: 466 | AU73: 484 | AV73: 501 | AW73: 524 | AX73: 549 | AY73: 576
B74: 1400 | C74: =ROUNDUP(IFERROR(AD74*(1+$AD$6/100),AD74),0) -> 131 | D74: =ROUNDUP(IFERROR(AE74*(1+$AD$6/100),AE74),0) -> 151 | E74: =ROUNDUP(IFERROR(AF74*(1+$AD$6/100),AF74),0) -> 158 | F74: =ROUNDUP(IFERROR(AG74*(1+$AD$6/100),AG74),0) -> 173 | G74: =ROUNDUP(IFERROR(AH74*(1+$AD$6/100),AH74),0) -> 192 | H74: =ROUNDUP(IFERROR(AI74*(1+$AD$6/100),AI74),0) -> 207 | I74: =ROUNDUP(IFERROR(AJ74*(1+$AD$6/100),AJ74),0) -> 222 | J74: =ROUNDUP(IFERROR(AK74*(1+$AD$6/100),AK74),0) -> 243 | ... X74: =ROUNDUP(IFERROR(AY74*(1+$AD$6/100),AY74),0) -> 482 | AD74: 174 | AE74: 201 | AF74: 210 | AG74: 230 | AH74: 255 | AI74: 275 | AJ74: 295 | AK74: 323 | AL74: 343 | AM74: 363 | AN74: 383 | AO74: 413 | AP74: 438 | AQ74: 458 | AR74: 478 | AS74: 498 | AT74: 518 | AU74: 538 | AV74: 558 | AW74: 584 | AX74: 612 | AY74: 642
B75: 1600 | C75: =ROUNDUP(IFERROR(AD75*(1+$AD$6/100),AD75),0) -> 143 | D75: =ROUNDUP(IFERROR(AE75*(1+$AD$6/100),AE75),0) -> 156 | E75: =ROUNDUP(IFERROR(AF75*(1+$AD$6/100),AF75),0) -> 173 | F75: =ROUNDUP(IFERROR(AG75*(1+$AD$6/100),AG75),0) -> 189 | G75: =ROUNDUP(IFERROR(AH75*(1+$AD$6/100),AH75),0) -> 210 | H75: =ROUNDUP(IFERROR(AI75*(1+$AD$6/100),AI75),0) -> 227 | I75: =ROUNDUP(IFERROR(AJ75*(1+$AD$6/100),AJ75),0) -> 243 | J75: =ROUNDUP(IFERROR(AK75*(1+$AD$6/100),AK75),0) -> 267 | ... X75: =ROUNDUP(IFERROR(AY75*(1+$AD$6/100),AY75),0) -> 532 | AD75: 190 | AE75: 207 | AF75: 230 | AG75: 252 | AH75: 279 | AI75: 302 | AJ75: 324 | AK75: 355 | AL75: 377 | AM75: 399 | AN75: 422 | AO75: 454 | AP75: 481 | AQ75: 504 | AR75: 526 | AS75: 548 | AT75: 571 | AU75: 593 | AV75: 615 | AW75: 644 | AX75: 676 | AY75: 709
B76: 1800 | C76: =ROUNDUP(IFERROR(AD76*(1+$AD$6/100),AD76),0) -> 149 | D76: =ROUNDUP(IFERROR(AE76*(1+$AD$6/100),AE76),0) -> 171 | E76: =ROUNDUP(IFERROR(AF76*(1+$AD$6/100),AF76),0) -> 189 | F76: =ROUNDUP(IFERROR(AG76*(1+$AD$6/100),AG76),0) -> 208 | G76: =ROUNDUP(IFERROR(AH76*(1+$AD$6/100),AH76),0) -> 231 | H76: =ROUNDUP(IFERROR(AI76*(1+$AD$6/100),AI76),0) -> 249 | I76: =ROUNDUP(IFERROR(AJ76*(1+$AD$6/100),AJ76),0) -> 267 | J76: =ROUNDUP(IFERROR(AK76*(1+$AD$6/100),AK76),0) -> 290 | ... X76: =ROUNDUP(IFERROR(AY76*(1+$AD$6/100),AY76),0) -> 582 | AD76: 198 | AE76: 228 | AF76: 252 | AG76: 277 | AH76: 307 | AI76: 332 | AJ76: 356 | AK76: 386 | AL76: 411 | AM76: 435 | AN76: 460 | AO76: 495 | AP76: 524 | AQ76: 549 | AR76: 574 | AS76: 598 | AT76: 623 | AU76: 648 | AV76: 672 | AW76: 704 | AX76: 739 | AY76: 776
B77: 2000 | C77: =ROUNDUP(IFERROR(AD77*(1+$AD$6/100),AD77),0) -> 160 | D77: =ROUNDUP(IFERROR(AE77*(1+$AD$6/100),AE77),0) -> 184 | E77: =ROUNDUP(IFERROR(AF77*(1+$AD$6/100),AF77),0) -> 204 | F77: =ROUNDUP(IFERROR(AG77*(1+$AD$6/100),AG77),0) -> 225 | G77: =ROUNDUP(IFERROR(AH77*(1+$AD$6/100),AH77),0) -> 249 | H77: =ROUNDUP(IFERROR(AI77*(1+$AD$6/100),AI77),0) -> 269 | I77: =ROUNDUP(IFERROR(AJ77*(1+$AD$6/100),AJ77),0) -> 289 | J77: =ROUNDUP(IFERROR(AK77*(1+$AD$6/100),AK77),0) -> 313 | ... X77: =ROUNDUP(IFERROR(AY77*(1+$AD$6/100),AY77),0) -> 632 | AD77: 213 | AE77: 245 | AF77: 272 | AG77: 299 | AH77: 331 | AI77: 358 | AJ77: 385 | AK77: 417 | AL77: 444 | AM77: 471 | AN77: 498 | AO77: 536 | AP77: 568 | AQ77: 595 | AR77: 622 | AS77: 648 | AT77: 675 | AU77: 702 | AV77: 729 | AW77: 764 | AX77: 802 | AY77: 842
B78: 2200 | C78: =ROUNDUP(IFERROR(AD78*(1+$AD$6/100),AD78),0) -> 171 | D78: =ROUNDUP(IFERROR(AE78*(1+$AD$6/100),AE78),0) -> 197 | E78: =ROUNDUP(IFERROR(AF78*(1+$AD$6/100),AF78),0) -> 219 | F78: =ROUNDUP(IFERROR(AG78*(1+$AD$6/100),AG78),0) -> 241 | G78: =ROUNDUP(IFERROR(AH78*(1+$AD$6/100),AH78),0) -> 267 | H78: =ROUNDUP(IFERROR(AI78*(1+$AD$6/100),AI78),0) -> 289 | I78: =ROUNDUP(IFERROR(AJ78*(1+$AD$6/100),AJ78),0) -> 311 | J78: =ROUNDUP(IFERROR(AK78*(1+$AD$6/100),AK78),0) -> 337 | ... X78: =ROUNDUP(IFERROR(AY78*(1+$AD$6/100),AY78),0) -> 682 | AD78: 228 | AE78: 262 | AF78: 292 | AG78: 321 | AH78: 356 | AI78: 385 | AJ78: 414 | AK78: 449 | AL78: 478 | AM78: 507 | AN78: 537 | AO78: 577 | AP78: 611 | AQ78: 640 | AR78: 669 | AS78: 699 | AT78: 728 | AU78: 757 | AV78: 786 | AW78: 824 | AX78: 865 | AY78: 909
B79: 2400 | C79: =ROUNDUP(IFERROR(AD79*(1+$AD$6/100),AD79),0) -> 186 | D79: =ROUNDUP(IFERROR(AE79*(1+$AD$6/100),AE79),0) -> 213 | E79: =ROUNDUP(IFERROR(AF79*(1+$AD$6/100),AF79),0) -> 237 | F79: =ROUNDUP(IFERROR(AG79*(1+$AD$6/100),AG79),0) -> 261 | G79: =ROUNDUP(IFERROR(AH79*(1+$AD$6/100),AH79),0) -> 289 | H79: =ROUNDUP(IFERROR(AI79*(1+$AD$6/100),AI79),0) -> 312 | I79: =ROUNDUP(IFERROR(AJ79*(1+$AD$6/100),AJ79),0) -> 336 | J79: =ROUNDUP(IFERROR(AK79*(1+$AD$6/100),AK79),0) -> 364 | ... U79: =ROUNDUP(IFERROR(AV79*(1+$AD$6/100),AV79),0) -> 633 | V79: N/A | W79: N/A | X79: N/A | AD79: 247 | AE79: 284 | AF79: 316 | AG79: 347 | AH79: 385 | AI79: 416 | AJ79: 448 | AK79: 485 | AL79: 517 | AM79: 548 | AN79: 580 | AO79: 622 | AP79: 654 | AQ79: 686 | AR79: 717 | AS79: 749 | AT79: 780 | AU79: 812 | AV79: 843 | AW79: 0 | AX79: 0 | AY79: 0
B80: 2600 | C80: =ROUNDUP(IFERROR(AD80*(1+$AD$6/100),AD80),0) -> 197 | D80: =ROUNDUP(IFERROR(AE80*(1+$AD$6/100),AE80),0) -> 227 | E80: =ROUNDUP(IFERROR(AF80*(1+$AD$6/100),AF80),0) -> 252 | F80: =ROUNDUP(IFERROR(AG80*(1+$AD$6/100),AG80),0) -> 277 | G80: =ROUNDUP(IFERROR(AH80*(1+$AD$6/100),AH80),0) -> 307 | H80: =ROUNDUP(IFERROR(AI80*(1+$AD$6/100),AI80),0) -> 333 | I80: =ROUNDUP(IFERROR(AJ80*(1+$AD$6/100),AJ80),0) -> 358 | J80: =ROUNDUP(IFERROR(AK80*(1+$AD$6/100),AK80),0) -> 387 | ... S80: =ROUNDUP(IFERROR(AT80*(1+$AD$6/100),AT80),0) -> 625 | T80: N/A | U80: N/A | V80: N/A | W80: N/A | X80: N/A | AD80: 262 | AE80: 302 | AF80: 336 | AG80: 369 | AH80: 409 | AI80: 443 | AJ80: 477 | AK80: 516 | AL80: 550 | AM80: 584 | AN80: 618 | AO80: 663 | AP80: 697 | AQ80: 731 | AR80: 765 | AS80: 799 | AT80: 833 | AU80: 0 | AV80: 0 | AW80: 0 | AX80: 0 | AY80: 0
B81: 2800 | C81: =ROUNDUP(IFERROR(AD81*(1+$AD$6/100),AD81),0) -> 208 | D81: =ROUNDUP(IFERROR(AE81*(1+$AD$6/100),AE81),0) -> 240 | E81: =ROUNDUP(IFERROR(AF81*(1+$AD$6/100),AF81),0) -> 267 | F81: =ROUNDUP(IFERROR(AG81*(1+$AD$6/100),AG81),0) -> 294 | G81: =ROUNDUP(IFERROR(AH81*(1+$AD$6/100),AH81),0) -> 325 | H81: =ROUNDUP(IFERROR(AI81*(1+$AD$6/100),AI81),0) -> 352 | I81: =ROUNDUP(IFERROR(AJ81*(1+$AD$6/100),AJ81),0) -> 380 | J81: =ROUNDUP(IFERROR(AK81*(1+$AD$6/100),AK81),0) -> 411 | ... R81: =ROUNDUP(IFERROR(AS81*(1+$AD$6/100),AS81),0) -> 637 | S81: N/A | T81: N/A | U81: N/A | V81: N/A | W81: N/A | X81: N/A | AD81: 277 | AE81: 319 | AF81: 355 | AG81: 391 | AH81: 433 | AI81: 469 | AJ81: 506 | AK81: 548 | AL81: 584 | AM81: 620 | AN81: 656 | AO81: 704 | AP81: 740 | AQ81: 776 | AR81: 813 | AS81: 849 | AT81: 0 | AU81: 0 | AV81: 0 | AW81: 0 | AX81: 0 | AY81: 0
B82: 3000 | C82: =ROUNDUP(IFERROR(AD82*(1+$AD$6/100),AD82),0) -> 219 | D82: =ROUNDUP(IFERROR(AE82*(1+$AD$6/100),AE82),0) -> 252 | E82: =ROUNDUP(IFERROR(AF82*(1+$AD$6/100),AF82),0) -> 282 | F82: =ROUNDUP(IFERROR(AG82*(1+$AD$6/100),AG82),0) -> 310 | G82: =ROUNDUP(IFERROR(AH82*(1+$AD$6/100),AH82),0) -> 344 | H82: =ROUNDUP(IFERROR(AI82*(1+$AD$6/100),AI82),0) -> 372 | I82: =ROUNDUP(IFERROR(AJ82*(1+$AD$6/100),AJ82),0) -> 402 | J82: =ROUNDUP(IFERROR(AK82*(1+$AD$6/100),AK82),0) -> 435 | ... P82: =ROUNDUP(IFERROR(AQ82*(1+$AD$6/100),AQ82),0) -> 617 | Q82: N/A | R82: N/A | S82: N/A | T82: N/A | U82: N/A | V82: N/A | W82: N/A | X82: N/A | AD82: 292 | AE82: 336 | AF82: 375 | AG82: 413 | AH82: 458 | AI82: 496 | AJ82: 535 | AK82: 579 | AL82: 618 | AM82: 656 | AN82: 695 | AO82: 745 | AP82: 783 | AQ82: 822 | AR82: 0 | AS82: 0 | AT82: 0 | AU82: 0 | AV82: 0 | AW82: 0 | AX82: 0 | AY82: 0
B83: 3200 | C83: =ROUNDUP(IFERROR(AD83*(1+$AD$6/100),AD83),0) -> 231 | D83: =ROUNDUP(IFERROR(AE83*(1+$AD$6/100),AE83),0) -> 265 | E83: =ROUNDUP(IFERROR(AF83*(1+$AD$6/100),AF83),0) -> 296 | F83: =ROUNDUP(IFERROR(AG83*(1+$AD$6/100),AG83),0) -> 327 | G83: =ROUNDUP(IFERROR(AH83*(1+$AD$6/100),AH83),0) -> 362 | H83: =ROUNDUP(IFERROR(AI83*(1+$AD$6/100),AI83),0) -> 393 | I83: =ROUNDUP(IFERROR(AJ83*(1+$AD$6/100),AJ83),0) -> 423 | J83: =ROUNDUP(IFERROR(AK83*(1+$AD$6/100),AK83),0) -> 458 | ... O83: =ROUNDUP(IFERROR(AP83*(1+$AD$6/100),AP83),0) -> 621 | P83: N/A | Q83: N/A | R83: N/A | S83: N/A | T83: N/A | U83: N/A | V83: N/A | W83: N/A | X83: N/A | AD83: 307 | AE83: 353 | AF83: 394 | AG83: 435 | AH83: 482 | AI83: 523 | AJ83: 564 | AK83: 610 | AL83: 651 | AM83: 692 | AN83: 733 | AO83: 786 | AP83: 827 | AQ83: 0 | AR83: 0 | AS83: 0 | AT83: 0 | AU83: 0 | AV83: 0 | AW83: 0 | AX83: 0 | AY83: 0
B85: Available in sizes up to 2710mm for Ultra White and Pure White, and up to 2410mm for Cascade, Walnut, and Cherry Blossom
B86: Standard Warranty is 3 Years
B87: All prices are subject to 10% GST. Prices subject to change without notice. All prices subject to CW Systems’ General Terms & Conditions - Prices do not include any applicable shipping/handling fees
B88: Page 2 of 3 | AD88: 0 | AE88: 0 | AF88: 0 | AG88: 0 | AH88: 0 | AI88: 0 | AJ88: 0 | AK88: 0 | AL88: 0 | AM88: 0 | AN88: 0 | AO88: 0 | AP88: 0 | AQ88: 0 | AR88: 0 | AS88: 0 | AT88: 0 | AU88: 0 | AV88: 0 | AW88: 0 | AX88: 0 | AY88: 0
B89: Aluminium
A90: Aluminium 25mm
B91: 610 | C91: 710 | D91: 810 | E91: 910 | F91: 1010 | G91: 1110 | H91: 1210 | I91: 1310 | J91: 1410 | K91: 1510 | L91: 1610 | M91: 1710 | N91: 1810 | O91: 1910 | P91: 2010 | Q91: 2110 | R91: 2210 | S91: 2310 | T91: 2410 | U91: 2510 | V91: 2610 | W91: 2710 | X91: 2810 | Y91: 2910 | Z91: 3010
A92: 600 | B92: =ROUNDUP(IFERROR(AC92*(1+$AD$6/100),AC92),0) -> 35 | C92: =ROUNDUP(IFERROR(AD92*(1+$AD$6/100),AD92),0) -> 38 | D92: =ROUNDUP(IFERROR(AE92*(1+$AD$6/100),AE92),0) -> 42 | E92: =ROUNDUP(IFERROR(AF92*(1+$AD$6/100),AF92),0) -> 46 | F92: =ROUNDUP(IFERROR(AG92*(1+$AD$6/100),AG92),0) -> 50 | G92: =ROUNDUP(IFERROR(AH92*(1+$AD$6/100),AH92),0) -> 54 | H92: =ROUNDUP(IFERROR(AI92*(1+$AD$6/100),AI92),0) -> 57 | I92: =ROUNDUP(IFERROR(AJ92*(1+$AD$6/100),AJ92),0) -> 61 | ... Z92: =ROUNDUP(IFERROR(BA92*(1+$AD$6/100),BA92),0) -> 118 | AA92: 600 | AC92: 46 | AD92: 50 | AE92: 56 | AF92: 61 | AG92: 66 | AH92: 71 | AI92: 76 | AJ92: 81 | AK92: 87 | AL92: 91 | AM92: 96 | AN92: 96 | AO92: 101 | AP92: 106 | AQ92: 111 | AR92: 115 | AS92: 120 | AT92: 124 | AU92: 129 | AV92: 134 | AW92: 138 | AX92: 143 | AY92: 147 | AZ92: 152 | BA92: 157
A93: 800 | B93: =ROUNDUP(IFERROR(AC93*(1+$AD$6/100),AC93),0) -> 40 | C93: =ROUNDUP(IFERROR(AD93*(1+$AD$6/100),AD93),0) -> 45 | D93: =ROUNDUP(IFERROR(AE93*(1+$AD$6/100),AE93),0) -> 50 | E93: =ROUNDUP(IFERROR(AF93*(1+$AD$6/100),AF93),0) -> 54 | F93: =ROUNDUP(IFERROR(AG93*(1+$AD$6/100),AG93),0) -> 60 | G93: =ROUNDUP(IFERROR(AH93*(1+$AD$6/100),AH93),0) -> 64 | H93: =ROUNDUP(IFERROR(AI93*(1+$AD$6/100),AI93),0) -> 69 | I93: =ROUNDUP(IFERROR(AJ93*(1+$AD$6/100),AJ93),0) -> 69 | ... Z93: =ROUNDUP(IFERROR(BA93*(1+$AD$6/100),BA93),0) -> 144 | AA93: 800 | AC93: 53 | AD93: 59 | AE93: 66 | AF93: 72 | AG93: 79 | AH93: 85 | AI93: 91 | AJ93: 92 | AK93: 98 | AL93: 104 | AM93: 110 | AN93: 115 | AO93: 121 | AP93: 128 | AQ93: 133 | AR93: 139 | AS93: 145 | AT93: 151 | AU93: 156 | AV93: 162 | AW93: 168 | AX93: 173 | AY93: 179 | AZ93: 185 | BA93: 191
A94: 1000 | B94: =ROUNDUP(IFERROR(AC94*(1+$AD$6/100),AC94),0) -> 45 | C94: =ROUNDUP(IFERROR(AD94*(1+$AD$6/100),AD94),0) -> 51 | D94: =ROUNDUP(IFERROR(AE94*(1+$AD$6/100),AE94),0) -> 57 | E94: =ROUNDUP(IFERROR(AF94*(1+$AD$6/100),AF94),0) -> 63 | F94: =ROUNDUP(IFERROR(AG94*(1+$AD$6/100),AG94),0) -> 65 | G94: =ROUNDUP(IFERROR(AH94*(1+$AD$6/100),AH94),0) -> 70 | H94: =ROUNDUP(IFERROR(AI94*(1+$AD$6/100),AI94),0) -> 75 | I94: =ROUNDUP(IFERROR(AJ94*(1+$AD$6/100),AJ94),0) -> 81 | ... Z94: =ROUNDUP(IFERROR(BA94*(1+$AD$6/100),BA94),0) -> 169 | AA94: 1000 | AC94: 60 | AD94: 68 | AE94: 76 | AF94: 83 | AG94: 86 | AH94: 93 | AI94: 100 | AJ94: 107 | AK94: 114 | AL94: 121 | AM94: 128 | AN94: 135 | AO94: 142 | AP94: 149 | AQ94: 156 | AR94: 163 | AS94: 170 | AT94: 177 | AU94: 184 | AV94: 190 | AW94: 197 | AX94: 204 | AY94: 211 | AZ94: 218 | BA94: 225
A95: 1200 | B95: =ROUNDUP(IFERROR(AC95*(1+$AD$6/100),AC95),0) -> 51 | C95: =ROUNDUP(IFERROR(AD95*(1+$AD$6/100),AD95),0) -> 57 | D95: =ROUNDUP(IFERROR(AE95*(1+$AD$6/100),AE95),0) -> 64 | E95: =ROUNDUP(IFERROR(AF95*(1+$AD$6/100),AF95),0) -> 67 | F95: =ROUNDUP(IFERROR(AG95*(1+$AD$6/100),AG95),0) -> 74 | G95: =ROUNDUP(IFERROR(AH95*(1+$AD$6/100),AH95),0) -> 80 | H95: =ROUNDUP(IFERROR(AI95*(1+$AD$6/100),AI95),0) -> 86 | I95: =ROUNDUP(IFERROR(AJ95*(1+$AD$6/100),AJ95),0) -> 92 | ... Z95: =ROUNDUP(IFERROR(BA95*(1+$AD$6/100),BA95),0) -> 195 | AA95: 1200 | AC95: 68 | AD95: 76 | AE95: 85 | AF95: 89 | AG95: 98 | AH95: 106 | AI95: 114 | AJ95: 122 | AK95: 130 | AL95: 138 | AM95: 146 | AN95: 154 | AO95: 162 | AP95: 171 | AQ95: 179 | AR95: 187 | AS95: 195 | AT95: 203 | AU95: 211 | AV95: 219 | AW95: 227 | AX95: 235 | AY95: 243 | AZ95: 251 | BA95: 259
A96: 1400 | B96: =ROUNDUP(IFERROR(AC96*(1+$AD$6/100),AC96),0) -> 57 | C96: =ROUNDUP(IFERROR(AD96*(1+$AD$6/100),AD96),0) -> 64 | D96: =ROUNDUP(IFERROR(AE96*(1+$AD$6/100),AE96),0) -> 68 | E96: =ROUNDUP(IFERROR(AF96*(1+$AD$6/100),AF96),0) -> 75 | F96: =ROUNDUP(IFERROR(AG96*(1+$AD$6/100),AG96),0) -> 82 | G96: =ROUNDUP(IFERROR(AH96*(1+$AD$6/100),AH96),0) -> 89 | H96: =ROUNDUP(IFERROR(AI96*(1+$AD$6/100),AI96),0) -> 96 | I96: =ROUNDUP(IFERROR(AJ96*(1+$AD$6/100),AJ96),0) -> 102 | ... Z96: =ROUNDUP(IFERROR(BA96*(1+$AD$6/100),BA96),0) -> 220 | AA96: 1400 | AC96: 75 | AD96: 85 | AE96: 90 | AF96: 99 | AG96: 109 | AH96: 118 | AI96: 127 | AJ96: 136 | AK96: 146 | AL96: 155 | AM96: 164 | AN96: 173 | AO96: 183 | AP96: 193 | AQ96: 202 | AR96: 211 | AS96: 220 | AT96: 229 | AU96: 238 | AV96: 247 | AW96: 256 | AX96: 265 | AY96: 274 | AZ96: 284 | BA96: 293
A97: 1600 | B97: =ROUNDUP(IFERROR(AC97*(1+$AD$6/100),AC97),0) -> 63 | C97: =ROUNDUP(IFERROR(AD97*(1+$AD$6/100),AD97),0) -> 67 | D97: =ROUNDUP(IFERROR(AE97*(1+$AD$6/100),AE97),0) -> 75 | E97: =ROUNDUP(IFERROR(AF97*(1+$AD$6/100),AF97),0) -> 83 | F97: =ROUNDUP(IFERROR(AG97*(1+$AD$6/100),AG97),0) -> 91 | G97: =ROUNDUP(IFERROR(AH97*(1+$AD$6/100),AH97),0) -> 99 | H97: =ROUNDUP(IFERROR(AI97*(1+$AD$6/100),AI97),0) -> 106 | I97: =ROUNDUP(IFERROR(AJ97*(1+$AD$6/100),AJ97),0) -> 114 | ... Z97: =ROUNDUP(IFERROR(BA97*(1+$AD$6/100),BA97),0) -> 246 | AA97: 1600 | AC97: 83 | AD97: 89 | AE97: 99 | AF97: 110 | AG97: 121 | AH97: 131 | AI97: 141 | AJ97: 151 | AK97: 162 | AL97: 173 | AM97: 183 | AN97: 193 | AO97: 203 | AP97: 215 | AQ97: 225 | AR97: 235 | AS97: 245 | AT97: 255 | AU97: 265 | AV97: 276 | AW97: 286 | AX97: 296 | AY97: 306 | AZ97: 316 | BA97: 327
A98: 1800 | B98: =ROUNDUP(IFERROR(AC98*(1+$AD$6/100),AC98),0) -> 65 | C98: =ROUNDUP(IFERROR(AD98*(1+$AD$6/100),AD98),0) -> 73 | D98: =ROUNDUP(IFERROR(AE98*(1+$AD$6/100),AE98),0) -> 82 | E98: =ROUNDUP(IFERROR(AF98*(1+$AD$6/100),AF98),0) -> 90 | F98: =ROUNDUP(IFERROR(AG98*(1+$AD$6/100),AG98),0) -> 99 | G98: =ROUNDUP(IFERROR(AH98*(1+$AD$6/100),AH98),0) -> 108 | H98: =ROUNDUP(IFERROR(AI98*(1+$AD$6/100),AI98),0) -> 117 | I98: =ROUNDUP(IFERROR(AJ98*(1+$AD$6/100),AJ98),0) -> 125 | ... Z98: =ROUNDUP(IFERROR(BA98*(1+$AD$6/100),BA98),0) -> 271 | AA98: 1800 | AC98: 86 | AD98: 97 | AE98: 109 | AF98: 120 | AG98: 132 | AH98: 144 | AI98: 155 | AJ98: 166 | AK98: 178 | AL98: 190 | AM98: 201 | AN98: 212 | AO98: 224 | AP98: 236 | AQ98: 248 | AR98: 259 | AS98: 270 | AT98: 282 | AU98: 293 | AV98: 304 | AW98: 315 | AX98: 327 | AY98: 338 | AZ98: 349 | BA98: 361
